Workbook
Name IQ_CH: 110000
Name IQ_CQ: 5000
Name IQ_CY: 10000
Name IQ_DAILY: 500000
Name IQ_FH: 100000
Name IQ_FQ: 500
Name IQ_FY: 1000
Name IQ_LTM: 2000
Name IQ_MONTH: 15000
Name IQ_NTM: 6000
Name IQ_WEEK: 50000
Name IQ_YTD: 3000

Sheet Data
A1: End Date | B1: 45973
A2: Span | B2: 5
A3: Start Date | B3: 44147
A4: Frequency | B4: M
B5: ConocoPhillips | C5: Exxon Mobil Corporation | D5: Chevron Corporation | E5: EOG Resources, Inc. | F5: BP p.l.c. | G5: Devon Energy Corporation | H5: PE-From Ifind | N5: EV/EBITDA-From Ifind | T5: PB | Z5: PS | AF5: Oil Price | AG5: Copper-Price Per Pound | AH5: Energy Sector Index | AI5: SPX | AJ5: Market Cap in Million | AP5: EV without Cash in Million
B6: COP | C6: XOM | D6: CVX | E6: EOG | F6: BP | G6: DVN | H6: COP | I6: XOM | J6: CVX | K6: EOG | L6: BP | M6: DVN | N6: COP | O6: XOM | P6: CVX | Q6: EOG | R6: BP | S6: DVN | T6: COP | U6: XOM | V6: CVX | W6: EOG | X6: BP | Y6: DVN | Z6: COP | AA6: XOM | AB6: CVX | AC6: EOG | AD6: BP | AE6: DVN | AF6: ^cl | AG6: ^HG | AH6: ^SP500-10 | AI6: IQT46156516 | AJ6: COP | AK6: XOM | AL6: CVX | AM6: EOG | AN6: BP | AO6: DVN | AP6: COP | AQ6: XOM | AR6: CVX | AS6: EOG | AT6: BP | AU6: DVN
A7: IQ_PRICEDATE | B7: IQ_CLOSEPRICE_ADJ | AF7: IQ_Closeprice | AG7: IQ_Closeprice | AH7: IQ_Closeprice | AI7: IQ_Closeprice
A8: IQ_PRICEDATE | B8: IQ_CLOSEPRICE_ADJ | C8: IQ_CLOSEPRICE_ADJ | D8: IQ_CLOSEPRICE_ADJ | E8: IQ_CLOSEPRICE_ADJ | F8: IQ_CLOSEPRICE_ADJ | G8: IQ_CLOSEPRICE_ADJ | AF8: IQ_Closeprice | AG8: IQ_Closeprice | AH8: IQ_Closeprice | AI8: IQ_Closeprice
A9: 45961 | B9: 88.86 | C9: 113.36841 | D9: 157.72 | E9: 105.84 | F9: 34.65422 | G9: 32.49 | H9: 12.413059 | I9: 16.10106 | J9: 24.872543 | K9: 10.384922 | L9: 60.486287 | M9: 7.495762 | N9: 5.5016082 | O9: 7.0835763 | P9: 7.9742035 | Q9: 4.9416416 | R9: 4.8598349 | S9: 3.7508836 | T9: 1.6913255 | U9: 1.8509104 | V9: 1.6728172 | W9: 1.8962728 | X9: 1.5764402 | Y9: 1.3277509 | Z9: 1.7682113 | AA9: 1.4467268 | AB9: 1.6337385 | AC9: 2.5434528 | AD9: 0.47600085 | AE9: 1.1666272 | AF9: 60.98 | AG9: 5.089 | AH9: 674.73686 | AI9: 13085.098 | AJ9: 109805.92 | AK9: 482275.06 | AL9: 317572.63 | AM9: 57428.621 | AN9: 91818.183 | AO9: 20380.977 | AP9: 128027.92 | AQ9: 519304.06 | AR9: 357148.63 | AS9: 61592.621 | AT9: 136498.18 | AU9: 27493.977
A10: 45930 | B10: 94.59 | C10: 111.77237 | D10: 155.29 | E10: 111.05368 | F10: 33.99329 | G10: 35.06 | H10: 13.213496 | I10: 15.874384 | J10: 24.48933 | K10: 11.025176 | L10: 59.656111 | M10: 8.1106068 | N10: 5.8058781 | O10: 6.9909621 | P10: 7.8649587 | Q10: 5.2257081 | R10: 4.8149669 | S10: 3.978955 | T10: 1.800388 | U10: 1.8248526 | V10: 1.647044 | W10: 2.0131823 | X10: 1.5548035 | Y10: 1.4366606 | Z10: 1.8822317 | AA10: 1.4263593 | AB10: 1.6085674 | AC10: 2.7002624 | AD10: 0.46946772 | AE10: 1.2623205 | AF10: 61.96 | AG10: 4.8565 | AH10: 682.82225 | AI10: 12788.463 | AJ10: 116886.59 | AK10: 475485.42 | AL10: 312679.77 | AM10: 60969.226 | AN10: 90557.976 | AO10: 22052.74 | AP10: 135108.59 | AQ10: 512514.42 | AR10: 352255.77 | AS10: 65133.226 | AT10: 135237.98 | AU10: 29165.74
A11: 45898 | B11: 98.97 | C11: 113.29902 | D11: 160.6 | E11: 123.6329 | F11: 34.75287 | G11: 35.85082 | H11: 13.457574 | I11: 15.710027 | J11: 20.232958 | K11: 11.88955 | L11: 164.9248 | M11: 8.0577637 | N11: 6.112149 | O11: 7.082873 | P11: 6.7822241 | Q11: 5.3891927 | R11: 4.9372187 | S11: 4.1292333 | T11: 1.8850702 | U11: 1.8555198 | V11: 1.8953759 | W11: 2.3309015 | X11: 1.5673981 | Y11: 1.5216653 | Z11: 2.0539002 | AA11: 1.4412251 | AB11: 1.4207726 | AC11: 3.002639 | AD11: 0.48367059 | AE11: 1.3352141 | AF11: 64.01 | AG11: 4.5185 | AH11: 686.39366 | AI11: 12342.326 | AJ11: 123607.82 | AK11: 487246.5 | AL11: 277515.25 | AM11: 68150.898 | AN11: 92852.662 | AO11: 22916.28 | AP11: 142235.82 | AQ11: 519252.5 | AR11: 303762.25 | AS11: 67170.898 | AT11: 138671.66 | AU11: 30267.28
A12: 45869 | B12: 94.55992 | C12: 109.65165 | D12: 149.97052 | E12: 118.87855 | F12: 31.26212 | G12: 32.9907 | H12: 12.96398 | I12: 15.345765 | J12: 19.104146 | K12: 11.432332 | L12: 150.50617 | M12: 7.4149283 | N12: 5.9173289 | O12: 6.9287678 | P12: 6.4365335 | Q12: 5.1789257 | R12: 4.6481992 | S12: 3.8798166 | T12: 1.81593 | U12: 1.8124965 | V12: 1.7896314 | W12: 2.2412658 | X12: 1.4303675 | Y12: 1.4002693 | Z12: 1.9785677 | AA12: 1.407808 | AB12: 1.3415066 | AC12: 2.8871714 | AD12: 0.44138545 | AE12: 1.2286929 | AF12: 69.26 | AG12: 4.3545 | AH12: 666.90745 | AI12: 12101.39 | AJ12: 119074.16 | AK12: 475948.9 | AL12: 262032.46 | AM12: 65530.13 | AN12: 84734.972 | AO12: 21088.056 | AP12: 137702.16 | AQ12: 507954.9 | AR12: 288279.46 | AS12: 64550.13 | AT12: 130553.97 | AU12: 28439.056
A13: 45838 | B13: 89.00574 | C13: 105.88004 | D13: 141.61355 | E13: 117.50014 | F13: 29.10342 | G13: 31.59043 | H13: 12.202513 | I13: 14.817928 | J13: 18.039585 | K13: 11.393207 | L13: 140.88483 | M13: 7.1136287 | N13: 5.6167798 | O13: 6.7054607 | P13: 6.1105194 | Q13: 5.1609325 | R13: 4.4553409 | S13: 3.7629141 | T13: 1.7092674 | U13: 1.7501534 | V13: 1.6899058 | W13: 2.2335954 | X13: 1.3389291 | Y13: 1.3433705 | Z13: 1.8623522 | AA13: 1.3593846 | AB13: 1.2667524 | AC13: 2.8772905 | AD13: 0.41316921 | AE13: 1.178766 | AF13: 65.11 | AG13: 5.0825 | AH13: 648.68124 | AI13: 11838.458 | AJ13: 112080.08 | AK13: 459578.03 | AL13: 247430.94 | AM13: 65305.862 | AN13: 79318.159 | AO13: 20231.16 | AP13: 130708.08 | AQ13: 491584.03 | AR13: 273677.94 | AS13: 64325.862 | AT13: 125137.16 | AU13: 27582.16
A14: 45807 | B14: 84.65166 | C14: 100.47799 | D14: 135.195 | E14: 106.65488 | F14: 28.29635 | G14: 29.84104 | H14: 11.290652 | I14: 13.290207 | J14: 15.244703 | K14: 9.7508797 | L14: -64.707795 | M14: 6.9666354 | N14: 5.3810191 | O14: 6.3902696 | P14: 5.9080791 | Q14: 4.6053511 | R14: 4.3413257 | S14: 3.7249585 | T14: 1.6515941 | U14: 1.6781214 | V14: 1.599609 | W14: 2.0075923 | X14: 1.3282799 | Y14: 1.3358505 | Z14: 1.808498 | AA14: 1.2609717 | AB14: 1.1836818 | AC14: 2.5493072 | AD14: 0.40159241 | AE14: 1.1568198 | AF14: 60.79 | AG14: 4.6775 | AH14: 619.34031 | AI14: 11269.579 | AJ14: 107746.7 | AK14: 440876.05 | AL14: 238732.05 | AM14: 59256.096 | AN14: 77325.815 | AO14: 19429.946 | AP14: 125221.7 | AQ14: 468477.05 | AR14: 264611.05 | AS14: 57401.096 | AT14: 121934.81 | AU14: 27303.946
A15: 45777 | B15: 87.6449 | C15: 102.80186 | D15: 132.94275 | E15: 108.38383 | F15: 26.28041 | G15: 29.98897 | H15: 11.789372 | I15: 13.722821 | J15: 15.17333 | K15: 9.9089486 | L15: -61.061032 | M15: 7.0011692 | N15: 5.5855349 | O15: 6.586026 | P15: 5.8831239 | Q15: 4.6824198 | R15: 4.1861692 | S15: 3.7380984 | T15: 1.7245468 | U15: 1.7327465 | V15: 1.59212 | W15: 2.0401369 | X15: 1.2534215 | Y15: 1.3424724 | Z15: 1.8883813 | AA15: 1.302018 | AB15: 1.1781401 | AC15: 2.5906333 | AD15: 0.37895971 | AE15: 1.1625542 | AF15: 58.21 | AG15: 4.609 | AH15: 617.46879 | AI15: 10606.485 | AJ15: 112505.98 | AK15: 455227.15 | AL15: 237614.35 | AM15: 60216.681 | AN15: 72967.934 | AO15: 19526.261 | AP15: 129980.98 | AQ15: 482828.15 | AR15: 263493.35 | AS15: 58361.681 | AT15: 117576.93 | AU15: 27400.261
A16: 45747 | B16: 103.28172 | C16: 115.74577 | D16: 163.45725 | E16: 124.83511 | F16: 32.33849 | G16: 36.88219 | H16: 13.892728 | I16: 15.450678 | J16: 18.656082 | K16: 11.632181 | L16: -75.929794 | M16: 8.6359269 | N16: 6.4480813 | O16: 7.3678758 | P16: 7.1008582 | Q16: 5.5226063 | R16: 4.8187811 | S16: 4.3601091 | T16: 2.0322251 | U16: 1.9509186 | V16: 1.957561 | W16: 2.3949304 | X16: 1.5586379 | Y16: 1.6559367 | Z16: 2.2252896 | AA16: 1.4659566 | AB16: 1.4485598 | AC16: 3.0411618 | AD16: 0.47123888 | AE16: 1.4340081 | AF16: 71.48 | AG16: 5.034 | AH16: 715.75121 | AI16: 10681.621 | AJ16: 132578.3 | AK16: 512545.34 | AL16: 292154.24 | AM16: 70688.765 | AN16: 90736.104 | AO16: 24085.6 | AP16: 150053.3 | AQ16: 540146.34 | AR16: 318033.24 | AS16: 68833.765 | AT16: 135345.1 | AU16: 31959.6
A17: 45716 | B17: 97.50888 | C17: 108.34925 | D17: 154.98589 | E17: 123.56962 | F17: 31.69727 | G17: 35.46483 | H17: 13.632114 | I17: 14.297356 | J17: 15.812589 | K17: 10.981635 | L17: 231.97251 | M17: 8.1310204 | N17: 6.220012 | O17: 6.9173377 | P17: 6.6505568 | Q17: 5.4537394 | R17: 4.550024 | S17: 4.3317572 | T17: 1.9450105 | U17: 1.8260365 | V17: 1.8334415 | W17: 2.3956733 | X17: 1.491772 | Y17: 1.6216046 | Z17: 2.2128579 | AA17: 1.3774474 | AB17: 1.3771063 | AC17: 2.9671453 | AD17: 0.45410255 | AE17: 1.4747039 | AF17: 69.76 | AG17: 4.548 | AH17: 689.88108 | AI17: 11323.729 | AJ17: 126028.9 | AK17: 481534.94 | AL17: 279266.14 | AM17: 70315.408 | AN17: 88381.525 | AO17: 23506.78 | AP17: 144745.9 | AQ17: 507116.94 | AR17: 297865.14 | AS17: 67975.408 | AT17: 127796.53 | AU17: 31751.78
A18: 45688 | B18: 96.41181 | C18: 103.048 | D18: 144.17282 | E18: 122.45016 | F18: 29.31827 | G18: 33.38903 | H18: 13.601875 | I18: 13.763381 | J18: 14.943601 | K18: 10.946627 | L18: 218.08155 | M18: 7.6786925 | N18: 6.2079986 | O18: 6.672023 | P18: 6.3078937 | Q18: 5.4357553 | R18: 4.3615933 | S18: 4.1533561 | T18: 1.940696 | U18: 1.757838 | V18: 1.7326839 | W18: 2.3880363 | X18: 1.4024419 | Y18: 1.5313949 | Z18: 2.2079493 | AA18: 1.3260028 | AB18: 1.3014268 | AC18: 2.9576865 | AD18: 0.42691003 | AE18: 1.3926662 | AF18: 72.53 | AG18: 4.279 | AH18: 667.9538 | AI18: 11477.597 | AJ18: 125749.34 | AK18: 463550.68 | AL18: 263918.94 | AM18: 70091.254 | AN18: 83089.071 | AO18: 22199.1 | AP18: 144466.34 | AQ18: 489132.68 | AR18: 282517.94 | AS18: 67751.254 | AT18: 122504.07 | AU18: 30444.1
A19: 45657 | B19: 96.74349 | C19: 103.7618 | D19: 139.96911 | E19: 118.48263 | F19: 27.90238 | G19: 32.04759 | H19: 13.686068 | I19: 13.905538 | J19: 14.507884 | K19: 10.667283 | L19: 209.23452 | M19: 7.3701937 | N19: 6.2414466 | O19: 6.7373314 | P19: 6.1360797 | Q19: 5.2922509 | R19: 4.2415833 | S19: 4.0316821 | T19: 1.9527085 | U19: 1.775994 | V19: 1.6821632 | W19: 2.3270967 | X19: 1.3455482 | Y19: 1.4698696 | Z19: 2.2216161 | AA19: 1.3396985 | AB19: 1.2634805 | AC19: 2.8822101 | AD19: 0.40959133 | AE19: 1.3367146 | AF19: 71.72 | AG19: 4.0265 | AH19: 654.84632 | AI19: 11169.347 | AJ19: 126527.7 | AK19: 468338.51 | AL19: 256223.74 | AM19: 68302.615 | AN19: 79718.351 | AO19: 21307.23 | AP19: 145244.7 | AQ19: 493920.51 | AR19: 274822.74 | AS19: 65962.615 | AT19: 119133.35 | AU19: 29552.23
A20: 45625 | B20: 105.68912 | C20: 113.78398 | D20: 156.48438 | E20: 128.80564 | F20: 27.6664 | G20: 36.91924 | H20: 12.536684 | I20: 15.384135 | J20: 17.445177 | K20: 10.497499 | L20: 28.864675 | M20: 7.3235473 | N20: 5.6101009 | O20: 7.2957515 | P20: 6.6717757 | Q20: 5.447231 | R20: 2.671304 | S20: 4.4635634 | T20: 2.4997466 | U20: 1.9302338 | V20: 1.8629915 | W20: 2.5343931 | X20: 1.2071103 | Y20: 1.74612 | Z20: 2.1676522 | AA20: 1.4791467 | AB20: 1.4715999 | AC20: 3.0630217 | AD20: 0.39297602 | AE20: 1.5896796 | AF20: 68 | AG20: 4.0805 | AH20: 724.05596 | AI20: 11446.164 | AJ20: 124689.86 | AK20: 518445.35 | AL20: 291003 | AM20: 74952.142 | AN20: 78252.135 | AO20: 24929.355 | AP20: 137772.86 | AQ20: 541877.35 | AR20: 312973 | AS20: 72606.142 | AT20: 116247.14 | AU20: 33338.355
... A68: 44165 | B68: 33.34864 | C68: 31.16404 | D68: 71.27706 | E68: 36.83312 | F68: 15.27118 | G68: 10.78976 | H68: -34.94659 | I68: 48.561014 | J68: -14.170722 | K68: -89.516398 | L68: -3.0526893 | M68: -1.6619158 | N68: 3.5319219 | O68: 5.7266464 | P68: 5.4958065 | Q68: 4.0111708 | R68: 4.1577136 | S68: 4.9245231 | T68: 1.3725247 | U68: 0.90880816 | V68: 1.2353974 | W68: 1.3573724 | X68: 0.97229647 | Y68: 1.7702179 | Z68: 1.9792209 | AA68: 0.79759847 | AB68: 1.5387468 | AC68: 2.207898 | AD68: 0.31903317 | AE68: 1.1214101 | AF68: 45.34 | AG68: 3.4205 | AH68: 274.4181 | AI68: 6585.1613 | AJ68: 42250.428 | AK68: 161222.57 | AL68: 162793.26 | AM68: 27348.782 | AN68: 66072.407 | AO68: 5351.3688 | AP68: 55147.428 | AQ68: 228401.57 | AR68: 191001.26 | AS68: 30003.959 | AT68: 122332.41 | AU68: 8066.3688
H69: 12.763687 | I69: 16.795169 | J69: 24.856773 | K69: 10.832345 | L69: 62.896785 | M69: 8.2686399 | N69: 5.6348922 | O69: 7.3671712 | P69: 7.9697078 | Q69: 5.1401532 | R69: 4.9901136 | S69: 4.037576 | T69: 1.7390998 | U69: 1.9307022 | V69: 1.6717565 | W69: 1.9779716 | X69: 1.6392645 | Y69: 1.4646536 | Z69: 1.8181574 | AA69: 1.5090944 | AB69: 1.6327027 | AC69: 2.6530347 | AD69: 0.49497042 | AE69: 1.2869165 | AJ69: 112907.58 | AK69: 503065.69 | AL69: 317371.27 | AM69: 59902.87 | AN69: 95477.32 | AO69: 22482.432 | AP69: 131129.58 | AQ69: 540094.69 | AR69: 356947.27 | AS69: 64066.87 | AT69: 140157.32 | AU69: 29595.432
H70: 12.763687 | I70: 16.795169 | J70: 24.856773 | K70: 10.832345 | L70: 62.896785 | M70: 8.2686399 | N70: 5.6348922 | O70: 7.3671712 | P70: 7.9697078 | Q70: 5.1401532 | R70: 4.9901136 | S70: 4.037576 | T70: 1.7390998 | U70: 1.9307022 | V70: 1.6717565 | W70: 1.9779716 | X70: 1.6392645 | Y70: 1.4646536 | Z70: 1.8181574 | AA70: 1.5090944 | AB70: 1.6327027 | AC70: 2.6530347 | AD70: 0.49497042 | AE70: 1.2869165 | AJ70: 112907.58 | AK70: 503065.69 | AL70: 317371.27 | AM70: 59902.87 | AN70: 95477.32 | AO70: 22482.432 | AP70: 131129.58 | AQ70: 540094.69 | AR70: 356947.27 | AS70: 64066.87 | AT70: 140157.32 | AU70: 29595.432
H71: 12.763687 | I71: 16.795169 | J71: 24.856773 | K71: 10.832345 | L71: 62.896785 | M71: 8.2686399 | N71: 5.6348922 | O71: 7.3671712 | P71: 7.9697078 | Q71: 5.1401532 | R71: 4.9901136 | S71: 4.037576 | T71: 1.7390998 | U71: 1.9307022 | V71: 1.6717565 | W71: 1.9779716 | X71: 1.6392645 | Y71: 1.4646536 | Z71: 1.8181574 | AA71: 1.5090944 | AB71: 1.6327027 | AC71: 2.6530347 | AD71: 0.49497042 | AE71: 1.2869165 | AJ71: 112907.58 | AK71: 503065.69 | AL71: 317371.27 | AM71: 59902.87 | AN71: 95477.32 | AO71: 22482.432 | AP71: 131129.58 | AQ71: 540094.69 | AR71: 356947.27 | AS71: 64066.87 | AT71: 140157.32 | AU71: 29595.432
H72: 12.763687 | I72: 16.795169 | J72: 24.856773 | K72: 10.832345 | L72: 62.896785 | M72: 8.2686399 | N72: 5.6348922 | O72: 7.3671712 | P72: 7.9697078 | Q72: 5.1401532 | R72: 4.9901136 | S72: 4.037576 | T72: 1.7390998 | U72: 1.9307022 | V72: 1.6717565 | W72: 1.9779716 | X72: 1.6392645 | Y72: 1.4646536 | Z72: 1.8181574 | AA72: 1.5090944 | AB72: 1.6327027 | AC72: 2.6530347 | AD72: 0.49497042 | AE72: 1.2869165 | AJ72: 112907.58 | AK72: 503065.69 | AL72: 317371.27 | AM72: 59902.87 | AN72: 95477.32 | AO72: 22482.432 | AP72: 131129.58 | AQ72: 540094.69 | AR72: 356947.27 | AS72: 64066.87 | AT72: 140157.32 | AU72: 29595.432
H73: 12.763687 | I73: 16.795169 | J73: 24.856773 | K73: 10.832345 | L73: 62.896785 | M73: 8.2686399 | N73: 5.6348922 | O73: 7.3671712 | P73: 7.9697078 | Q73: 5.1401532 | R73: 4.9901136 | S73: 4.037576 | T73: 1.7390998 | U73: 1.9307022 | V73: 1.6717565 | W73: 1.9779716 | X73: 1.6392645 | Y73: 1.4646536 | Z73: 1.8181574 | AA73: 1.5090944 | AB73: 1.6327027 | AC73: 2.6530347 | AD73: 0.49497042 | AE73: 1.2869165 | AJ73: 112907.58 | AK73: 503065.69 | AL73: 317371.27 | AM73: 59902.87 | AN73: 95477.32 | AO73: 22482.432 | AP73: 131129.58 | AQ73: 540094.69 | AR73: 356947.27 | AS73: 64066.87 | AT73: 140157.32 | AU73: 29595.432
H74: 12.763687 | I74: 16.795169 | J74: 24.856773 | K74: 10.832345 | L74: 62.896785 | M74: 8.2686399 | N74: 5.6348922 | O74: 7.3671712 | P74: 7.9697078 | Q74: 5.1401532 | R74: 4.9901136 | S74: 4.037576 | T74: 1.7390998 | U74: 1.9307022 | V74: 1.6717565 | W74: 1.9779716 | X74: 1.6392645 | Y74: 1.4646536 | Z74: 1.8181574 | AA74: 1.5090944 | AB74: 1.6327027 | AC74: 2.6530347 | AD74: 0.49497042 | AE74: 1.2869165 | AJ74: 112907.58 | AK74: 503065.69 | AL74: 317371.27 | AM74: 59902.87 | AN74: 95477.32 | AO74: 22482.432 | AP74: 131129.58 | AQ74: 540094.69 | AR74: 356947.27 | AS74: 64066.87 | AT74: 140157.32 | AU74: 29595.432
H75: 12.763687 | I75: 16.795169 | J75: 24.856773 | K75: 10.832345 | L75: 62.896785 | M75: 8.2686399 | N75: 5.6348922 | O75: 7.3671712 | P75: 7.9697078 | Q75: 5.1401532 | R75: 4.9901136 | S75: 4.037576 | T75: 1.7390998 | U75: 1.9307022 | V75: 1.6717565 | W75: 1.9779716 | X75: 1.6392645 | Y75: 1.4646536 | Z75: 1.8181574 | AA75: 1.5090944 | AB75: 1.6327027 | AC75: 2.6530347 | AD75: 0.49497042 | AE75: 1.2869165 | AJ75: 112907.58 | AK75: 503065.69 | AL75: 317371.27 | AM75: 59902.87 | AN75: 95477.32 | AO75: 22482.432 | AP75: 131129.58 | AQ75: 540094.69 | AR75: 356947.27 | AS75: 64066.87 | AT75: 140157.32 | AU75: 29595.432
H76: 12.763687 | I76: 16.795169 | J76: 24.856773 | K76: 10.832345 | L76: 62.896785 | M76: 8.2686399 | N76: 5.6348922 | O76: 7.3671712 | P76: 7.9697078 | Q76: 5.1401532 | R76: 4.9901136 | S76: 4.037576 | T76: 1.7390998 | U76: 1.9307022 | V76: 1.6717565 | W76: 1.9779716 | X76: 1.6392645 | Y76: 1.4646536 | Z76: 1.8181574 | AA76: 1.5090944 | AB76: 1.6327027 | AC76: 2.6530347 | AD76: 0.49497042 | AE76: 1.2869165 | AJ76: 112907.58 | AK76: 503065.69 | AL76: 317371.27 | AM76: 59902.87 | AN76: 95477.32 | AO76: 22482.432 | AP76: 131129.58 | AQ76: 540094.69 | AR76: 356947.27 | AS76: 64066.87 | AT76: 140157.32 | AU76: 29595.432
H77: 12.763687 | I77: 16.795169 | J77: 24.856773 | K77: 10.832345 | L77: 62.896785 | M77: 8.2686399 | N77: 5.6348922 | O77: 7.3671712 | P77: 7.9697078 | Q77: 5.1401532 | R77: 4.9901136 | S77: 4.037576 | T77: 1.7390998 | U77: 1.9307022 | V77: 1.6717565 | W77: 1.9779716 | X77: 1.6392645 | Y77: 1.4646536 | Z77: 1.8181574 | AA77: 1.5090944 | AB77: 1.6327027 | AC77: 2.6530347 | AD77: 0.49497042 | AE77: 1.2869165 | AJ77: 112907.58 | AK77: 503065.69 | AL77: 317371.27 | AM77: 59902.87 | AN77: 95477.32 | AO77: 22482.432 | AP77: 131129.58 | AQ77: 540094.69 | AR77: 356947.27 | AS77: 64066.87 | AT77: 140157.32 | AU77: 29595.432
H78: 12.763687 | I78: 16.795169 | J78: 24.856773 | K78: 10.832345 | L78: 62.896785 | M78: 8.2686399 | N78: 5.6348922 | O78: 7.3671712 | P78: 7.9697078 | Q78: 5.1401532 | R78: 4.9901136 | S78: 4.037576 | T78: 1.7390998 | U78: 1.9307022 | V78: 1.6717565 | W78: 1.9779716 | X78: 1.6392645 | Y78: 1.4646536 | Z78: 1.8181574 | AA78: 1.5090944 | AB78: 1.6327027 | AC78: 2.6530347 | AD78: 0.49497042 | AE78: 1.2869165 | AJ78: 112907.58 | AK78: 503065.69 | AL78: 317371.27 | AM78: 59902.87 | AN78: 95477.32 | AO78: 22482.432 | AP78: 131129.58 | AQ78: 540094.69 | AR78: 356947.27 | AS78: 64066.87 | AT78: 140157.32 | AU78: 29595.432
H79: 12.763687 | I79: 16.795169 | J79: 24.856773 | K79: 10.832345 | L79: 62.896785 | M79: 8.2686399 | N79: 5.6348922 | O79: 7.3671712 | P79: 7.9697078 | Q79: 5.1401532 | R79: 4.9901136 | S79: 4.037576 | T79: 1.7390998 | U79: 1.9307022 | V79: 1.6717565 | W79: 1.9779716 | X79: 1.6392645 | Y79: 1.4646536 | Z79: 1.8181574 | AA79: 1.5090944 | AB79: 1.6327027 | AC79: 2.6530347 | AD79: 0.49497042 | AE79: 1.2869165 | AJ79: 112907.58 | AK79: 503065.69 | AL79: 317371.27 | AM79: 59902.87 | AN79: 95477.32 | AO79: 22482.432 | AP79: 131129.58 | AQ79: 540094.69 | AR79: 356947.27 | AS79: 64066.87 | AT79: 140157.32 | AU79: 29595.432
H80: 12.763687 | I80: 16.795169 | J80: 24.856773 | K80: 10.832345 | L80: 62.896785 | M80: 8.2686399 | N80: 5.6348922 | O80: 7.3671712 | P80: 7.9697078 | Q80: 5.1401532 | R80: 4.9901136 | S80: 4.037576 | T80: 1.7390998 | U80: 1.9307022 | V80: 1.6717565 | W80: 1.9779716 | X80: 1.6392645 | Y80: 1.4646536 | Z80: 1.8181574 | AA80: 1.5090944 | AB80: 1.6327027 | AC80: 2.6530347 | AD80: 0.49497042 | AE80: 1.2869165 | AJ80: 112907.58 | AK80: 503065.69 | AL80: 317371.27 | AM80: 59902.87 | AN80: 95477.32 | AO80: 22482.432 | AP80: 131129.58 | AQ80: 540094.69 | AR80: 356947.27 | AS80: 64066.87 | AT80: 140157.32 | AU80: 29595.432
... H188: 12.763687 | I188: 16.795169 | J188: 24.856773 | K188: 10.832345 | L188: 62.896785 | M188: 8.2686399 | N188: 5.6348922 | O188: 7.3671712 | P188: 7.9697078 | Q188: 5.1401532 | R188: 4.9901136 | S188: 4.037576 | T188: 1.7390998 | U188: 1.9307022 | V188: 1.6717565 | W188: 1.9779716 | X188: 1.6392645 | Y188: 1.4646536 | Z188: 1.8181574 | AA188: 1.5090944 | AB188: 1.6327027 | AC188: 2.6530347 | AD188: 0.49497042 | AE188: 1.2869165 | AJ188: 112907.58 | AK188: 503065.69 | AL188: 317371.27 | AM188: 59902.87 | AN188: 95477.32 | AO188: 22482.432 | AP188: 131129.58 | AQ188: 540094.69 | AR188: 356947.27 | AS188: 64066.87 | AT188: 140157.32 | AU188: 29595.432

Sheet Financials
B1: ="IQ_Total_Revenue" -> IQ_Total_Revenue | N1: ="IQ_TOTAL_REV_1YR_ANN_GROWTH" -> IQ_TOTAL_REV_1YR_ANN_GROWTH | Z1: ="IQ_NI" -> IQ_NI | AL1: ="IQ_NI_1YR_ANN_Growth" -> IQ_NI_1YR_ANN_Growth | AX1: ="IQ_EBITDA" -> IQ_EBITDA | BI1: 4 | BJ1: IQ_EBITDA growth | BV1: ="IQ_RETURN_INVESTED_CAPITAL" -> IQ_RETURN_INVESTED_CAPITAL
B2: ="IQ_CQ" -> IQ_CQ | H2: ="IQ_LTM" -> IQ_LTM | N2: ="IQ_CQ" -> IQ_CQ | T2: =H2 -> IQ_LTM | Z2: =N2 -> IQ_CQ | AF2: =T2 -> IQ_LTM | AL2: =Z2 -> IQ_CQ | AR2: =AF2 -> IQ_LTM | AX2: =AL2 -> IQ_CQ | BD2: =AR2 -> IQ_LTM | BI2: =_xlfn.XMATCH("*",D:D,-1,2) -> 67 | BJ2: =AX2 -> IQ_CQ | BP2: =BD2 -> IQ_LTM | BV2: IQ_CQ | CB2: IQ_LTM
B3: {=Data!B6:G6} -> COP | C3: XOM | D3: CVX | E3: EOG | F3: BP | G3: DVN | H3: {=B3:G3} -> COP | I3: XOM | J3: CVX | K3: EOG | L3: BP | M3: DVN | N3: {=H3:M3} -> COP | O3: XOM | P3: CVX | Q3: EOG | R3: BP | S3: DVN | T3: {=_xlfn.ANCHORARRAY(N3)} -> COP | U3: XOM | V3: CVX | W3: EOG | X3: BP | Y3: DVN | Z3: {=_xlfn.ANCHORARRAY(T3)} -> COP | AA3: XOM | AB3: CVX | AC3: EOG | AD3: BP | AE3: DVN | AF3: {=_xlfn.ANCHORARRAY(Z3)} -> COP | AG3: XOM | AH3: CVX | AI3: EOG | AJ3: BP | AK3: DVN | AL3: {=_xlfn.ANCHORARRAY(AF3)} -> COP | AM3: XOM | AN3: CVX | AO3: EOG | AP3: BP | AQ3: DVN | AR3: {=_xlfn.ANCHORARRAY(AF3)} -> COP | AS3: XOM | AT3: CVX | AU3: EOG | AV3: BP | AW3: DVN | AX3: {=_xlfn.ANCHORARRAY(AL3)} -> COP | AY3: XOM | AZ3: CVX | BA3: EOG | BB3: BP | BC3: DVN | BD3: {=_xlfn.ANCHORARRAY(AX3)} -> COP | BE3: XOM | BF3: CVX | BG3: EOG | BH3: BP | BI3: DVN | BJ3: {=_xlfn.ANCHORARRAY(BD3)} -> COP | BK3: XOM | BL3: CVX | BM3: EOG | BN3: BP | BO3: DVN | BP3: {=_xlfn.ANCHORARRAY(BJ3)} -> COP | BQ3: XOM | BR3: CVX | BS3: EOG | BT3: BP | BU3: DVN | BV3: {=_xlfn.ANCHORARRAY(BP3)} -> COP | BW3: XOM | BX3: CVX | BY3: EOG | BZ3: BP | CA3: DVN | CB3: {=_xlfn.ANCHORARRAY(BV3)} -> COP | CC3: XOM | CD3: CVX | CE3: EOG | CF3: BP | CG3: DVN
A4: 45930 | B4: {=_xll.ciqfunctions.udf.CIQ(B$3,$B$1,$B$2,$A4,"L",,"USD","H")} -> 15376 | C4: {=_xll.ciqfunctions.udf.CIQ(C$3,$B$1,$B$2,$A4,"L",,"USD","H")} -> 83331 | D4: {=_xll.ciqfunctions.udf.CIQ(D$3,$B$1,$B$2,$A4,"L",,"USD","H")} -> 48747 | E4: {=_xll.ciqfunctions.udf.CIQ(E$3,$B$1,$B$2,$A4,"L",,"USD","H")} -> 5749 | F4: {=_xll.ciqfunctions.udf.CIQ(F$3,$B$1,$B$2,$A4,"L",,"USD","H")} -> 48386 | G4: {=_xll.ciqfunctions.udf.CIQ(G$3,$B$1,$B$2,$A4,"L",,"USD","H")} -> 4067 | H4: {=_xll.ciqfunctions.udf.CIQ(B$3,$B$1,$H$2,$A4,"L",,"USD","H")} -> 61280 | I4: {=_xll.ciqfunctions.udf.CIQ(C$3,$B$1,$H$2,$A4,"L",,"USD","H")} -> 326245 | J4: {=_xll.ciqfunctions.udf.CIQ(D$3,$B$1,$H$2,$A4,"L",,"USD","H")} -> 188687 | K4: {=_xll.ciqfunctions.udf.CIQ(E$3,$B$1,$H$2,$A4,"L",,"USD","H")} -> 22654 | L4: {=_xll.ciqfunctions.udf.CIQ(F$3,$B$1,$H$2,$A4,"L",,"USD","H")} -> 185934 | M4: {=_xll.ciqfunctions.udf.CIQ(G$3,$B$1,$H$2,$A4,"L",,"USD","H")} -> 16554 | N4: {=_xll.ciqfunctions.udf.CIQ(B$3,$N$1,$B$2,$A4,"L",,"USD","H")} -> 14.0483 | O4: {=_xll.ciqfunctions.udf.CIQ(C$3,$N$1,$B$2,$A4,"L",,"USD","H")} -> -5.0814 | P4: {=_xll.ciqfunctions.udf.CIQ(D$3,$N$1,$B$2,$A4,"L",,"USD","H")} -> -1.3539 | Q4: {=_xll.ciqfunctions.udf.CIQ(E$3,$N$1,$B$2,$A4,"L",,"USD","H")} -> -2.4436 | R4: {=_xll.ciqfunctions.udf.CIQ(F$3,$N$1,$B$2,$A4,"L",,"USD","H")} -> 2.4627 | S4: {=_xll.ciqfunctions.udf.CIQ(G$3,$N$1,$B$2,$A4,"L",,"USD","H")} -> 7.1108 | T4: {=_xll.ciqfunctions.udf.CIQ(N$3,$N$1,$T$2,$A4,"L",,"USD","H")} -> 7.6523 | U4: {=_xll.ciqfunctions.udf.CIQ(O$3,$N$1,$T$2,$A4,"L",,"USD","H")} -> -4.5635 | V4: {=_xll.ciqfunctions.udf.CIQ(P$3,$N$1,$T$2,$A4,"L",,"USD","H")} -> -1.5661 | W4: {=_xll.ciqfunctions.udf.CIQ(Q$3,$N$1,$T$2,$A4,"L",,"USD","H")} -> -5.0704 | X4: {=_xll.ciqfunctions.udf.CIQ(R$3,$N$1,$T$2,$A4,"L",,"USD","H")} -> -4.1227 | Y4: {=_xll.ciqfunctions.udf.CIQ(S$3,$N$1,$T$2,$A4,"L",,"USD","H")} -> 13.9376 | Z4: {=_xll.ciqfunctions.udf.CIQ(B$3,$Z$1,$B$2,$A4,"L",,"USD","H")} -> 1726 | AA4: {=_xll.ciqfunctions.udf.CIQ(C$3,$Z$1,$B$2,$A4,"L",,"USD","H")} -> 7548 | AB4: {=_xll.ciqfunctions.udf.CIQ(D$3,$Z$1,$B$2,$A4,"L",,"USD","H")} -> 3539 | AC4: {=_xll.ciqfunctions.udf.CIQ(E$3,$Z$1,$B$2,$A4,"L",,"USD","H")} -> 1471 | AD4: {=_xll.ciqfunctions.udf.CIQ(F$3,$Z$1,$B$2,$A4,"L",,"USD","H")} -> 1161 | AE4: {=_xll.ciqfunctions.udf.CIQ(G$3,$Z$1,$B$2,$A4,"L",,"USD","H")} -> 687 | AF4: {=_xll.ciqfunctions.udf.CIQ(B$3,$Z$1,$H$2,$A4,"L",,"USD","H")} -> 8852 | AG4: {=_xll.ciqfunctions.udf.CIQ(C$3,$Z$1,$H$2,$A4,"L",,"USD","H")} -> 29953 | AH4: {=_xll.ciqfunctions.udf.CIQ(D$3,$Z$1,$H$2,$A4,"L",,"USD","H")} -> 12768 | AI4: {=_xll.ciqfunctions.udf.CIQ(E$3,$Z$1,$H$2,$A4,"L",,"USD","H")} -> 5530 | AJ4: {=_xll.ciqfunctions.udf.CIQ(F$3,$Z$1,$H$2,$A4,"L",,"USD","H")} -> 1518 | AK4: {=_xll.ciqfunctions.udf.CIQ(G$3,$Z$1,$H$2,$A4,"L",,"USD","H")} -> 2719 | AL4: {=_xll.ciqfunctions.udf.CIQ(B$3,$AL$1,$AL$2,$A4,"L",,"USD","H")} -> -16.1729 | AM4: {=_xll.ciqfunctions.udf.CIQ(C$3,$AL$1,$AL$2,$A4,"L",,"USD","H")} -> -12.3345 | AN4: {=_xll.ciqfunctions.udf.CIQ(D$3,$AL$1,$AL$2,$A4,"L",,"USD","H")} -> -21.1278 | AO4: {=_xll.ciqfunctions.udf.CIQ(E$3,$AL$1,$AL$2,$A4,"L",,"USD","H")} -> -12.0742 | AP4: {=_xll.ciqfunctions.udf.CIQ(F$3,$AL$1,$AL$2,$A4,"L",,"USD","H")} -> 463.5922 | AQ4: {=_xll.ciqfunctions.udf.CIQ(G$3,$AL$1,$AL$2,$A4,"L",,"USD","H")} -> -15.3941 | AR4: {=_xll.ciqfunctions.udf.CIQ(B$3,$AL$1,$AR$2,$A4,"L",,"USD","H")} -> -10.9994 | AS4: {=_xll.ciqfunctions.udf.CIQ(C$3,$AL$1,$AR$2,$A4,"L",,"USD","H")} -> -11.1187 | AT4: {=_xll.ciqfunctions.udf.CIQ(D$3,$AL$1,$AR$2,$A4,"L",,"USD","H")} -> -23.4579 | AU4: {=_xll.ciqfunctions.udf.CIQ(E$3,$AL$1,$AR$2,$A4,"L",,"USD","H")} -> -22.5491 | AV4: {=_xll.ciqfunctions.udf.CIQ(F$3,$AL$1,$AR$2,$A4,"L",,"USD","H")} -> -44.006 | AW4: {=_xll.ciqfunctions.udf.CIQ(G$3,$AL$1,$AR$2,$A4,"L",,"USD","H")} -> -20.1234 | AX4: {=_xll.ciqfunctions.udf.CIQ(B$3,$AX$1,$AX$2,$A4,"L",,"USD","H")} -> 5942 | AY4: {=_xll.ciqfunctions.udf.CIQ(C$3,$AX$1,$AX$2,$A4,"L",,"USD","H")} -> 15689 | AZ4: {=_xll.ciqfunctions.udf.CIQ(D$3,$AX$1,$AX$2,$A4,"L",,"USD","H")} -> 10584 | BA4: {=_xll.ciqfunctions.udf.CIQ(E$3,$AX$1,$AX$2,$A4,"L",,"USD","H")} -> 3094 | BB4: {=_xll.ciqfunctions.udf.CIQ(F$3,$AX$1,$AX$2,$A4,"L",,"USD","H")} -> 9478 | BC4: {=_xll.ciqfunctions.udf.CIQ(G$3,$AX$1,$AX$2,$A4,"L",,"USD","H")} -> 1863 | BD4: {=_xll.ciqfunctions.udf.CIQ(B$3,$AX$1,$BD$2,$A4,"L",,"USD","H")} -> 25422 | BE4: {=_xll.ciqfunctions.udf.CIQ(C$3,$AX$1,$BD$2,$A4,"L",,"USD","H")} -> 61694 | BF4: {=_xll.ciqfunctions.udf.CIQ(D$3,$AX$1,$BD$2,$A4,"L",,"USD","H")} -> 37683 | BG4: {=_xll.ciqfunctions.udf.CIQ(E$3,$AX$1,$BD$2,$A4,"L",,"USD","H")} -> 11760 | BH4: {=_xll.ciqfunctions.udf.CIQ(F$3,$AX$1,$BD$2,$A4,"L",,"USD","H")} -> 28658 | BI4: {=_xll.ciqfunctions.udf.CIQ(G$3,$AX$1,$BD$2,$A4,"L",,"USD","H")} -> 7670 | BJ4: =AX4/AX8-1 -> 0.049267173 | BK4: =AY4/AY8-1 -> -0.091388197 | BL4: =AZ4/AZ8-1 -> 0.10181137 | BM4: =BA4/BA8-1 -> -0.015276894 | BN4: =BB4/BB8-1 -> 0.16580566 | BO4: =BC4/BC8-1 -> -0.042651593 | BP4: =BD4/BD8-1 -> 0.039924732 | BQ4: =BE4/BE8-1 -> -0.073594114 | ... BU4: =BI4/BI8-1 -> 0.0076195481 | BV4: {=_xll.ciqfunctions.udf.CIQ(B$3,$BV$1,$BV$2,$A4,"L",,"USD","H")/100} -> 0.033844 | BW4: {=_xll.ciqfunctions.udf.CIQ(C$3,$BV$1,$BV$2,$A4,"L",,"USD","H")/100} -> 0.042712 | BX4: {=_xll.ciqfunctions.udf.CIQ(D$3,$BV$1,$BV$2,$A4,"L",,"USD","H")/100} -> 0.002124 | BY4: {=_xll.ciqfunctions.udf.CIQ(E$3,$BV$1,$BV$2,$A4,"L",,"USD","H")/100} -> 0.102536 | BZ4: {=_xll.ciqfunctions.udf.CIQ(F$3,$BV$1,$BV$2,$A4,"L",,"USD","H")/100} -> -0.003304 | CA4: {=_xll.ciqfunctions.udf.CIQ(G$3,$BV$1,$BV$2,$A4,"L",,"USD","H")/100} -> 0.088696 | CB4: {=_xll.ciqfunctions.udf.CIQ(B$3,$BV$1,$CB$2,$A4,"L",,"USD","H")/100} -> 0.063835 | CC4: {=_xll.ciqfunctions.udf.CIQ(C$3,$BV$1,$CB$2,$A4,"L",,"USD","H")/100} -> 0.040422 | CD4: {=_xll.ciqfunctions.udf.CIQ(D$3,$BV$1,$CB$2,$A4,"L",,"USD","H")/100} -> 0.002542 | CE4: {=_xll.ciqfunctions.udf.CIQ(E$3,$BV$1,$CB$2,$A4,"L",,"USD","H")/100} -> 0.09459 | CF4: {=_xll.ciqfunctions.udf.CIQ(F$3,$BV$1,$CB$2,$A4,"L",,"USD","H")/100} -> -0.023582 | CG4: {=_xll.ciqfunctions.udf.CIQ(G$3,$BV$1,$CB$2,$A4,"L",,"USD","H")/100} -> 0.088237
A5: 45838 | B5: {=_xll.ciqfunctions.udf.CIQ(B$3,$B$1,$B$2,$A5,"L",,"USD","H")} -> 14319 | C5: {=_xll.ciqfunctions.udf.CIQ(C$3,$B$1,$B$2,$A5,"L",,"USD","H")} -> 79477 | D5: {=_xll.ciqfunctions.udf.CIQ(D$3,$B$1,$B$2,$A5,"L",,"USD","H")} -> 44516 | E5: {=_xll.ciqfunctions.udf.CIQ(E$3,$B$1,$B$2,$A5,"L",,"USD","H")} -> 5371 | F5: {=_xll.ciqfunctions.udf.CIQ(F$3,$B$1,$B$2,$A5,"L",,"USD","H")} -> 46973 | G5: {=_xll.ciqfunctions.udf.CIQ(G$3,$B$1,$B$2,$A5,"L",,"USD","H")} -> 3868 | H5: {=_xll.ciqfunctions.udf.CIQ(B$3,$B$1,$H$2,$A5,"L",,"USD","H")} -> 59386 | I5: {=_xll.ciqfunctions.udf.CIQ(C$3,$B$1,$H$2,$A5,"L",,"USD","H")} -> 330706 | J5: {=_xll.ciqfunctions.udf.CIQ(D$3,$B$1,$H$2,$A5,"L",,"USD","H")} -> 189356 | K5: {=_xll.ciqfunctions.udf.CIQ(E$3,$B$1,$H$2,$A5,"L",,"USD","H")} -> 22798 | L5: {=_xll.ciqfunctions.udf.CIQ(F$3,$B$1,$H$2,$A5,"L",,"USD","H")} -> 184771 | M5: {=_xll.ciqfunctions.udf.CIQ(G$3,$B$1,$H$2,$A5,"L",,"USD","H")} -> 16105 | N5: {=_xll.ciqfunctions.udf.CIQ(B$3,$N$1,$B$2,$A5,"L",,"USD","H")} -> 2.1108 | O5: {=_xll.ciqfunctions.udf.CIQ(C$3,$N$1,$B$2,$A5,"L",,"USD","H")} -> -11.6785 | P5: {=_xll.ciqfunctions.udf.CIQ(D$3,$N$1,$B$2,$A5,"L",,"USD","H")} -> -10.571 | Q5: {=_xll.ciqfunctions.udf.CIQ(E$3,$N$1,$B$2,$A5,"L",,"USD","H")} -> -11.2525 | R5: {=_xll.ciqfunctions.udf.CIQ(F$3,$N$1,$B$2,$A5,"L",,"USD","H")} -> -1.338 | S5: {=_xll.ciqfunctions.udf.CIQ(G$3,$N$1,$B$2,$A5,"L",,"USD","H")} -> -0.6677 | T5: {=_xll.ciqfunctions.udf.CIQ(N$3,$N$1,$T$2,$A5,"L",,"USD","H")} -> 2.2486 | U5: {=_xll.ciqfunctions.udf.CIQ(O$3,$N$1,$T$2,$A5,"L",,"USD","H")} -> -3.4782 | V5: {=_xll.ciqfunctions.udf.CIQ(P$3,$N$1,$T$2,$A5,"L",,"USD","H")} -> -2.9183 | W5: {=_xll.ciqfunctions.udf.CIQ(Q$3,$N$1,$T$2,$A5,"L",,"USD","H")} -> -5.4222 | X5: {=_xll.ciqfunctions.udf.CIQ(R$3,$N$1,$T$2,$A5,"L",,"USD","H")} -> -7.5817 | Y5: {=_xll.ciqfunctions.udf.CIQ(S$3,$N$1,$T$2,$A5,"L",,"USD","H")} -> 7.7906 | Z5: {=_xll.ciqfunctions.udf.CIQ(B$3,$Z$1,$B$2,$A5,"L",,"USD","H")} -> 1971 | AA5: {=_xll.ciqfunctions.udf.CIQ(C$3,$Z$1,$B$2,$A5,"L",,"USD","H")} -> 7082 | AB5: {=_xll.ciqfunctions.udf.CIQ(D$3,$Z$1,$B$2,$A5,"L",,"USD","H")} -> 2490 | AC5: {=_xll.ciqfunctions.udf.CIQ(E$3,$Z$1,$B$2,$A5,"L",,"USD","H")} -> 1345 | AD5: {=_xll.ciqfunctions.udf.CIQ(F$3,$Z$1,$B$2,$A5,"L",,"USD","H")} -> 1629 | AE5: {=_xll.ciqfunctions.udf.CIQ(G$3,$Z$1,$B$2,$A5,"L",,"USD","H")} -> 899 | AF5: {=_xll.ciqfunctions.udf.CIQ(B$3,$Z$1,$H$2,$A5,"L",,"USD","H")} -> 9185 | AG5: {=_xll.ciqfunctions.udf.CIQ(C$3,$Z$1,$H$2,$A5,"L",,"USD","H")} -> 31015 | AH5: {=_xll.ciqfunctions.udf.CIQ(D$3,$Z$1,$H$2,$A5,"L",,"USD","H")} -> 13716 | AI5: {=_xll.ciqfunctions.udf.CIQ(E$3,$Z$1,$H$2,$A5,"L",,"USD","H")} -> 5732 | AJ5: {=_xll.ciqfunctions.udf.CIQ(F$3,$Z$1,$H$2,$A5,"L",,"USD","H")} -> 563 | AK5: {=_xll.ciqfunctions.udf.CIQ(G$3,$Z$1,$H$2,$A5,"L",,"USD","H")} -> 2844 | AL5: {=_xll.ciqfunctions.udf.CIQ(B$3,$AL$1,$AL$2,$A5,"L",,"USD","H")} -> -15.3715 | AM5: {=_xll.ciqfunctions.udf.CIQ(C$3,$AL$1,$AL$2,$A5,"L",,"USD","H")} -> -23.355 | AN5: {=_xll.ciqfunctions.udf.CIQ(D$3,$AL$1,$AL$2,$A5,"L",,"USD","H")} -> -43.8431 | AO5: {=_xll.ciqfunctions.udf.CIQ(E$3,$AL$1,$AL$2,$A5,"L",,"USD","H")} -> -20.4143 | AP5: {=_xll.ciqfunctions.udf.CIQ(F$3,$AL$1,$AL$2,$A5,"L",,"USD","H")} -> NM | AQ5: {=_xll.ciqfunctions.udf.CIQ(G$3,$AL$1,$AL$2,$A5,"L",,"USD","H")} -> 6.5165 | AR5: {=_xll.ciqfunctions.udf.CIQ(B$3,$AL$1,$AR$2,$A5,"L",,"USD","H")} -> -14.0384 | AS5: {=_xll.ciqfunctions.udf.CIQ(C$3,$AL$1,$AR$2,$A5,"L",,"USD","H")} -> -9.2067 | AT5: {=_xll.ciqfunctions.udf.CIQ(D$3,$AL$1,$AR$2,$A5,"L",,"USD","H")} -> -26.7308 | AU5: {=_xll.ciqfunctions.udf.CIQ(E$3,$AL$1,$AR$2,$A5,"L",,"USD","H")} -> -23.5428 | AV5: {=_xll.ciqfunctions.udf.CIQ(F$3,$AL$1,$AR$2,$A5,"L",,"USD","H")} -> -92.3537 | AW5: {=_xll.ciqfunctions.udf.CIQ(G$3,$AL$1,$AR$2,$A5,"L",,"USD","H")} -> -18.7893 | AX5: {=_xll.ciqfunctions.udf.CIQ(B$3,$AX$1,$AX$2,$A5,"L",,"USD","H")} -> 5681 | AY5: {=_xll.ciqfunctions.udf.CIQ(C$3,$AX$1,$AX$2,$A5,"L",,"USD","H")} -> 14922 | AZ5: {=_xll.ciqfunctions.udf.CIQ(D$3,$AX$1,$AX$2,$A5,"L",,"USD","H")} -> 8458 | BA5: {=_xll.ciqfunctions.udf.CIQ(E$3,$AX$1,$AX$2,$A5,"L",,"USD","H")} -> 2839 | BB5: {=_xll.ciqfunctions.udf.CIQ(F$3,$AX$1,$AX$2,$A5,"L",,"USD","H")} -> 9702 | BC5: {=_xll.ciqfunctions.udf.CIQ(G$3,$AX$1,$AX$2,$A5,"L",,"USD","H")} -> 1884 | BD5: {=_xll.ciqfunctions.udf.CIQ(B$3,$AX$1,$BD$2,$A5,"L",,"USD","H")} -> 25143 | BE5: {=_xll.ciqfunctions.udf.CIQ(C$3,$AX$1,$BD$2,$A5,"L",,"USD","H")} -> 63272 | BF5: {=_xll.ciqfunctions.udf.CIQ(D$3,$AX$1,$BD$2,$A5,"L",,"USD","H")} -> 36705 | BG5: {=_xll.ciqfunctions.udf.CIQ(E$3,$AX$1,$BD$2,$A5,"L",,"USD","H")} -> 11808 | BH5: {=_xll.ciqfunctions.udf.CIQ(F$3,$AX$1,$BD$2,$A5,"L",,"USD","H")} -> 27310 | BI5: {=_xll.ciqfunctions.udf.CIQ(G$3,$AX$1,$BD$2,$A5,"L",,"USD","H")} -> 7744 | BJ5: =AX5/AX9-1 -> -0.072489796 | BK5: =AY5/AY9-1 -> -0.10372995 | BL5: =AZ5/AZ9-1 -> -0.13322402 | BM5: =BA5/BA9-1 -> -0.10582677 | BN5: =BB5/BB9-1 -> 0.23623853 | BO5: =BC5/BC9-1 -> -0.022314478 | BP5: =BD5/BD9-1 -> 0.0049562333 | BQ5: =BE5/BE9-1 -> -0.032848779 | ... BU5: =BI5/BI9-1 -> 0.036541293 | BV5: {=_xll.ciqfunctions.udf.CIQ(B$3,$BV$1,$BV$2,$A5,"L",,"USD","H")/100} -> 0.044328 | BW5: {=_xll.ciqfunctions.udf.CIQ(C$3,$BV$1,$BV$2,$A5,"L",,"USD","H")/100} -> 0.036264 | BX5: {=_xll.ciqfunctions.udf.CIQ(D$3,$BV$1,$BV$2,$A5,"L",,"USD","H")/100} -> -0.00996 | BY5: {=_xll.ciqfunctions.udf.CIQ(E$3,$BV$1,$BV$2,$A5,"L",,"USD","H")/100} -> 0.095536 | BZ5: {=_xll.ciqfunctions.udf.CIQ(F$3,$BV$1,$BV$2,$A5,"L",,"USD","H")/100} -> 0.042888 | CA5: {=_xll.ciqfunctions.udf.CIQ(G$3,$BV$1,$BV$2,$A5,"L",,"USD","H")/100} -> 0.123484 | CB5: {=_xll.ciqfunctions.udf.CIQ(B$3,$BV$1,$CB$2,$A5,"L",,"USD","H")/100} -> 0.068652 | CC5: {=_xll.ciqfunctions.udf.CIQ(C$3,$BV$1,$CB$2,$A5,"L",,"USD","H")/100} -> 0.04386 | CD5: {=_xll.ciqfunctions.udf.CIQ(D$3,$BV$1,$CB$2,$A5,"L",,"USD","H")/100} -> 0.010983 | CE5: {=_xll.ciqfunctions.udf.CIQ(E$3,$BV$1,$CB$2,$A5,"L",,"USD","H")/100} -> 0.10805 | CF5: {=_xll.ciqfunctions.udf.CIQ(F$3,$BV$1,$CB$2,$A5,"L",,"USD","H")/100} -> -0.029341 | CG5: {=_xll.ciqfunctions.udf.CIQ(G$3,$BV$1,$CB$2,$A5,"L",,"USD","H")/100} -> 0.09682
A6: 45747 | B6: {=_xll.ciqfunctions.udf.CIQ(B$3,$B$1,$B$2,$A6,"L",,"USD","H")} -> 16909 | C6: {=_xll.ciqfunctions.udf.CIQ(C$3,$B$1,$B$2,$A6,"L",,"USD","H")} -> 81058 | D6: {=_xll.ciqfunctions.udf.CIQ(D$3,$B$1,$B$2,$A6,"L",,"USD","H")} -> 46265 | E6: {=_xll.ciqfunctions.udf.CIQ(E$3,$B$1,$B$2,$A6,"L",,"USD","H")} -> 5861 | F6: {=_xll.ciqfunctions.udf.CIQ(F$3,$B$1,$B$2,$A6,"L",,"USD","H")} -> 46458 | G6: {=_xll.ciqfunctions.udf.CIQ(G$3,$B$1,$B$2,$A6,"L",,"USD","H")} -> 4338 | H6: {=_xll.ciqfunctions.udf.CIQ(B$3,$B$1,$H$2,$A6,"L",,"USD","H")} -> 59090 | I6: {=_xll.ciqfunctions.udf.CIQ(C$3,$B$1,$H$2,$A6,"L",,"USD","H")} -> 341215 | J6: {=_xll.ciqfunctions.udf.CIQ(D$3,$B$1,$H$2,$A6,"L",,"USD","H")} -> 194618 | K6: {=_xll.ciqfunctions.udf.CIQ(E$3,$B$1,$H$2,$A6,"L",,"USD","H")} -> 23479 | L6: {=_xll.ciqfunctions.udf.CIQ(F$3,$B$1,$H$2,$A6,"L",,"USD","H")} -> 185408 | M6: {=_xll.ciqfunctions.udf.CIQ(G$3,$B$1,$H$2,$A6,"L",,"USD","H")} -> 15943 | N6: {=_xll.ciqfunctions.udf.CIQ(B$3,$N$1,$B$2,$A6,"L",,"USD","H")} -> 18.5016 | O6: {=_xll.ciqfunctions.udf.CIQ(C$3,$N$1,$B$2,$A6,"L",,"USD","H")} -> 0.8046 | P6: {=_xll.ciqfunctions.udf.CIQ(D$3,$N$1,$B$2,$A6,"L",,"USD","H")} -> -2.0121 | Q6: {=_xll.ciqfunctions.udf.CIQ(E$3,$N$1,$B$2,$A6,"L",,"USD","H")} -> 0.017 | R6: {=_xll.ciqfunctions.udf.CIQ(F$3,$N$1,$B$2,$A6,"L",,"USD","H")} -> -4.0838 | S6: {=_xll.ciqfunctions.udf.CIQ(G$3,$N$1,$B$2,$A6,"L",,"USD","H")} -> 21.6489 | T6: {=_xll.ciqfunctions.udf.CIQ(N$3,$N$1,$T$2,$A6,"L",,"USD","H")} -> 3.995 | U6: {=_xll.ciqfunctions.udf.CIQ(O$3,$N$1,$T$2,$A6,"L",,"USD","H")} -> 2.4999 | V6: {=_xll.ciqfunctions.udf.CIQ(P$3,$N$1,$T$2,$A6,"L",,"USD","H")} -> 0.9413 | W6: {=_xll.ciqfunctions.udf.CIQ(Q$3,$N$1,$T$2,$A6,"L",,"USD","H")} -> -0.2338 | X6: {=_xll.ciqfunctions.udf.CIQ(R$3,$N$1,$T$2,$A6,"L",,"USD","H")} -> -7.7935 | Y6: {=_xll.ciqfunctions.udf.CIQ(S$3,$N$1,$T$2,$A6,"L",,"USD","H")} -> 9.3934 | Z6: {=_xll.ciqfunctions.udf.CIQ(B$3,$Z$1,$B$2,$A6,"L",,"USD","H")} -> 2849 | AA6: {=_xll.ciqfunctions.udf.CIQ(C$3,$Z$1,$B$2,$A6,"L",,"USD","H")} -> 7713 | AB6: {=_xll.ciqfunctions.udf.CIQ(D$3,$Z$1,$B$2,$A6,"L",,"USD","H")} -> 3500 | AC6: {=_xll.ciqfunctions.udf.CIQ(E$3,$Z$1,$B$2,$A6,"L",,"USD","H")} -> 1463 | AD6: {=_xll.ciqfunctions.udf.CIQ(F$3,$Z$1,$B$2,$A6,"L",,"USD","H")} -> 687 | AE6: {=_xll.ciqfunctions.udf.CIQ(G$3,$Z$1,$B$2,$A6,"L",,"USD","H")} -> 494 | AF6: {=_xll.ciqfunctions.udf.CIQ(B$3,$Z$1,$H$2,$A6,"L",,"USD","H")} -> 9543 | AG6: {=_xll.ciqfunctions.udf.CIQ(C$3,$Z$1,$H$2,$A6,"L",,"USD","H")} -> 33173 | AH6: {=_xll.ciqfunctions.udf.CIQ(D$3,$Z$1,$H$2,$A6,"L",,"USD","H")} -> 15660 | AI6: {=_xll.ciqfunctions.udf.CIQ(E$3,$Z$1,$H$2,$A6,"L",,"USD","H")} -> 6077 | AJ6: {=_xll.ciqfunctions.udf.CIQ(F$3,$Z$1,$H$2,$A6,"L",,"USD","H")} -> -1195 | AK6: {=_xll.ciqfunctions.udf.CIQ(G$3,$Z$1,$H$2,$A6,"L",,"USD","H")} -> 2789 | AL6: {=_xll.ciqfunctions.udf.CIQ(B$3,$AL$1,$AL$2,$A6,"L",,"USD","H")} -> 11.6816 | AM6: {=_xll.ciqfunctions.udf.CIQ(C$3,$AL$1,$AL$2,$A6,"L",,"USD","H")} -> -6.1679 | AN6: {=_xll.ciqfunctions.udf.CIQ(D$3,$AL$1,$AL$2,$A6,"L",,"USD","H")} -> -36.3753 | AO6: {=_xll.ciqfunctions.udf.CIQ(E$3,$AL$1,$AL$2,$A6,"L",,"USD","H")} -> -18.2225 | AP6: {=_xll.ciqfunctions.udf.CIQ(F$3,$AL$1,$AL$2,$A6,"L",,"USD","H")} -> -69.6421 | AQ6: {=_xll.ciqfunctions.udf.CIQ(G$3,$AL$1,$AL$2,$A6,"L",,"USD","H")} -> -17.1141 | AR6: {=_xll.ciqfunctions.udf.CIQ(B$3,$AL$1,$AR$2,$A6,"L",,"USD","H")} -> -9.8697 | AS6: {=_xll.ciqfunctions.udf.CIQ(C$3,$AL$1,$AR$2,$A6,"L",,"USD","H")} -> 1.1371 | AT6: {=_xll.ciqfunctions.udf.CIQ(D$3,$AL$1,$AR$2,$A6,"L",,"USD","H")} -> -22.842 | AU6: {=_xll.ciqfunctions.udf.CIQ(E$3,$AL$1,$AR$2,$A6,"L",,"USD","H")} -> -17.4321 | AV6: {=_xll.ciqfunctions.udf.CIQ(F$3,$AL$1,$AR$2,$A6,"L",,"USD","H")} -> NM | AW6: {=_xll.ciqfunctions.udf.CIQ(G$3,$AL$1,$AR$2,$A6,"L",,"USD","H")} -> -16.6966 | AX6: {=_xll.ciqfunctions.udf.CIQ(B$3,$AX$1,$AX$2,$A6,"L",,"USD","H")} -> 7275 | AY6: {=_xll.ciqfunctions.udf.CIQ(C$3,$AX$1,$AX$2,$A6,"L",,"USD","H")} -> 15435 | AZ6: {=_xll.ciqfunctions.udf.CIQ(D$3,$AX$1,$AX$2,$A6,"L",,"USD","H")} -> 8567 | BA6: {=_xll.ciqfunctions.udf.CIQ(E$3,$AX$1,$AX$2,$A6,"L",,"USD","H")} -> 2917 | BB6: {=_xll.ciqfunctions.udf.CIQ(F$3,$AX$1,$AX$2,$A6,"L",,"USD","H")} -> 8215 | BC6: {=_xll.ciqfunctions.udf.CIQ(G$3,$AX$1,$AX$2,$A6,"L",,"USD","H")} -> 1937 | BD6: {=_xll.ciqfunctions.udf.CIQ(B$3,$AX$1,$BD$2,$A6,"L",,"USD","H")} -> 25587 | BE6: {=_xll.ciqfunctions.udf.CIQ(C$3,$AX$1,$BD$2,$A6,"L",,"USD","H")} -> 64999 | BF6: {=_xll.ciqfunctions.udf.CIQ(D$3,$AX$1,$BD$2,$A6,"L",,"USD","H")} -> 38005 | BG6: {=_xll.ciqfunctions.udf.CIQ(E$3,$AX$1,$BD$2,$A6,"L",,"USD","H")} -> 12144 | BH6: {=_xll.ciqfunctions.udf.CIQ(F$3,$AX$1,$BD$2,$A6,"L",,"USD","H")} -> 25456 | BI6: {=_xll.ciqfunctions.udf.CIQ(G$3,$AX$1,$BD$2,$A6,"L",,"USD","H")} -> 7759 | BJ6: =AX6/AX10-1 -> 0.21330887 | BK6: =AY6/AY10-1 -> 0.047861507 | BL6: =AZ6/AZ10-1 -> -0.19505778 | BM6: =BA6/BA10-1 -> -0.12612343 | BN6: =BB6/BB10-1 -> -0.15483539 | BO6: =BC6/BC10-1 -> 0.23611997 | BP6: =BD6/BD10-1 -> 0.053526578 | BQ6: =BE6/BE10-1 -> 0.043976165 | ... BU6: =BI6/BI10-1 -> 0.086694678 | BV6: {=_xll.ciqfunctions.udf.CIQ(B$3,$BV$1,$BV$2,$A6,"L",,"USD","H")/100} -> 0.082648 | BW6: {=_xll.ciqfunctions.udf.CIQ(C$3,$BV$1,$BV$2,$A6,"L",,"USD","H")/100} -> 0.043148 | BX6: {=_xll.ciqfunctions.udf.CIQ(D$3,$BV$1,$BV$2,$A6,"L",,"USD","H")/100} -> 0.011384 | BY6: {=_xll.ciqfunctions.udf.CIQ(E$3,$BV$1,$BV$2,$A6,"L",,"USD","H")/100} -> 0.106136 | BZ6: {=_xll.ciqfunctions.udf.CIQ(F$3,$BV$1,$BV$2,$A6,"L",,"USD","H")/100} -> -0.015252 | CA6: {=_xll.ciqfunctions.udf.CIQ(G$3,$BV$1,$BV$2,$A6,"L",,"USD","H")/100} -> 0.055464 | CB6: {=_xll.ciqfunctions.udf.CIQ(B$3,$BV$1,$CB$2,$A6,"L",,"USD","H")/100} -> 0.07429 | CC6: {=_xll.ciqfunctions.udf.CIQ(C$3,$BV$1,$CB$2,$A6,"L",,"USD","H")/100} -> 0.056849 | CD6: {=_xll.ciqfunctions.udf.CIQ(D$3,$BV$1,$CB$2,$A6,"L",,"USD","H")/100} -> 0.021351 | CE6: {=_xll.ciqfunctions.udf.CIQ(E$3,$BV$1,$CB$2,$A6,"L",,"USD","H")/100} -> 0.118146 | CF6: {=_xll.ciqfunctions.udf.CIQ(F$3,$BV$1,$CB$2,$A6,"L",,"USD","H")/100} -> -0.041839 | CG6: {=_xll.ciqfunctions.udf.CIQ(G$3,$BV$1,$CB$2,$A6,"L",,"USD","H")/100} -> 0.093317
A7: 45657 | B7: {=_xll.ciqfunctions.udf.CIQ(B$3,$B$1,$B$2,$A7,"L",,"USD","H")} -> 14676 | C7: {=_xll.ciqfunctions.udf.CIQ(C$3,$B$1,$B$2,$A7,"L",,"USD","H")} -> 82379 | D7: {=_xll.ciqfunctions.udf.CIQ(D$3,$B$1,$B$2,$A7,"L",,"USD","H")} -> 49159 | E7: {=_xll.ciqfunctions.udf.CIQ(E$3,$B$1,$B$2,$A7,"L",,"USD","H")} -> 5673 | F7: {=_xll.ciqfunctions.udf.CIQ(F$3,$B$1,$B$2,$A7,"L",,"USD","H")} -> 44117 | G7: {=_xll.ciqfunctions.udf.CIQ(G$3,$B$1,$B$2,$A7,"L",,"USD","H")} -> 4281 | H7: {=_xll.ciqfunctions.udf.CIQ(B$3,$B$1,$H$2,$A7,"L",,"USD","H")} -> 56450 | I7: {=_xll.ciqfunctions.udf.CIQ(C$3,$B$1,$H$2,$A7,"L",,"USD","H")} -> 340568 | J7: {=_xll.ciqfunctions.udf.CIQ(D$3,$B$1,$H$2,$A7,"L",,"USD","H")} -> 195568 | K7: {=_xll.ciqfunctions.udf.CIQ(E$3,$B$1,$H$2,$A7,"L",,"USD","H")} -> 23478 | L7: {=_xll.ciqfunctions.udf.CIQ(F$3,$B$1,$H$2,$A7,"L",,"USD","H")} -> 187386 | M7: {=_xll.ciqfunctions.udf.CIQ(G$3,$B$1,$H$2,$A7,"L",,"USD","H")} -> 15171 | N7: {=_xll.ciqfunctions.udf.CIQ(B$3,$N$1,$B$2,$A7,"L",,"USD","H")} -> -3.1288 | O7: {=_xll.ciqfunctions.udf.CIQ(C$3,$N$1,$B$2,$A7,"L",,"USD","H")} -> -1.5265 | P7: {=_xll.ciqfunctions.udf.CIQ(D$3,$N$1,$B$2,$A7,"L",,"USD","H")} -> 8.5666 | Q7: {=_xll.ciqfunctions.udf.CIQ(E$3,$N$1,$B$2,$A7,"L",,"USD","H")} -> -6.3707 | R7: {=_xll.ciqfunctions.udf.CIQ(F$3,$N$1,$B$2,$A7,"L",,"USD","H")} -> -12.9156 | S7: {=_xll.ciqfunctions.udf.CIQ(G$3,$N$1,$B$2,$A7,"L",,"USD","H")} -> 17.6422 | T7: {=_xll.ciqfunctions.udf.CIQ(N$3,$N$1,$T$2,$A7,"L",,"USD","H")} -> -2.4387 | U7: {=_xll.ciqfunctions.udf.CIQ(O$3,$N$1,$T$2,$A7,"L",,"USD","H")} -> 1.1593 | V7: {=_xll.ciqfunctions.udf.CIQ(P$3,$N$1,$T$2,$A7,"L",,"USD","H")} -> 0.3947 | W7: {=_xll.ciqfunctions.udf.CIQ(Q$3,$N$1,$T$2,$A7,"L",,"USD","H")} -> 0.8808 | X7: {=_xll.ciqfunctions.udf.CIQ(R$3,$N$1,$T$2,$A7,"L",,"USD","H")} -> -10.0624 | Y7: {=_xll.ciqfunctions.udf.CIQ(S$3,$N$1,$T$2,$A7,"L",,"USD","H")} -> 5.1569 | Z7: {=_xll.ciqfunctions.udf.CIQ(B$3,$Z$1,$B$2,$A7,"L",,"USD","H")} -> 2306 | AA7: {=_xll.ciqfunctions.udf.CIQ(C$3,$Z$1,$B$2,$A7,"L",,"USD","H")} -> 7610 | AB7: {=_xll.ciqfunctions.udf.CIQ(D$3,$Z$1,$B$2,$A7,"L",,"USD","H")} -> 3239 | AC7: {=_xll.ciqfunctions.udf.CIQ(E$3,$Z$1,$B$2,$A7,"L",,"USD","H")} -> 1251 | AD7: {=_xll.ciqfunctions.udf.CIQ(F$3,$Z$1,$B$2,$A7,"L",,"USD","H")} -> -1959 | AE7: {=_xll.ciqfunctions.udf.CIQ(G$3,$Z$1,$B$2,$A7,"L",,"USD","H")} -> 639 | AF7: {=_xll.ciqfunctions.udf.CIQ(B$3,$Z$1,$H$2,$A7,"L",,"USD","H")} -> 9245 | AG7: {=_xll.ciqfunctions.udf.CIQ(C$3,$Z$1,$H$2,$A7,"L",,"USD","H")} -> 33680 | AH7: {=_xll.ciqfunctions.udf.CIQ(D$3,$Z$1,$H$2,$A7,"L",,"USD","H")} -> 17661 | AI7: {=_xll.ciqfunctions.udf.CIQ(E$3,$Z$1,$H$2,$A7,"L",,"USD","H")} -> 6403 | AJ7: {=_xll.ciqfunctions.udf.CIQ(F$3,$Z$1,$H$2,$A7,"L",,"USD","H")} -> 381 | AK7: {=_xll.ciqfunctions.udf.CIQ(G$3,$Z$1,$H$2,$A7,"L",,"USD","H")} -> 2891 | AL7: {=_xll.ciqfunctions.udf.CIQ(B$3,$AL$1,$AL$2,$A7,"L",,"USD","H")} -> -23.3123 | AM7: {=_xll.ciqfunctions.udf.CIQ(C$3,$AL$1,$AL$2,$A7,"L",,"USD","H")} -> -0.2622 | AN7: {=_xll.ciqfunctions.udf.CIQ(D$3,$AL$1,$AL$2,$A7,"L",,"USD","H")} -> 43.382 | AO7: {=_xll.ciqfunctions.udf.CIQ(E$3,$AL$1,$AL$2,$A7,"L",,"USD","H")} -> -37.0725 | AP7: {=_xll.ciqfunctions.udf.CIQ(F$3,$AL$1,$AL$2,$A7,"L",,"USD","H")} -> NM | AQ7: {=_xll.ciqfunctions.udf.CIQ(G$3,$AL$1,$AL$2,$A7,"L",,"USD","H")} -> -44.5313 | AR7: {=_xll.ciqfunctions.udf.CIQ(B$3,$AL$1,$AR$2,$A7,"L",,"USD","H")} -> -15.6248 | AS7: {=_xll.ciqfunctions.udf.CIQ(C$3,$AL$1,$AR$2,$A7,"L",,"USD","H")} -> -6.4705 | AT7: {=_xll.ciqfunctions.udf.CIQ(D$3,$AL$1,$AR$2,$A7,"L",,"USD","H")} -> -17.3523 | AU7: {=_xll.ciqfunctions.udf.CIQ(E$3,$AL$1,$AR$2,$A7,"L",,"USD","H")} -> -15.6835 | AV7: {=_xll.ciqfunctions.udf.CIQ(F$3,$AL$1,$AR$2,$A7,"L",,"USD","H")} -> -97.4999 | AW7: {=_xll.ciqfunctions.udf.CIQ(G$3,$AL$1,$AR$2,$A7,"L",,"USD","H")} -> -22.845 | AX7: {=_xll.ciqfunctions.udf.CIQ(B$3,$AX$1,$AX$2,$A7,"L",,"USD","H")} -> 6524 | AY7: {=_xll.ciqfunctions.udf.CIQ(C$3,$AX$1,$AX$2,$A7,"L",,"USD","H")} -> 15648 | AZ7: {=_xll.ciqfunctions.udf.CIQ(D$3,$AX$1,$AX$2,$A7,"L",,"USD","H")} -> 10074 | BA7: {=_xll.ciqfunctions.udf.CIQ(E$3,$AX$1,$AX$2,$A7,"L",,"USD","H")} -> 2910 | BB7: {=_xll.ciqfunctions.udf.CIQ(F$3,$AX$1,$AX$2,$A7,"L",,"USD","H")} -> 1263 | BC7: {=_xll.ciqfunctions.udf.CIQ(G$3,$AX$1,$AX$2,$A7,"L",,"USD","H")} -> 1939 | BD7: {=_xll.ciqfunctions.udf.CIQ(B$3,$AX$1,$BD$2,$A7,"L",,"USD","H")} -> 24308 | BE7: {=_xll.ciqfunctions.udf.CIQ(C$3,$AX$1,$BD$2,$A7,"L",,"USD","H")} -> 64294 | BF7: {=_xll.ciqfunctions.udf.CIQ(D$3,$AX$1,$BD$2,$A7,"L",,"USD","H")} -> 40081 | BG7: {=_xll.ciqfunctions.udf.CIQ(E$3,$AX$1,$BD$2,$A7,"L",,"USD","H")} -> 12565 | BH7: {=_xll.ciqfunctions.udf.CIQ(F$3,$AX$1,$BD$2,$A7,"L",,"USD","H")} -> 26961 | BI7: {=_xll.ciqfunctions.udf.CIQ(G$3,$AX$1,$BD$2,$A7,"L",,"USD","H")} -> 7389 | BJ7: =AX7/AX11-1 -> -0.0207145 | BK7: =AY7/AY11-1 -> -0.12819656 | BL7: =AZ7/AZ11-1 -> 0.12735004 | BM7: =BA7/BA11-1 -> -0.17164816 | BN7: =BB7/BB11-1 -> -0.78932444 | BO7: =BC7/BC11-1 -> -0.1072744 | BP7: =BD7/BD11-1 -> -0.017977619 | BQ7: =BE7/BE11-1 -> -0.031074809 | ... BU7: =BI7/BI11-1 -> -0.012693747 | BV7: {=_xll.ciqfunctions.udf.CIQ(B$3,$BV$1,$BV$2,$A7,"L",,"USD","H")/100} -> 0.071192 | BW7: {=_xll.ciqfunctions.udf.CIQ(C$3,$BV$1,$BV$2,$A7,"L",,"USD","H")/100} -> 0.04062 | BX7: {=_xll.ciqfunctions.udf.CIQ(D$3,$BV$1,$BV$2,$A7,"L",,"USD","H")/100} -> 0.0077 | BY7: {=_xll.ciqfunctions.udf.CIQ(E$3,$BV$1,$BV$2,$A7,"L",,"USD","H")/100} -> 0.08624 | BZ7: {=_xll.ciqfunctions.udf.CIQ(F$3,$BV$1,$BV$2,$A7,"L",,"USD","H")/100} -> -0.052536 | CA7: {=_xll.ciqfunctions.udf.CIQ(G$3,$BV$1,$BV$2,$A7,"L",,"USD","H")/100} -> 0.083172 | CB7: {=_xll.ciqfunctions.udf.CIQ(B$3,$BV$1,$CB$2,$A7,"L",,"USD","H")/100} -> 0.070402 | CC7: {=_xll.ciqfunctions.udf.CIQ(C$3,$BV$1,$CB$2,$A7,"L",,"USD","H")/100} -> 0.058622 | CD7: {=_xll.ciqfunctions.udf.CIQ(D$3,$BV$1,$CB$2,$A7,"L",,"USD","H")/100} -> 0.03161 | CE7: {=_xll.ciqfunctions.udf.CIQ(E$3,$BV$1,$CB$2,$A7,"L",,"USD","H")/100} -> 0.126879 | CF7: {=_xll.ciqfunctions.udf.CIQ(F$3,$BV$1,$CB$2,$A7,"L",,"USD","H")/100} -> -0.030975 | CG7: {=_xll.ciqfunctions.udf.CIQ(G$3,$BV$1,$CB$2,$A7,"L",,"USD","H")/100} -> 0.091608
A8: =EDATE(A4,-12) -> 45565 | B8: {=_xll.ciqfunctions.udf.CIQ(B$3,$B$1,$B$2,$A8,"L",,"USD","H")} -> 13482 | C8: {=_xll.ciqfunctions.udf.CIQ(C$3,$B$1,$B$2,$A8,"L",,"USD","H")} -> 87792 | D8: {=_xll.ciqfunctions.udf.CIQ(D$3,$B$1,$B$2,$A8,"L",,"USD","H")} -> 49416 | E8: {=_xll.ciqfunctions.udf.CIQ(E$3,$B$1,$B$2,$A8,"L",,"USD","H")} -> 5893 | F8: {=_xll.ciqfunctions.udf.CIQ(F$3,$B$1,$B$2,$A8,"L",,"USD","H")} -> 47223 | G8: {=_xll.ciqfunctions.udf.CIQ(G$3,$B$1,$B$2,$A8,"L",,"USD","H")} -> 3797 | H8: {=_xll.ciqfunctions.udf.CIQ(B$3,$B$1,$H$2,$A8,"L",,"USD","H")} -> 56924 | I8: {=_xll.ciqfunctions.udf.CIQ(C$3,$B$1,$H$2,$A8,"L",,"USD","H")} -> 341845 | J8: {=_xll.ciqfunctions.udf.CIQ(D$3,$B$1,$H$2,$A8,"L",,"USD","H")} -> 191689 | K8: {=_xll.ciqfunctions.udf.CIQ(E$3,$B$1,$H$2,$A8,"L",,"USD","H")} -> 23864 | L8: {=_xll.ciqfunctions.udf.CIQ(F$3,$B$1,$H$2,$A8,"L",,"USD","H")} -> 193929 | M8: {=_xll.ciqfunctions.udf.CIQ(G$3,$B$1,$H$2,$A8,"L",,"USD","H")} -> 14529 | N8: {=_xll.ciqfunctions.udf.CIQ(B$3,$N$1,$B$2,$A8,"L",,"USD","H")} -> -7.8973 | O8: {=_xll.ciqfunctions.udf.CIQ(C$3,$N$1,$B$2,$A8,"L",,"USD","H")} -> -0.8785 | P8: {=_xll.ciqfunctions.udf.CIQ(D$3,$N$1,$B$2,$A8,"L",,"USD","H")} -> -6.3648 | Q8: {=_xll.ciqfunctions.udf.CIQ(E$3,$N$1,$B$2,$A8,"L",,"USD","H")} -> -3.929 | R8: {=_xll.ciqfunctions.udf.CIQ(F$3,$N$1,$B$2,$A8,"L",,"USD","H")} -> -11.2734 | S8: {=_xll.ciqfunctions.udf.CIQ(G$3,$N$1,$B$2,$A8,"L",,"USD","H")} -> -5.7817 | T8: {=_xll.ciqfunctions.udf.CIQ(N$3,$N$1,$T$2,$A8,"L",,"USD","H")} -> -7.9481 | U8: {=_xll.ciqfunctions.udf.CIQ(O$3,$N$1,$T$2,$A8,"L",,"USD","H")} -> -1.4285 | V8: {=_xll.ciqfunctions.udf.CIQ(P$3,$N$1,$T$2,$A8,"L",,"USD","H")} -> -5.6022 | W8: {=_xll.ciqfunctions.udf.CIQ(Q$3,$N$1,$T$2,$A8,"L",,"USD","H")} -> 0.5774 | X8: {=_xll.ciqfunctions.udf.CIQ(R$3,$N$1,$T$2,$A8,"L",,"USD","H")} -> -14.339 | Y8: {=_xll.ciqfunctions.udf.CIQ(S$3,$N$1,$T$2,$A8,"L",,"USD","H")} -> -2.6859 | Z8: {=_xll.ciqfunctions.udf.CIQ(B$3,$Z$1,$B$2,$A8,"L",,"USD","H")} -> 2059 | AA8: {=_xll.ciqfunctions.udf.CIQ(C$3,$Z$1,$B$2,$A8,"L",,"USD","H")} -> 8610 | AB8: {=_xll.ciqfunctions.udf.CIQ(D$3,$Z$1,$B$2,$A8,"L",,"USD","H")} -> 4487 | AC8: {=_xll.ciqfunctions.udf.CIQ(E$3,$Z$1,$B$2,$A8,"L",,"USD","H")} -> 1673 | AD8: {=_xll.ciqfunctions.udf.CIQ(F$3,$Z$1,$B$2,$A8,"L",,"USD","H")} -> 206 | AE8: {=_xll.ciqfunctions.udf.CIQ(G$3,$Z$1,$B$2,$A8,"L",,"USD","H")} -> 812 | AF8: {=_xll.ciqfunctions.udf.CIQ(B$3,$Z$1,$H$2,$A8,"L",,"USD","H")} -> 9946 | AG8: {=_xll.ciqfunctions.udf.CIQ(C$3,$Z$1,$H$2,$A8,"L",,"USD","H")} -> 33700 | AH8: {=_xll.ciqfunctions.udf.CIQ(D$3,$Z$1,$H$2,$A8,"L",,"USD","H")} -> 16681 | AI8: {=_xll.ciqfunctions.udf.CIQ(E$3,$Z$1,$H$2,$A8,"L",,"USD","H")} -> 7140 | AJ8: {=_xll.ciqfunctions.udf.CIQ(F$3,$Z$1,$H$2,$A8,"L",,"USD","H")} -> 2711 | AK8: {=_xll.ciqfunctions.udf.CIQ(G$3,$Z$1,$H$2,$A8,"L",,"USD","H")} -> 3404 | AL8: {=_xll.ciqfunctions.udf.CIQ(B$3,$AL$1,$AL$2,$A8,"L",,"USD","H")} -> -26.4118 | AM8: {=_xll.ciqfunctions.udf.CIQ(C$3,$AL$1,$AL$2,$A8,"L",,"USD","H")} -> -5.0717 | AN8: {=_xll.ciqfunctions.udf.CIQ(D$3,$AL$1,$AL$2,$A8,"L",,"USD","H")} -> -31.2443 | AO8: {=_xll.ciqfunctions.udf.CIQ(E$3,$AL$1,$AL$2,$A8,"L",,"USD","H")} -> -17.5863 | AP8: {=_xll.ciqfunctions.udf.CIQ(F$3,$AL$1,$AL$2,$A8,"L",,"USD","H")} -> -95.7596 | AQ8: {=_xll.ciqfunctions.udf.CIQ(G$3,$AL$1,$AL$2,$A8,"L",,"USD","H")} -> -10.7693 | AR8: {=_xll.ciqfunctions.udf.CIQ(B$3,$AL$1,$AR$2,$A8,"L",,"USD","H")} -> -11.1885 | AS8: {=_xll.ciqfunctions.udf.CIQ(C$3,$AL$1,$AR$2,$A8,"L",,"USD","H")} -> -18.0647 | AT8: {=_xll.ciqfunctions.udf.CIQ(D$3,$AL$1,$AR$2,$A8,"L",,"USD","H")} -> -34.4893 | AU8: {=_xll.ciqfunctions.udf.CIQ(E$3,$AL$1,$AR$2,$A8,"L",,"USD","H")} -> -9.4254 | AV8: {=_xll.ciqfunctions.udf.CIQ(F$3,$AL$1,$AR$2,$A8,"L",,"USD","H")} -> -89.4395 | AW8: {=_xll.ciqfunctions.udf.CIQ(G$3,$AL$1,$AR$2,$A8,"L",,"USD","H")} -> -10.3267 | AX8: {=_xll.ciqfunctions.udf.CIQ(B$3,$AX$1,$AX$2,$A8,"L",,"USD","H")} -> 5663 | AY8: {=_xll.ciqfunctions.udf.CIQ(C$3,$AX$1,$AX$2,$A8,"L",,"USD","H")} -> 17267 | AZ8: {=_xll.ciqfunctions.udf.CIQ(D$3,$AX$1,$AX$2,$A8,"L",,"USD","H")} -> 9606 | BA8: {=_xll.ciqfunctions.udf.CIQ(E$3,$AX$1,$AX$2,$A8,"L",,"USD","H")} -> 3142 | BB8: {=_xll.ciqfunctions.udf.CIQ(F$3,$AX$1,$AX$2,$A8,"L",,"USD","H")} -> 8130 | BC8: {=_xll.ciqfunctions.udf.CIQ(G$3,$AX$1,$AX$2,$A8,"L",,"USD","H")} -> 1946 | BD8: {=_xll.ciqfunctions.udf.CIQ(B$3,$AX$1,$BD$2,$A8,"L",,"USD","H")} -> 24446 | BE8: {=_xll.ciqfunctions.udf.CIQ(C$3,$AX$1,$BD$2,$A8,"L",,"USD","H")} -> 66595 | BF8: {=_xll.ciqfunctions.udf.CIQ(D$3,$AX$1,$BD$2,$A8,"L",,"USD","H")} -> 38943 | BG8: {=_xll.ciqfunctions.udf.CIQ(E$3,$AX$1,$BD$2,$A8,"L",,"USD","H")} -> 13168 | BH8: {=_xll.ciqfunctions.udf.CIQ(F$3,$AX$1,$BD$2,$A8,"L",,"USD","H")} -> 31693 | BI8: {=_xll.ciqfunctions.udf.CIQ(G$3,$AX$1,$BD$2,$A8,"L",,"USD","H")} -> 7612 | BJ8: =AX8/AX12-1 -> -0.091885824 | BK8: =AY8/AY12-1 -> 0.072950972 | BL8: =AZ8/AZ12-1 -> -0.16931857 | BM8: =BA8/BA12-1 -> -0.09556707 | BN8: =BB8/BB12-1 -> -0.3634513 | BO8: =BC8/BC12-1 -> 0.078116343 | BP8: =BD8/BD12-1 -> -0.040656149 | BQ8: =BE8/BE12-1 -> 0.12802141 | ... BU8: =BI8/BI12-1 -> 0.013446944 | BV8: {=_xll.ciqfunctions.udf.CIQ(B$3,$BV$1,$BV$2,$A8,"L",,"USD","H")/100} -> 0.067448 | BW8: {=_xll.ciqfunctions.udf.CIQ(C$3,$BV$1,$BV$2,$A8,"L",,"USD","H")/100} -> 0.05476 | BX8: {=_xll.ciqfunctions.udf.CIQ(D$3,$BV$1,$BV$2,$A8,"L",,"USD","H")/100} -> 0.033936 | BY8: {=_xll.ciqfunctions.udf.CIQ(E$3,$BV$1,$BV$2,$A8,"L",,"USD","H")/100} -> 0.136252 | BZ8: {=_xll.ciqfunctions.udf.CIQ(F$3,$BV$1,$BV$2,$A8,"L",,"USD","H")/100} -> -0.029452 | CA8: {=_xll.ciqfunctions.udf.CIQ(G$3,$BV$1,$BV$2,$A8,"L",,"USD","H")/100} -> 0.100516 | CB8: {=_xll.ciqfunctions.udf.CIQ(B$3,$BV$1,$CB$2,$A8,"L",,"USD","H")/100} -> 0.085767 | CC8: {=_xll.ciqfunctions.udf.CIQ(C$3,$BV$1,$CB$2,$A8,"L",,"USD","H")/100} -> 0.061747 | CD8: {=_xll.ciqfunctions.udf.CIQ(D$3,$BV$1,$CB$2,$A8,"L",,"USD","H")/100} -> 0.026823 | CE8: {=_xll.ciqfunctions.udf.CIQ(E$3,$BV$1,$CB$2,$A8,"L",,"USD","H")/100} -> 0.11076 | CF8: {=_xll.ciqfunctions.udf.CIQ(F$3,$BV$1,$CB$2,$A8,"L",,"USD","H")/100} -> -0.015098 | CG8: {=_xll.ciqfunctions.udf.CIQ(G$3,$BV$1,$CB$2,$A8,"L",,"USD","H")/100} -> 0.101028
A9: =EDATE(A5,-12) -> 45473 | B9: {=_xll.ciqfunctions.udf.CIQ(B$3,$B$1,$B$2,$A9,"L",,"USD","H")} -> 14023 | C9: {=_xll.ciqfunctions.udf.CIQ(C$3,$B$1,$B$2,$A9,"L",,"USD","H")} -> 89986 | D9: {=_xll.ciqfunctions.udf.CIQ(D$3,$B$1,$B$2,$A9,"L",,"USD","H")} -> 49778 | E9: {=_xll.ciqfunctions.udf.CIQ(E$3,$B$1,$B$2,$A9,"L",,"USD","H")} -> 6052 | F9: {=_xll.ciqfunctions.udf.CIQ(F$3,$B$1,$B$2,$A9,"L",,"USD","H")} -> 47610 | G9: {=_xll.ciqfunctions.udf.CIQ(G$3,$B$1,$B$2,$A9,"L",,"USD","H")} -> 3715 | H9: {=_xll.ciqfunctions.udf.CIQ(B$3,$B$1,$H$2,$A9,"L",,"USD","H")} -> 58080 | I9: {=_xll.ciqfunctions.udf.CIQ(C$3,$B$1,$H$2,$A9,"L",,"USD","H")} -> 342623 | J9: {=_xll.ciqfunctions.udf.CIQ(D$3,$B$1,$H$2,$A9,"L",,"USD","H")} -> 195048 | K9: {=_xll.ciqfunctions.udf.CIQ(E$3,$B$1,$H$2,$A9,"L",,"USD","H")} -> 24105 | L9: {=_xll.ciqfunctions.udf.CIQ(F$3,$B$1,$H$2,$A9,"L",,"USD","H")} -> 199929 | M9: {=_xll.ciqfunctions.udf.CIQ(G$3,$B$1,$H$2,$A9,"L",,"USD","H")} -> 14762 | N9: {=_xll.ciqfunctions.udf.CIQ(B$3,$N$1,$B$2,$A9,"L",,"USD","H")} -> 9.8722 | O9: {=_xll.ciqfunctions.udf.CIQ(C$3,$N$1,$B$2,$A9,"L",,"USD","H")} -> 12.1237 | P9: {=_xll.ciqfunctions.udf.CIQ(D$3,$N$1,$B$2,$A9,"L",,"USD","H")} -> 4.723 | Q9: {=_xll.ciqfunctions.udf.CIQ(E$3,$N$1,$B$2,$A9,"L",,"USD","H")} -> 10.4178 | R9: {=_xll.ciqfunctions.udf.CIQ(F$3,$N$1,$B$2,$A9,"L",,"USD","H")} -> -2.3585 | S9: {=_xll.ciqfunctions.udf.CIQ(G$3,$N$1,$B$2,$A9,"L",,"USD","H")} -> 11.2608 | T9: {=_xll.ciqfunctions.udf.CIQ(N$3,$N$1,$T$2,$A9,"L",,"USD","H")} -> -15.5508 | U9: {=_xll.ciqfunctions.udf.CIQ(O$3,$N$1,$T$2,$A9,"L",,"USD","H")} -> -6.302 | V9: {=_xll.ciqfunctions.udf.CIQ(P$3,$N$1,$T$2,$A9,"L",,"USD","H")} -> -9.083 | W9: {=_xll.ciqfunctions.udf.CIQ(Q$3,$N$1,$T$2,$A9,"L",,"USD","H")} -> -4.4401 | X9: {=_xll.ciqfunctions.udf.CIQ(R$3,$N$1,$T$2,$A9,"L",,"USD","H")} -> -12.1346 | Y9: {=_xll.ciqfunctions.udf.CIQ(S$3,$N$1,$T$2,$A9,"L",,"USD","H")} -> -8.2194 | Z9: {=_xll.ciqfunctions.udf.CIQ(B$3,$Z$1,$B$2,$A9,"L",,"USD","H")} -> 2329 | AA9: {=_xll.ciqfunctions.udf.CIQ(C$3,$Z$1,$B$2,$A9,"L",,"USD","H")} -> 9240 | AB9: {=_xll.ciqfunctions.udf.CIQ(D$3,$Z$1,$B$2,$A9,"L",,"USD","H")} -> 4434 | AC9: {=_xll.ciqfunctions.udf.CIQ(E$3,$Z$1,$B$2,$A9,"L",,"USD","H")} -> 1690 | AD9: {=_xll.ciqfunctions.udf.CIQ(F$3,$Z$1,$B$2,$A9,"L",,"USD","H")} -> -129 | AE9: {=_xll.ciqfunctions.udf.CIQ(G$3,$Z$1,$B$2,$A9,"L",,"USD","H")} -> 844 | AF9: {=_xll.ciqfunctions.udf.CIQ(B$3,$Z$1,$H$2,$A9,"L",,"USD","H")} -> 10685 | AG9: {=_xll.ciqfunctions.udf.CIQ(C$3,$Z$1,$H$2,$A9,"L",,"USD","H")} -> 34160 | AH9: {=_xll.ciqfunctions.udf.CIQ(D$3,$Z$1,$H$2,$A9,"L",,"USD","H")} -> 18720 | AI9: {=_xll.ciqfunctions.udf.CIQ(E$3,$Z$1,$H$2,$A9,"L",,"USD","H")} -> 7497 | AJ9: {=_xll.ciqfunctions.udf.CIQ(F$3,$Z$1,$H$2,$A9,"L",,"USD","H")} -> 7363 | AK9: {=_xll.ciqfunctions.udf.CIQ(G$3,$Z$1,$H$2,$A9,"L",,"USD","H")} -> 3502 | AL9: {=_xll.ciqfunctions.udf.CIQ(B$3,$AL$1,$AL$2,$A9,"L",,"USD","H")} -> 4.3458 | AM9: {=_xll.ciqfunctions.udf.CIQ(C$3,$AL$1,$AL$2,$A9,"L",,"USD","H")} -> 17.2588 | AN9: {=_xll.ciqfunctions.udf.CIQ(D$3,$AL$1,$AL$2,$A9,"L",,"USD","H")} -> -26.223 | AO9: {=_xll.ciqfunctions.udf.CIQ(E$3,$AL$1,$AL$2,$A9,"L",,"USD","H")} -> 8.8216 | AP9: {=_xll.ciqfunctions.udf.CIQ(F$3,$AL$1,$AL$2,$A9,"L",,"USD","H")} -> NM | AQ9: {=_xll.ciqfunctions.udf.CIQ(G$3,$AL$1,$AL$2,$A9,"L",,"USD","H")} -> 22.3188 | AR9: {=_xll.ciqfunctions.udf.CIQ(B$3,$AL$1,$AR$2,$A9,"L",,"USD","H")} -> -17.35 | AS9: {=_xll.ciqfunctions.udf.CIQ(C$3,$AL$1,$AR$2,$A9,"L",,"USD","H")} -> -33.9521 | AT9: {=_xll.ciqfunctions.udf.CIQ(D$3,$AL$1,$AR$2,$A9,"L",,"USD","H")} -> -37.9475 | AU9: {=_xll.ciqfunctions.udf.CIQ(E$3,$AL$1,$AR$2,$A9,"L",,"USD","H")} -> -13.8969 | AV9: {=_xll.ciqfunctions.udf.CIQ(F$3,$AL$1,$AR$2,$A9,"L",,"USD","H")} -> -60.5202 | AW9: {=_xll.ciqfunctions.udf.CIQ(G$3,$AL$1,$AR$2,$A9,"L",,"USD","H")} -> -26.7211 | AX9: {=_xll.ciqfunctions.udf.CIQ(B$3,$AX$1,$AX$2,$A9,"L",,"USD","H")} -> 6125 | AY9: {=_xll.ciqfunctions.udf.CIQ(C$3,$AX$1,$AX$2,$A9,"L",,"USD","H")} -> 16649 | AZ9: {=_xll.ciqfunctions.udf.CIQ(D$3,$AX$1,$AX$2,$A9,"L",,"USD","H")} -> 9758 | BA9: {=_xll.ciqfunctions.udf.CIQ(E$3,$AX$1,$AX$2,$A9,"L",,"USD","H")} -> 3175 | BB9: {=_xll.ciqfunctions.udf.CIQ(F$3,$AX$1,$AX$2,$A9,"L",,"USD","H")} -> 7848 | BC9: {=_xll.ciqfunctions.udf.CIQ(G$3,$AX$1,$AX$2,$A9,"L",,"USD","H")} -> 1927 | BD9: {=_xll.ciqfunctions.udf.CIQ(B$3,$AX$1,$BD$2,$A9,"L",,"USD","H")} -> 25019 | BE9: {=_xll.ciqfunctions.udf.CIQ(C$3,$AX$1,$BD$2,$A9,"L",,"USD","H")} -> 65421 | BF9: {=_xll.ciqfunctions.udf.CIQ(D$3,$AX$1,$BD$2,$A9,"L",,"USD","H")} -> 40901 | BG9: {=_xll.ciqfunctions.udf.CIQ(E$3,$AX$1,$BD$2,$A9,"L",,"USD","H")} -> 13500 | BH9: {=_xll.ciqfunctions.udf.CIQ(F$3,$AX$1,$BD$2,$A9,"L",,"USD","H")} -> 36335 | BI9: {=_xll.ciqfunctions.udf.CIQ(G$3,$AX$1,$BD$2,$A9,"L",,"USD","H")} -> 7471 | BJ9: =AX9/AX13-1 -> 0.1357315 | BK9: =AY9/AY13-1 -> 0.23426496 | BL9: =AZ9/AZ13-1 -> -0.034339436 | BM9: =BA9/BA13-1 -> 0.10243056 | BN9: =BB9/BB13-1 -> -0.17666807 | BO9: =BC9/BC13-1 -> 0.20739348 | BP9: =BD9/BD13-1 -> -0.12609592 | BQ9: =BE9/BE13-1 -> -0.14959248 | ... BU9: =BI9/BI13-1 -> -0.15352368 | BV9: {=_xll.ciqfunctions.udf.CIQ(B$3,$BV$1,$BV$2,$A9,"L",,"USD","H")/100} -> 0.083272 | BW9: {=_xll.ciqfunctions.udf.CIQ(C$3,$BV$1,$BV$2,$A9,"L",,"USD","H")/100} -> 0.069184 | BX9: {=_xll.ciqfunctions.udf.CIQ(D$3,$BV$1,$BV$2,$A9,"L",,"USD","H")/100} -> 0.03174 | BY9: {=_xll.ciqfunctions.udf.CIQ(E$3,$BV$1,$BV$2,$A9,"L",,"USD","H")/100} -> 0.141836 | BZ9: {=_xll.ciqfunctions.udf.CIQ(F$3,$BV$1,$BV$2,$A9,"L",,"USD","H")/100} -> -0.003476 | CA9: {=_xll.ciqfunctions.udf.CIQ(G$3,$BV$1,$BV$2,$A9,"L",,"USD","H")/100} -> 0.130536 | CB9: {=_xll.ciqfunctions.udf.CIQ(B$3,$BV$1,$CB$2,$A9,"L",,"USD","H")/100} -> 0.092388 | CC9: {=_xll.ciqfunctions.udf.CIQ(C$3,$BV$1,$CB$2,$A9,"L",,"USD","H")/100} -> 0.065376 | CD9: {=_xll.ciqfunctions.udf.CIQ(D$3,$BV$1,$CB$2,$A9,"L",,"USD","H")/100} -> 0.038862 | CE9: {=_xll.ciqfunctions.udf.CIQ(E$3,$BV$1,$CB$2,$A9,"L",,"USD","H")/100} -> 0.118309 | CF9: {=_xll.ciqfunctions.udf.CIQ(F$3,$BV$1,$CB$2,$A9,"L",,"USD","H")/100} -> 0.017363 | CG9: {=_xll.ciqfunctions.udf.CIQ(G$3,$BV$1,$CB$2,$A9,"L",,"USD","H")/100} -> 0.117466
A10: =EDATE(A6,-12) -> 45382 | B10: {=_xll.ciqfunctions.udf.CIQ(B$3,$B$1,$B$2,$A10,"L",,"USD","H")} -> 14269 | C10: {=_xll.ciqfunctions.udf.CIQ(C$3,$B$1,$B$2,$A10,"L",,"USD","H")} -> 80411 | D10: {=_xll.ciqfunctions.udf.CIQ(D$3,$B$1,$B$2,$A10,"L",,"USD","H")} -> 47215 | E10: {=_xll.ciqfunctions.udf.CIQ(E$3,$B$1,$B$2,$A10,"L",,"USD","H")} -> 5860 | F10: {=_xll.ciqfunctions.udf.CIQ(F$3,$B$1,$B$2,$A10,"L",,"USD","H")} -> 48436 | G10: {=_xll.ciqfunctions.udf.CIQ(G$3,$B$1,$B$2,$A10,"L",,"USD","H")} -> 3378 | H10: {=_xll.ciqfunctions.udf.CIQ(B$3,$B$1,$H$2,$A10,"L",,"USD","H")} -> 56820 | I10: {=_xll.ciqfunctions.udf.CIQ(C$3,$B$1,$H$2,$A10,"L",,"USD","H")} -> 332893 | J10: {=_xll.ciqfunctions.udf.CIQ(D$3,$B$1,$H$2,$A10,"L",,"USD","H")} -> 192803 | K10: {=_xll.ciqfunctions.udf.CIQ(E$3,$B$1,$H$2,$A10,"L",,"USD","H")} -> 23534 | L10: {=_xll.ciqfunctions.udf.CIQ(F$3,$B$1,$H$2,$A10,"L",,"USD","H")} -> 201079 | M10: {=_xll.ciqfunctions.udf.CIQ(G$3,$B$1,$H$2,$A10,"L",,"USD","H")} -> 14386 | N10: {=_xll.ciqfunctions.udf.CIQ(B$3,$N$1,$B$2,$A10,"L",,"USD","H")} -> -6.7995 | O10: {=_xll.ciqfunctions.udf.CIQ(C$3,$N$1,$B$2,$A10,"L",,"USD","H")} -> -4.4808 | P10: {=_xll.ciqfunctions.udf.CIQ(D$3,$N$1,$B$2,$A10,"L",,"USD","H")} -> -4.0561 | Q10: {=_xll.ciqfunctions.udf.CIQ(E$3,$N$1,$B$2,$A10,"L",,"USD","H")} -> 4.6615 | R10: {=_xll.ciqfunctions.udf.CIQ(F$3,$N$1,$B$2,$A10,"L",,"USD","H")} -> -13.0538 | S10: {=_xll.ciqfunctions.udf.CIQ(G$3,$N$1,$B$2,$A10,"L",,"USD","H")} -> -1.1992 | T10: {=_xll.ciqfunctions.udf.CIQ(N$3,$N$1,$T$2,$A10,"L",,"USD","H")} -> -26.8698 | U10: {=_xll.ciqfunctions.udf.CIQ(O$3,$N$1,$T$2,$A10,"L",,"USD","H")} -> -16.2332 | V10: {=_xll.ciqfunctions.udf.CIQ(P$3,$N$1,$T$2,$A10,"L",,"USD","H")} -> -17.3605 | W10: {=_xll.ciqfunctions.udf.CIQ(Q$3,$N$1,$T$2,$A10,"L",,"USD","H")} -> -17.2242 | X10: {=_xll.ciqfunctions.udf.CIQ(R$3,$N$1,$T$2,$A10,"L",,"USD","H")} -> -18.2679 | Y10: {=_xll.ciqfunctions.udf.CIQ(S$3,$N$1,$T$2,$A10,"L",,"USD","H")} -> -21.3407 | Z10: {=_xll.ciqfunctions.udf.CIQ(B$3,$Z$1,$B$2,$A10,"L",,"USD","H")} -> 2551 | AA10: {=_xll.ciqfunctions.udf.CIQ(C$3,$Z$1,$B$2,$A10,"L",,"USD","H")} -> 8220 | AB10: {=_xll.ciqfunctions.udf.CIQ(D$3,$Z$1,$B$2,$A10,"L",,"USD","H")} -> 5501 | AC10: {=_xll.ciqfunctions.udf.CIQ(E$3,$Z$1,$B$2,$A10,"L",,"USD","H")} -> 1789 | AD10: {=_xll.ciqfunctions.udf.CIQ(F$3,$Z$1,$B$2,$A10,"L",,"USD","H")} -> 2263 | AE10: {=_xll.ciqfunctions.udf.CIQ(G$3,$Z$1,$B$2,$A10,"L",,"USD","H")} -> 596 | AF10: {=_xll.ciqfunctions.udf.CIQ(B$3,$Z$1,$H$2,$A10,"L",,"USD","H")} -> 10588 | AG10: {=_xll.ciqfunctions.udf.CIQ(C$3,$Z$1,$H$2,$A10,"L",,"USD","H")} -> 32800 | AH10: {=_xll.ciqfunctions.udf.CIQ(D$3,$Z$1,$H$2,$A10,"L",,"USD","H")} -> 20296 | AI10: {=_xll.ciqfunctions.udf.CIQ(E$3,$Z$1,$H$2,$A10,"L",,"USD","H")} -> 7360 | AJ10: {=_xll.ciqfunctions.udf.CIQ(F$3,$Z$1,$H$2,$A10,"L",,"USD","H")} -> 9284 | AK10: {=_xll.ciqfunctions.udf.CIQ(G$3,$Z$1,$H$2,$A10,"L",,"USD","H")} -> 3348 | AL10: {=_xll.ciqfunctions.udf.CIQ(B$3,$AL$1,$AL$2,$A10,"L",,"USD","H")} -> -12.637 | AM10: {=_xll.ciqfunctions.udf.CIQ(C$3,$AL$1,$AL$2,$A10,"L",,"USD","H")} -> -28.084 | AN10: {=_xll.ciqfunctions.udf.CIQ(D$3,$AL$1,$AL$2,$A10,"L",,"USD","H")} -> -16.3219 | AO10: {=_xll.ciqfunctions.udf.CIQ(E$3,$AL$1,$AL$2,$A10,"L",,"USD","H")} -> -11.567 | AP10: {=_xll.ciqfunctions.udf.CIQ(F$3,$AL$1,$AL$2,$A10,"L",,"USD","H")} -> -72.4629 | AQ10: {=_xll.ciqfunctions.udf.CIQ(G$3,$AL$1,$AL$2,$A10,"L",,"USD","H")} -> -40.1006 | AR10: {=_xll.ciqfunctions.udf.CIQ(B$3,$AL$1,$AR$2,$A10,"L",,"USD","H")} -> -33.1608 | AS10: {=_xll.ciqfunctions.udf.CIQ(C$3,$AL$1,$AR$2,$A10,"L",,"USD","H")} -> -46.831 | AT10: {=_xll.ciqfunctions.udf.CIQ(D$3,$AL$1,$AR$2,$A10,"L",,"USD","H")} -> -43.2756 | AU10: {=_xll.ciqfunctions.udf.CIQ(E$3,$AL$1,$AR$2,$A10,"L",,"USD","H")} -> -21.6355 | AV10: {=_xll.ciqfunctions.udf.CIQ(F$3,$AL$1,$AR$2,$A10,"L",,"USD","H")} -> -64.4496 | AW10: {=_xll.ciqfunctions.udf.CIQ(G$3,$AL$1,$AR$2,$A10,"L",,"USD","H")} -> -44.3947 | AX10: {=_xll.ciqfunctions.udf.CIQ(B$3,$AX$1,$AX$2,$A10,"L",,"USD","H")} -> 5996 | AY10: {=_xll.ciqfunctions.udf.CIQ(C$3,$AX$1,$AX$2,$A10,"L",,"USD","H")} -> 14730 | AZ10: {=_xll.ciqfunctions.udf.CIQ(D$3,$AX$1,$AX$2,$A10,"L",,"USD","H")} -> 10643 | BA10: {=_xll.ciqfunctions.udf.CIQ(E$3,$AX$1,$AX$2,$A10,"L",,"USD","H")} -> 3338 | BB10: {=_xll.ciqfunctions.udf.CIQ(F$3,$AX$1,$AX$2,$A10,"L",,"USD","H")} -> 9720 | BC10: {=_xll.ciqfunctions.udf.CIQ(G$3,$AX$1,$AX$2,$A10,"L",,"USD","H")} -> 1567 | BD10: {=_xll.ciqfunctions.udf.CIQ(B$3,$AX$1,$BD$2,$A10,"L",,"USD","H")} -> 24287 | BE10: {=_xll.ciqfunctions.udf.CIQ(C$3,$AX$1,$BD$2,$A10,"L",,"USD","H")} -> 62261 | BF10: {=_xll.ciqfunctions.udf.CIQ(D$3,$AX$1,$BD$2,$A10,"L",,"USD","H")} -> 41248 | BG10: {=_xll.ciqfunctions.udf.CIQ(E$3,$AX$1,$BD$2,$A10,"L",,"USD","H")} -> 13205 | BH10: {=_xll.ciqfunctions.udf.CIQ(F$3,$AX$1,$BD$2,$A10,"L",,"USD","H")} -> 38019 | BI10: {=_xll.ciqfunctions.udf.CIQ(G$3,$AX$1,$BD$2,$A10,"L",,"USD","H")} -> 7140 | BJ10: =AX10/AX14-1 -> -0.072113897 | BK10: =AY10/AY14-1 -> -0.21752988 | BL10: =AZ10/AZ14-1 -> -0.080279986 | BM10: =BA10/BA14-1 -> 0.00089955022 | BN10: =BB10/BB14-1 -> -0.38709881 | BO10: =BC10/BC14-1 -> -0.18001047 | BP10: =BD10/BD14-1 -> -0.25593579 | BQ10: =BE10/BE14-1 -> -0.33715533 | ... BU10: =BI10/BI14-1 -> -0.30921053 | BV10: {=_xll.ciqfunctions.udf.CIQ(B$3,$BV$1,$BV$2,$A10,"L",,"USD","H")/100} -> 0.095244 | BW10: {=_xll.ciqfunctions.udf.CIQ(C$3,$BV$1,$BV$2,$A10,"L",,"USD","H")/100} -> 0.068704 | BX10: {=_xll.ciqfunctions.udf.CIQ(D$3,$BV$1,$BV$2,$A10,"L",,"USD","H")/100} -> 0.053792 | BY10: {=_xll.ciqfunctions.udf.CIQ(E$3,$BV$1,$BV$2,$A10,"L",,"USD","H")/100} -> 0.154064 | BZ10: {=_xll.ciqfunctions.udf.CIQ(F$3,$BV$1,$BV$2,$A10,"L",,"USD","H")/100} -> 0.028064 | CA10: {=_xll.ciqfunctions.udf.CIQ(G$3,$BV$1,$BV$2,$A10,"L",,"USD","H")/100} -> 0.063312 | CB10: {=_xll.ciqfunctions.udf.CIQ(B$3,$BV$1,$CB$2,$A10,"L",,"USD","H")/100} -> 0.084309 | CC10: {=_xll.ciqfunctions.udf.CIQ(C$3,$BV$1,$CB$2,$A10,"L",,"USD","H")/100} -> 0.070964 | CD10: {=_xll.ciqfunctions.udf.CIQ(D$3,$BV$1,$CB$2,$A10,"L",,"USD","H")/100} -> 0.048015 | CE10: {=_xll.ciqfunctions.udf.CIQ(E$3,$BV$1,$CB$2,$A10,"L",,"USD","H")/100} -> 0.144822 | CF10: {=_xll.ciqfunctions.udf.CIQ(F$3,$BV$1,$CB$2,$A10,"L",,"USD","H")/100} -> 0.030259 | CG10: {=_xll.ciqfunctions.udf.CIQ(G$3,$BV$1,$CB$2,$A10,"L",,"USD","H")/100} -> 0.097575
A11: =EDATE(A7,-12) -> 45291 | B11: {=_xll.ciqfunctions.udf.CIQ(B$3,$B$1,$B$2,$A11,"L",,"USD","H")} -> 15150 | C11: {=_xll.ciqfunctions.udf.CIQ(C$3,$B$1,$B$2,$A11,"L",,"USD","H")} -> 83656 | D11: {=_xll.ciqfunctions.udf.CIQ(D$3,$B$1,$B$2,$A11,"L",,"USD","H")} -> 45280 | E11: {=_xll.ciqfunctions.udf.CIQ(E$3,$B$1,$B$2,$A11,"L",,"USD","H")} -> 6059 | F11: {=_xll.ciqfunctions.udf.CIQ(F$3,$B$1,$B$2,$A11,"L",,"USD","H")} -> 50660 | G11: {=_xll.ciqfunctions.udf.CIQ(G$3,$B$1,$B$2,$A11,"L",,"USD","H")} -> 3639 | H11: {=_xll.ciqfunctions.udf.CIQ(B$3,$B$1,$H$2,$A11,"L",,"USD","H")} -> 57861 | I11: {=_xll.ciqfunctions.udf.CIQ(C$3,$B$1,$H$2,$A11,"L",,"USD","H")} -> 336665 | J11: {=_xll.ciqfunctions.udf.CIQ(D$3,$B$1,$H$2,$A11,"L",,"USD","H")} -> 194799 | K11: {=_xll.ciqfunctions.udf.CIQ(E$3,$B$1,$H$2,$A11,"L",,"USD","H")} -> 23273 | L11: {=_xll.ciqfunctions.udf.CIQ(F$3,$B$1,$H$2,$A11,"L",,"USD","H")} -> 208351 | M11: {=_xll.ciqfunctions.udf.CIQ(G$3,$B$1,$H$2,$A11,"L",,"USD","H")} -> 14427 | N11: {=_xll.ciqfunctions.udf.CIQ(B$3,$N$1,$B$2,$A11,"L",,"USD","H")} -> -20.7968 | O11: {=_xll.ciqfunctions.udf.CIQ(C$3,$N$1,$B$2,$A11,"L",,"USD","H")} -> -10.805 | P11: {=_xll.ciqfunctions.udf.CIQ(D$3,$N$1,$B$2,$A11,"L",,"USD","H")} -> -15.4372 | Q11: {=_xll.ciqfunctions.udf.CIQ(E$3,$N$1,$B$2,$A11,"L",,"USD","H")} -> -6.9707 | R11: {=_xll.ciqfunctions.udf.CIQ(F$3,$N$1,$B$2,$A11,"L",,"USD","H")} -> -26.2591 | S11: {=_xll.ciqfunctions.udf.CIQ(G$3,$N$1,$B$2,$A11,"L",,"USD","H")} -> -12.1439 | T11: {=_xll.ciqfunctions.udf.CIQ(N$3,$N$1,$T$2,$A11,"L",,"USD","H")} -> -28.1899 | U11: {=_xll.ciqfunctions.udf.CIQ(O$3,$N$1,$T$2,$A11,"L",,"USD","H")} -> -15.9886 | V11: {=_xll.ciqfunctions.udf.CIQ(P$3,$N$1,$T$2,$A11,"L",,"USD","H")} -> -17.4287 | W11: {=_xll.ciqfunctions.udf.CIQ(Q$3,$N$1,$T$2,$A11,"L",,"USD","H")} -> -21.4016 | X11: {=_xll.ciqfunctions.udf.CIQ(R$3,$N$1,$T$2,$A11,"L",,"USD","H")} -> -12.8483 | Y11: {=_xll.ciqfunctions.udf.CIQ(S$3,$N$1,$T$2,$A11,"L",,"USD","H")} -> -27.2356 | Z11: {=_xll.ciqfunctions.udf.CIQ(B$3,$Z$1,$B$2,$A11,"L",,"USD","H")} -> 3007 | AA11: {=_xll.ciqfunctions.udf.CIQ(C$3,$Z$1,$B$2,$A11,"L",,"USD","H")} -> 7630 | AB11: {=_xll.ciqfunctions.udf.CIQ(D$3,$Z$1,$B$2,$A11,"L",,"USD","H")} -> 2259 | AC11: {=_xll.ciqfunctions.udf.CIQ(E$3,$Z$1,$B$2,$A11,"L",,"USD","H")} -> 1988 | AD11: {=_xll.ciqfunctions.udf.CIQ(F$3,$Z$1,$B$2,$A11,"L",,"USD","H")} -> 371 | AE11: {=_xll.ciqfunctions.udf.CIQ(G$3,$Z$1,$B$2,$A11,"L",,"USD","H")} -> 1152 | AF11: {=_xll.ciqfunctions.udf.CIQ(B$3,$Z$1,$H$2,$A11,"L",,"USD","H")} -> 10957 | AG11: {=_xll.ciqfunctions.udf.CIQ(C$3,$Z$1,$H$2,$A11,"L",,"USD","H")} -> 36010 | AH11: {=_xll.ciqfunctions.udf.CIQ(D$3,$Z$1,$H$2,$A11,"L",,"USD","H")} -> 21369 | AI11: {=_xll.ciqfunctions.udf.CIQ(E$3,$Z$1,$H$2,$A11,"L",,"USD","H")} -> 7594 | AJ11: {=_xll.ciqfunctions.udf.CIQ(F$3,$Z$1,$H$2,$A11,"L",,"USD","H")} -> 15239 | AK11: {=_xll.ciqfunctions.udf.CIQ(G$3,$Z$1,$H$2,$A11,"L",,"USD","H")} -> 3747 | AL11: {=_xll.ciqfunctions.udf.CIQ(B$3,$AL$1,$AL$2,$A11,"L",,"USD","H")} -> -7.4485 | AM11: {=_xll.ciqfunctions.udf.CIQ(C$3,$AL$1,$AL$2,$A11,"L",,"USD","H")} -> -40.1569 | AN11: {=_xll.ciqfunctions.udf.CIQ(D$3,$AL$1,$AL$2,$A11,"L",,"USD","H")} -> -64.442 | AO11: {=_xll.ciqfunctions.udf.CIQ(E$3,$AL$1,$AL$2,$A11,"L",,"USD","H")} -> -12.6922 | AP11: {=_xll.ciqfunctions.udf.CIQ(F$3,$AL$1,$AL$2,$A11,"L",,"USD","H")} -> -96.5658 | AQ11: {=_xll.ciqfunctions.udf.CIQ(G$3,$AL$1,$AL$2,$A11,"L",,"USD","H")} -> -4.08 | AR11: {=_xll.ciqfunctions.udf.CIQ(B$3,$AL$1,$AR$2,$A11,"L",,"USD","H")} -> -41.3437 | AS11: {=_xll.ciqfunctions.udf.CIQ(C$3,$AL$1,$AR$2,$A11,"L",,"USD","H")} -> -35.3965 | AT11: {=_xll.ciqfunctions.udf.CIQ(D$3,$AL$1,$AR$2,$A11,"L",,"USD","H")} -> -39.7463 | AU11: {=_xll.ciqfunctions.udf.CIQ(E$3,$AL$1,$AR$2,$A11,"L",,"USD","H")} -> -2.1266 | AV11: {=_xll.ciqfunctions.udf.CIQ(F$3,$AL$1,$AR$2,$A11,"L",,"USD","H")} -> NM | AW11: {=_xll.ciqfunctions.udf.CIQ(G$3,$AL$1,$AR$2,$A11,"L",,"USD","H")} -> -37.7058 | AX11: {=_xll.ciqfunctions.udf.CIQ(B$3,$AX$1,$AX$2,$A11,"L",,"USD","H")} -> 6662 | AY11: {=_xll.ciqfunctions.udf.CIQ(C$3,$AX$1,$AX$2,$A11,"L",,"USD","H")} -> 17949 | AZ11: {=_xll.ciqfunctions.udf.CIQ(D$3,$AX$1,$AX$2,$A11,"L",,"USD","H")} -> 8936 | BA11: {=_xll.ciqfunctions.udf.CIQ(E$3,$AX$1,$AX$2,$A11,"L",,"USD","H")} -> 3513 | BB11: {=_xll.ciqfunctions.udf.CIQ(F$3,$AX$1,$AX$2,$A11,"L",,"USD","H")} -> 5995 | BC11: {=_xll.ciqfunctions.udf.CIQ(G$3,$AX$1,$AX$2,$A11,"L",,"USD","H")} -> 2172 | BD11: {=_xll.ciqfunctions.udf.CIQ(B$3,$AX$1,$BD$2,$A11,"L",,"USD","H")} -> 24753 | BE11: {=_xll.ciqfunctions.udf.CIQ(C$3,$AX$1,$BD$2,$A11,"L",,"USD","H")} -> 66356 | BF11: {=_xll.ciqfunctions.udf.CIQ(D$3,$AX$1,$BD$2,$A11,"L",,"USD","H")} -> 42177 | BG11: {=_xll.ciqfunctions.udf.CIQ(E$3,$AX$1,$BD$2,$A11,"L",,"USD","H")} -> 13202 | BH11: {=_xll.ciqfunctions.udf.CIQ(F$3,$AX$1,$BD$2,$A11,"L",,"USD","H")} -> 44158 | BI11: {=_xll.ciqfunctions.udf.CIQ(G$3,$AX$1,$BD$2,$A11,"L",,"USD","H")} -> 7484 | BJ11: =AX11/AX15-1 -> -0.098633473 | BK11: =AY11/AY15-1 -> -0.001390898 | BL11: =AZ11/AZ15-1 -> -0.31566856 | BM11: =BA11/BA15-1 -> -0.093419355 | BN11: =BB11/BB15-1 -> -0.72491167 | BO11: =BC11/BC15-1 -> -0.012278308 | BP11: =BD11/BD15-1 -> -0.29107 | BQ11: =BE11/BE15-1 -> -0.25981617 | ... BU11: =BI11/BI15-1 -> -0.27255054 | BV11: {=_xll.ciqfunctions.udf.CIQ(B$3,$BV$1,$BV$2,$A11,"L",,"USD","H")/100} -> 0.094252 | BW11: {=_xll.ciqfunctions.udf.CIQ(C$3,$BV$1,$BV$2,$A11,"L",,"USD","H")/100} -> 0.059576 | BX11: {=_xll.ciqfunctions.udf.CIQ(D$3,$BV$1,$BV$2,$A11,"L",,"USD","H")/100} -> -0.011736 | BY11: {=_xll.ciqfunctions.udf.CIQ(E$3,$BV$1,$BV$2,$A11,"L",,"USD","H")/100} -> 0.0072 | BZ11: {=_xll.ciqfunctions.udf.CIQ(F$3,$BV$1,$BV$2,$A11,"L",,"USD","H")/100} -> 0.010028 | CA11: {=_xll.ciqfunctions.udf.CIQ(G$3,$BV$1,$BV$2,$A11,"L",,"USD","H")/100} -> 0.143716 | CB11: {=_xll.ciqfunctions.udf.CIQ(B$3,$BV$1,$CB$2,$A11,"L",,"USD","H")/100} -> 0.080146 | CC11: {=_xll.ciqfunctions.udf.CIQ(C$3,$BV$1,$CB$2,$A11,"L",,"USD","H")/100} -> 0.082682 | CD11: {=_xll.ciqfunctions.udf.CIQ(D$3,$BV$1,$CB$2,$A11,"L",,"USD","H")/100} -> 0.053422 | CE11: {=_xll.ciqfunctions.udf.CIQ(E$3,$BV$1,$CB$2,$A11,"L",,"USD","H")/100} -> 0.13227 | CF11: {=_xll.ciqfunctions.udf.CIQ(F$3,$BV$1,$CB$2,$A11,"L",,"USD","H")/100} -> 0.07267 | CG11: {=_xll.ciqfunctions.udf.CIQ(G$3,$BV$1,$CB$2,$A11,"L",,"USD","H")/100} -> 0.102903
A12: =EDATE(A8,-12) -> 45199 | B12: {=_xll.ciqfunctions.udf.CIQ(B$3,$B$1,$B$2,$A12,"L",,"USD","H")} -> 14638 | C12: {=_xll.ciqfunctions.udf.CIQ(C$3,$B$1,$B$2,$A12,"L",,"USD","H")} -> 88570 | D12: {=_xll.ciqfunctions.udf.CIQ(D$3,$B$1,$B$2,$A12,"L",,"USD","H")} -> 52775 | E12: {=_xll.ciqfunctions.udf.CIQ(E$3,$B$1,$B$2,$A12,"L",,"USD","H")} -> 6134 | F12: {=_xll.ciqfunctions.udf.CIQ(F$3,$B$1,$B$2,$A12,"L",,"USD","H")} -> 53223 | G12: {=_xll.ciqfunctions.udf.CIQ(G$3,$B$1,$B$2,$A12,"L",,"USD","H")} -> 4030 | H12: {=_xll.ciqfunctions.udf.CIQ(B$3,$B$1,$H$2,$A12,"L",,"USD","H")} -> 61839 | I12: {=_xll.ciqfunctions.udf.CIQ(C$3,$B$1,$H$2,$A12,"L",,"USD","H")} -> 346799 | J12: {=_xll.ciqfunctions.udf.CIQ(D$3,$B$1,$H$2,$A12,"L",,"USD","H")} -> 203065 | K12: {=_xll.ciqfunctions.udf.CIQ(E$3,$B$1,$H$2,$A12,"L",,"USD","H")} -> 23727 | L12: {=_xll.ciqfunctions.udf.CIQ(F$3,$B$1,$H$2,$A12,"L",,"USD","H")} -> 226391 | M12: {=_xll.ciqfunctions.udf.CIQ(G$3,$B$1,$H$2,$A12,"L",,"USD","H")} -> 14930 | N12: {=_xll.ciqfunctions.udf.CIQ(B$3,$N$1,$B$2,$A12,"L",,"USD","H")} -> -32.1499 | O12: {=_xll.ciqfunctions.udf.CIQ(C$3,$N$1,$B$2,$A12,"L",,"USD","H")} -> -17.5618 | P12: {=_xll.ciqfunctions.udf.CIQ(D$3,$N$1,$B$2,$A12,"L",,"USD","H")} -> -17.8523 | Q12: {=_xll.ciqfunctions.udf.CIQ(E$3,$N$1,$B$2,$A12,"L",,"USD","H")} -> -19.6279 | R12: {=_xll.ciqfunctions.udf.CIQ(F$3,$N$1,$B$2,$A12,"L",,"USD","H")} -> -2.1133 | S12: {=_xll.ciqfunctions.udf.CIQ(G$3,$N$1,$B$2,$A12,"L",,"USD","H")} -> -22.2609 | T12: 4.957 | U12: {=_xll.ciqfunctions.udf.CIQ(O$3,$N$1,$T$2,$A12,"L",,"USD","H")} -> -11.1406 | V12: {=_xll.ciqfunctions.udf.CIQ(P$3,$N$1,$T$2,$A12,"L",,"USD","H")} -> -10.816 | W12: {=_xll.ciqfunctions.udf.CIQ(Q$3,$N$1,$T$2,$A12,"L",,"USD","H")} -> -18.2786 | X12: {=_xll.ciqfunctions.udf.CIQ(R$3,$N$1,$T$2,$A12,"L",,"USD","H")} -> 2.4996 | Y12: {=_xll.ciqfunctions.udf.CIQ(S$3,$N$1,$T$2,$A12,"L",,"USD","H")} -> -20.5217 | Z12: {=_xll.ciqfunctions.udf.CIQ(B$3,$Z$1,$B$2,$A12,"L",,"USD","H")} -> 2798 | AA12: {=_xll.ciqfunctions.udf.CIQ(C$3,$Z$1,$B$2,$A12,"L",,"USD","H")} -> 9070 | AB12: {=_xll.ciqfunctions.udf.CIQ(D$3,$Z$1,$B$2,$A12,"L",,"USD","H")} -> 6526 | AC12: {=_xll.ciqfunctions.udf.CIQ(E$3,$Z$1,$B$2,$A12,"L",,"USD","H")} -> 2030 | AD12: {=_xll.ciqfunctions.udf.CIQ(F$3,$Z$1,$B$2,$A12,"L",,"USD","H")} -> 4858 | AE12: {=_xll.ciqfunctions.udf.CIQ(G$3,$Z$1,$B$2,$A12,"L",,"USD","H")} -> 910 | AF12: {=_xll.ciqfunctions.udf.CIQ(B$3,$Z$1,$H$2,$A12,"L",,"USD","H")} -> 11199 | AG12: {=_xll.ciqfunctions.udf.CIQ(C$3,$Z$1,$H$2,$A12,"L",,"USD","H")} -> 41130 | AH12: {=_xll.ciqfunctions.udf.CIQ(D$3,$Z$1,$H$2,$A12,"L",,"USD","H")} -> 25463 | AI12: {=_xll.ciqfunctions.udf.CIQ(E$3,$Z$1,$H$2,$A12,"L",,"USD","H")} -> 7883 | AJ12: {=_xll.ciqfunctions.udf.CIQ(F$3,$Z$1,$H$2,$A12,"L",,"USD","H")} -> 25671 | AK12: {=_xll.ciqfunctions.udf.CIQ(G$3,$Z$1,$H$2,$A12,"L",,"USD","H")} -> 3796 | AL12: {=_xll.ciqfunctions.udf.CIQ(B$3,$AL$1,$AL$2,$A12,"L",,"USD","H")} -> -38.1931 | AM12: {=_xll.ciqfunctions.udf.CIQ(C$3,$AL$1,$AL$2,$A12,"L",,"USD","H")} -> -53.8658 | AN12: {=_xll.ciqfunctions.udf.CIQ(D$3,$AL$1,$AL$2,$A12,"L",,"USD","H")} -> -41.893 | AO12: {=_xll.ciqfunctions.udf.CIQ(E$3,$AL$1,$AL$2,$A12,"L",,"USD","H")} -> -28.8718 | AP12: {=_xll.ciqfunctions.udf.CIQ(F$3,$AL$1,$AL$2,$A12,"L",,"USD","H")} -> NM | AQ12: {=_xll.ciqfunctions.udf.CIQ(G$3,$AL$1,$AL$2,$A12,"L",,"USD","H")} -> -51.9282 | AR12: {=_xll.ciqfunctions.udf.CIQ(B$3,$AL$1,$AR$2,$A12,"L",,"USD","H")} -> -37.9832 | AS12: {=_xll.ciqfunctions.udf.CIQ(C$3,$AL$1,$AR$2,$A12,"L",,"USD","H")} -> -20.6904 | AT12: {=_xll.ciqfunctions.udf.CIQ(D$3,$AL$1,$AR$2,$A12,"L",,"USD","H")} -> -25.4749 | AU12: {=_xll.ciqfunctions.udf.CIQ(E$3,$AL$1,$AR$2,$A12,"L",,"USD","H")} -> 5.5711 | AV12: {=_xll.ciqfunctions.udf.CIQ(F$3,$AL$1,$AR$2,$A12,"L",,"USD","H")} -> NM | AW12: {=_xll.ciqfunctions.udf.CIQ(G$3,$AL$1,$AR$2,$A12,"L",,"USD","H")} -> -39.9368 | AX12: {=_xll.ciqfunctions.udf.CIQ(B$3,$AX$1,$AX$2,$A12,"L",,"USD","H")} -> 6236 | AY12: {=_xll.ciqfunctions.udf.CIQ(C$3,$AX$1,$AX$2,$A12,"L",,"USD","H")} -> 16093 | AZ12: {=_xll.ciqfunctions.udf.CIQ(D$3,$AX$1,$AX$2,$A12,"L",,"USD","H")} -> 11564 | BA12: {=_xll.ciqfunctions.udf.CIQ(E$3,$AX$1,$AX$2,$A12,"L",,"USD","H")} -> 3474 | BB12: {=_xll.ciqfunctions.udf.CIQ(F$3,$AX$1,$AX$2,$A12,"L",,"USD","H")} -> 12772 | BC12: {=_xll.ciqfunctions.udf.CIQ(G$3,$AX$1,$AX$2,$A12,"L",,"USD","H")} -> 1805 | BD12: {=_xll.ciqfunctions.udf.CIQ(B$3,$AX$1,$BD$2,$A12,"L",,"USD","H")} -> 25482 | BE12: {=_xll.ciqfunctions.udf.CIQ(C$3,$AX$1,$BD$2,$A12,"L",,"USD","H")} -> 59037 | BF12: {=_xll.ciqfunctions.udf.CIQ(D$3,$AX$1,$BD$2,$A12,"L",,"USD","H")} -> 46299 | BG12: {=_xll.ciqfunctions.udf.CIQ(E$3,$AX$1,$BD$2,$A12,"L",,"USD","H")} -> 13564 | BH12: {=_xll.ciqfunctions.udf.CIQ(F$3,$AX$1,$BD$2,$A12,"L",,"USD","H")} -> 59956 | BI12: {=_xll.ciqfunctions.udf.CIQ(G$3,$AX$1,$BD$2,$A12,"L",,"USD","H")} -> 7511 | BJ12: =AX12/AX16-1 -> -0.3353938 | BK12: =AY12/AY16-1 -> -0.52646756 | BL12: =AZ12/AZ16-1 -> -0.30870397 | BM12: =BA12/BA16-1 -> -0.25848453 | BN12: =BB12/BB16-1 -> 2.2706786 | BO12: =BC12/BC16-1 -> -0.42147436 | BP12: =BD12/BD16-1 -> -0.25848974 | BQ12: =BE12/BE16-1 -> -0.37955713 | ... BU12: =BI12/BI16-1 -> -0.27646662 | BV12: {=_xll.ciqfunctions.udf.CIQ(B$3,$BV$1,$BV$2,$A12,"L",,"USD","H")/100} -> 0.089368 | BW12: {=_xll.ciqfunctions.udf.CIQ(C$3,$BV$1,$BV$2,$A12,"L",,"USD","H")/100} -> 0.086984 | BX12: {=_xll.ciqfunctions.udf.CIQ(D$3,$BV$1,$BV$2,$A12,"L",,"USD","H")/100} -> 0.079952 | BY12: {=_xll.ciqfunctions.udf.CIQ(E$3,$BV$1,$BV$2,$A12,"L",,"USD","H")/100} -> 0.163444 | BZ12: {=_xll.ciqfunctions.udf.CIQ(F$3,$BV$1,$BV$2,$A12,"L",,"USD","H")/100} -> 0.098312 | CA12: {=_xll.ciqfunctions.udf.CIQ(G$3,$BV$1,$BV$2,$A12,"L",,"USD","H")/100} -> 0.132348 | CB12: {=_xll.ciqfunctions.udf.CIQ(B$3,$BV$1,$CB$2,$A12,"L",,"USD","H")/100} -> 0.069763 | CC12: {=_xll.ciqfunctions.udf.CIQ(C$3,$BV$1,$CB$2,$A12,"L",,"USD","H")/100} -> 0.107791 | CD12: {=_xll.ciqfunctions.udf.CIQ(D$3,$BV$1,$CB$2,$A12,"L",,"USD","H")/100} -> 0.076865 | CE12: {=_xll.ciqfunctions.udf.CIQ(E$3,$BV$1,$CB$2,$A12,"L",,"USD","H")/100} -> 0.258166 | CF12: {=_xll.ciqfunctions.udf.CIQ(F$3,$BV$1,$CB$2,$A12,"L",,"USD","H")/100} -> 0.152627 | CG12: {=_xll.ciqfunctions.udf.CIQ(G$3,$BV$1,$CB$2,$A12,"L",,"USD","H")/100} -> 0.086159
A13: =EDATE(A9,-12) -> 45107 | B13: {=_xll.ciqfunctions.udf.CIQ(B$3,$B$1,$B$2,$A13,"L",,"USD","H")} -> 12763 | C13: {=_xll.ciqfunctions.udf.CIQ(C$3,$B$1,$B$2,$A13,"L",,"USD","H")} -> 80256 | D13: {=_xll.ciqfunctions.udf.CIQ(D$3,$B$1,$B$2,$A13,"L",,"USD","H")} -> 47533 | E13: {=_xll.ciqfunctions.udf.CIQ(E$3,$B$1,$B$2,$A13,"L",,"USD","H")} -> 5481 | F13: {=_xll.ciqfunctions.udf.CIQ(F$3,$B$1,$B$2,$A13,"L",,"USD","H")} -> 48760 | G13: {=_xll.ciqfunctions.udf.CIQ(G$3,$B$1,$B$2,$A13,"L",,"USD","H")} -> 3339 | H13: {=_xll.ciqfunctions.udf.CIQ(B$3,$B$1,$H$2,$A13,"L",,"USD","H")} -> 68775 | I13: {=_xll.ciqfunctions.udf.CIQ(C$3,$B$1,$H$2,$A13,"L",,"USD","H")} -> 365667 | J13: {=_xll.ciqfunctions.udf.CIQ(D$3,$B$1,$H$2,$A13,"L",,"USD","H")} -> 214534 | K13: {=_xll.ciqfunctions.udf.CIQ(E$3,$B$1,$H$2,$A13,"L",,"USD","H")} -> 25225 | L13: {=_xll.ciqfunctions.udf.CIQ(F$3,$B$1,$H$2,$A13,"L",,"USD","H")} -> 227540 | M13: {=_xll.ciqfunctions.udf.CIQ(G$3,$B$1,$H$2,$A13,"L",,"USD","H")} -> 16084 | N13: {=_xll.ciqfunctions.udf.CIQ(B$3,$N$1,$B$2,$A13,"L",,"USD","H")} -> -41.1437 | O13: {=_xll.ciqfunctions.udf.CIQ(C$3,$N$1,$B$2,$A13,"L",,"USD","H")} -> -28.3384 | P13: {=_xll.ciqfunctions.udf.CIQ(D$3,$N$1,$B$2,$A13,"L",,"USD","H")} -> -28.3116 | Q13: {=_xll.ciqfunctions.udf.CIQ(E$3,$N$1,$B$2,$A13,"L",,"USD","H")} -> -36.9058 | R13: {=_xll.ciqfunctions.udf.CIQ(F$3,$N$1,$B$2,$A13,"L",,"USD","H")} -> -27.4858 | S13: {=_xll.ciqfunctions.udf.CIQ(G$3,$N$1,$B$2,$A13,"L",,"USD","H")} -> -39.7728 | T13: 5.089 | U13: {=_xll.ciqfunctions.udf.CIQ(O$3,$N$1,$T$2,$A13,"L",,"USD","H")} -> 3.0175 | V13: {=_xll.ciqfunctions.udf.CIQ(P$3,$N$1,$T$2,$A13,"L",,"USD","H")} -> 4.1427 | W13: {=_xll.ciqfunctions.udf.CIQ(Q$3,$N$1,$T$2,$A13,"L",,"USD","H")} -> -5.3826 | X13: {=_xll.ciqfunctions.udf.CIQ(R$3,$N$1,$T$2,$A13,"L",,"USD","H")} -> 12.4665 | Y13: {=_xll.ciqfunctions.udf.CIQ(S$3,$N$1,$T$2,$A13,"L",,"USD","H")} -> -7.5739 | Z13: {=_xll.ciqfunctions.udf.CIQ(B$3,$Z$1,$B$2,$A13,"L",,"USD","H")} -> 2232 | AA13: {=_xll.ciqfunctions.udf.CIQ(C$3,$Z$1,$B$2,$A13,"L",,"USD","H")} -> 7880 | AB13: {=_xll.ciqfunctions.udf.CIQ(D$3,$Z$1,$B$2,$A13,"L",,"USD","H")} -> 6010 | AC13: {=_xll.ciqfunctions.udf.CIQ(E$3,$Z$1,$B$2,$A13,"L",,"USD","H")} -> 1553 | AD13: {=_xll.ciqfunctions.udf.CIQ(F$3,$Z$1,$B$2,$A13,"L",,"USD","H")} -> 1792 | AE13: {=_xll.ciqfunctions.udf.CIQ(G$3,$Z$1,$B$2,$A13,"L",,"USD","H")} -> 690 | AF13: {=_xll.ciqfunctions.udf.CIQ(B$3,$Z$1,$H$2,$A13,"L",,"USD","H")} -> 12928 | AG13: {=_xll.ciqfunctions.udf.CIQ(C$3,$Z$1,$H$2,$A13,"L",,"USD","H")} -> 51720 | AH13: {=_xll.ciqfunctions.udf.CIQ(D$3,$Z$1,$H$2,$A13,"L",,"USD","H")} -> 30168 | AI13: {=_xll.ciqfunctions.udf.CIQ(E$3,$Z$1,$H$2,$A13,"L",,"USD","H")} -> 8707 | AJ13: {=_xll.ciqfunctions.udf.CIQ(F$3,$Z$1,$H$2,$A13,"L",,"USD","H")} -> 18650 | AK13: {=_xll.ciqfunctions.udf.CIQ(G$3,$Z$1,$H$2,$A13,"L",,"USD","H")} -> 4779 | AL13: {=_xll.ciqfunctions.udf.CIQ(B$3,$AL$1,$AL$2,$A13,"L",,"USD","H")} -> -56.6181 | AM13: {=_xll.ciqfunctions.udf.CIQ(C$3,$AL$1,$AL$2,$A13,"L",,"USD","H")} -> -55.8544 | AN13: {=_xll.ciqfunctions.udf.CIQ(D$3,$AL$1,$AL$2,$A13,"L",,"USD","H")} -> -48.2878 | AO13: {=_xll.ciqfunctions.udf.CIQ(E$3,$AL$1,$AL$2,$A13,"L",,"USD","H")} -> -30.6077 | AP13: {=_xll.ciqfunctions.udf.CIQ(F$3,$AL$1,$AL$2,$A13,"L",,"USD","H")} -> -80.6417 | AQ13: {=_xll.ciqfunctions.udf.CIQ(G$3,$AL$1,$AL$2,$A13,"L",,"USD","H")} -> -64.2858 | AR13: {=_xll.ciqfunctions.udf.CIQ(B$3,$AL$1,$AR$2,$A13,"L",,"USD","H")} -> -18.743 | AS13: {=_xll.ciqfunctions.udf.CIQ(C$3,$AL$1,$AR$2,$A13,"L",,"USD","H")} -> 32.7856 | AT13: {=_xll.ciqfunctions.udf.CIQ(D$3,$AL$1,$AR$2,$A13,"L",,"USD","H")} -> 3.8592 | AU13: {=_xll.ciqfunctions.udf.CIQ(E$3,$AL$1,$AR$2,$A13,"L",,"USD","H")} -> 52.5402 | AV13: {=_xll.ciqfunctions.udf.CIQ(F$3,$AL$1,$AR$2,$A13,"L",,"USD","H")} -> NM | AW13: {=_xll.ciqfunctions.udf.CIQ(G$3,$AL$1,$AR$2,$A13,"L",,"USD","H")} -> -9.2308 | AX13: {=_xll.ciqfunctions.udf.CIQ(B$3,$AX$1,$AX$2,$A13,"L",,"USD","H")} -> 5393 | AY13: {=_xll.ciqfunctions.udf.CIQ(C$3,$AX$1,$AX$2,$A13,"L",,"USD","H")} -> 13489 | AZ13: {=_xll.ciqfunctions.udf.CIQ(D$3,$AX$1,$AX$2,$A13,"L",,"USD","H")} -> 10105 | BA13: {=_xll.ciqfunctions.udf.CIQ(E$3,$AX$1,$AX$2,$A13,"L",,"USD","H")} -> 2880 | BB13: {=_xll.ciqfunctions.udf.CIQ(F$3,$AX$1,$AX$2,$A13,"L",,"USD","H")} -> 9532 | BC13: {=_xll.ciqfunctions.udf.CIQ(G$3,$AX$1,$AX$2,$A13,"L",,"USD","H")} -> 1596 | BD13: {=_xll.ciqfunctions.udf.CIQ(B$3,$AX$1,$BD$2,$A13,"L",,"USD","H")} -> 28629 | BE13: {=_xll.ciqfunctions.udf.CIQ(C$3,$AX$1,$BD$2,$A13,"L",,"USD","H")} -> 76929 | BF13: {=_xll.ciqfunctions.udf.CIQ(D$3,$AX$1,$BD$2,$A13,"L",,"USD","H")} -> 51463 | BG13: =_xll.ciqfunctions.udf.CIQ("COP", "IQ_PRICEDATE", "11/7/2025") -> 45968 | BH13: {=_xll.ciqfunctions.udf.CIQ(F$3,$AX$1,$BD$2,$A13,"L",,"USD","H")} -> 51089 | BI13: {=_xll.ciqfunctions.udf.CIQ(G$3,$AX$1,$BD$2,$A13,"L",,"USD","H")} -> 8826 | BJ13: =AX13/AX17-1 -> -0.42658161 | BK13: =AY13/AY17-1 -> -0.47898803 | BL13: =AZ13/AZ17-1 -> -0.41818287 | BM13: =BA13/BA17-1 -> -0.24369748 | BN13: =BB13/BB17-1 -> -0.43978842 | BO13: =BC13/BC17-1 -> -0.48615583 | BP13: =BD13/BD17-1 -> -0.055553723 | BQ13: =BE13/BE17-1 -> 0.035272111 | ... BU13: =BI13/BI17-1 -> -0.0099831744 | BV13: {=_xll.ciqfunctions.udf.CIQ(B$3,$BV$1,$BV$2,$A13,"L",,"USD","H")/100} -> 0.054976 | BW13: {=_xll.ciqfunctions.udf.CIQ(C$3,$BV$1,$BV$2,$A13,"L",,"USD","H")/100} -> 0.067352 | BX13: {=_xll.ciqfunctions.udf.CIQ(D$3,$BV$1,$BV$2,$A13,"L",,"USD","H")/100} -> 0.070064 | BY13: {=_xll.ciqfunctions.udf.CIQ(E$3,$BV$1,$BV$2,$A13,"L",,"USD","H")/100} -> 0.206972 | BZ13: {=_xll.ciqfunctions.udf.CIQ(F$3,$BV$1,$BV$2,$A13,"L",,"USD","H")/100} -> 0.049316 | CA13: {=_xll.ciqfunctions.udf.CIQ(G$3,$BV$1,$BV$2,$A13,"L",,"USD","H")/100} -> 0.051108 | CB13: {=_xll.ciqfunctions.udf.CIQ(B$3,$BV$1,$CB$2,$A13,"L",,"USD","H")/100} -> 0.094793 | CC13: {=_xll.ciqfunctions.udf.CIQ(C$3,$BV$1,$CB$2,$A13,"L",,"USD","H")/100} -> 0.153491 | CD13: {=_xll.ciqfunctions.udf.CIQ(D$3,$BV$1,$CB$2,$A13,"L",,"USD","H")/100} -> 0.10529 | CE13: {=_xll.ciqfunctions.udf.CIQ(E$3,$BV$1,$CB$2,$A13,"L",,"USD","H")/100} -> 0.300112 | CF13: {=_xll.ciqfunctions.udf.CIQ(F$3,$BV$1,$CB$2,$A13,"L",,"USD","H")/100} -> 0.12916 | CG13: {=_xll.ciqfunctions.udf.CIQ(G$3,$BV$1,$CB$2,$A13,"L",,"USD","H")/100} -> 0.105513
A14: =EDATE(A10,-12) -> 45016 | B14: {=_xll.ciqfunctions.udf.CIQ(B$3,$B$1,$B$2,$A14,"L",,"USD","H")} -> 15310 | C14: {=_xll.ciqfunctions.udf.CIQ(C$3,$B$1,$B$2,$A14,"L",,"USD","H")} -> 84183 | D14: {=_xll.ciqfunctions.udf.CIQ(D$3,$B$1,$B$2,$A14,"L",,"USD","H")} -> 49211 | E14: {=_xll.ciqfunctions.udf.CIQ(E$3,$B$1,$B$2,$A14,"L",,"USD","H")} -> 5599 | F14: {=_xll.ciqfunctions.udf.CIQ(F$3,$B$1,$B$2,$A14,"L",,"USD","H")} -> 55708 | G14: {=_xll.ciqfunctions.udf.CIQ(G$3,$B$1,$B$2,$A14,"L",,"USD","H")} -> 3419 | H14: {=_xll.ciqfunctions.udf.CIQ(B$3,$B$1,$H$2,$A14,"L",,"USD","H")} -> 77697 | I14: {=_xll.ciqfunctions.udf.CIQ(C$3,$B$1,$H$2,$A14,"L",,"USD","H")} -> 397404 | J14: {=_xll.ciqfunctions.udf.CIQ(D$3,$B$1,$H$2,$A14,"L",,"USD","H")} -> 233306 | K14: {=_xll.ciqfunctions.udf.CIQ(E$3,$B$1,$H$2,$A14,"L",,"USD","H")} -> 28431 | L14: {=_xll.ciqfunctions.udf.CIQ(F$3,$B$1,$H$2,$A14,"L",,"USD","H")} -> 246022 | M14: {=_xll.ciqfunctions.udf.CIQ(G$3,$B$1,$H$2,$A14,"L",,"USD","H")} -> 18289 | N14: {=_xll.ciqfunctions.udf.CIQ(B$3,$N$1,$B$2,$A14,"L",,"USD","H")} -> -15.8237 | O14: {=_xll.ciqfunctions.udf.CIQ(C$3,$N$1,$B$2,$A14,"L",,"USD","H")} -> -4.2962 | P14: {=_xll.ciqfunctions.udf.CIQ(D$3,$N$1,$B$2,$A14,"L",,"USD","H")} -> -5.0366 | Q14: {=_xll.ciqfunctions.udf.CIQ(E$3,$N$1,$B$2,$A14,"L",,"USD","H")} -> -17.3946 | R14: {=_xll.ciqfunctions.udf.CIQ(F$3,$N$1,$B$2,$A14,"L",,"USD","H")} -> 14.2657 | S14: {=_xll.ciqfunctions.udf.CIQ(G$3,$N$1,$B$2,$A14,"L",,"USD","H")} -> -14.5891 | T14: 5.1225 | U14: {=_xll.ciqfunctions.udf.CIQ(O$3,$N$1,$T$2,$A14,"L",,"USD","H")} -> 28.4978 | V14: {=_xll.ciqfunctions.udf.CIQ(P$3,$N$1,$T$2,$A14,"L",,"USD","H")} -> 32.7019 | W14: {=_xll.ciqfunctions.udf.CIQ(Q$3,$N$1,$T$2,$A14,"L",,"USD","H")} -> 26.4274 | X14: {=_xll.ciqfunctions.udf.CIQ(R$3,$N$1,$T$2,$A14,"L",,"USD","H")} -> 43.6641 | Y14: {=_xll.ciqfunctions.udf.CIQ(S$3,$N$1,$T$2,$A14,"L",,"USD","H")} -> 23.5576 | Z14: {=_xll.ciqfunctions.udf.CIQ(B$3,$Z$1,$B$2,$A14,"L",,"USD","H")} -> 2920 | AA14: {=_xll.ciqfunctions.udf.CIQ(C$3,$Z$1,$B$2,$A14,"L",,"USD","H")} -> 11430 | AB14: {=_xll.ciqfunctions.udf.CIQ(D$3,$Z$1,$B$2,$A14,"L",,"USD","H")} -> 6574 | AC14: {=_xll.ciqfunctions.udf.CIQ(E$3,$Z$1,$B$2,$A14,"L",,"USD","H")} -> 2023 | AD14: {=_xll.ciqfunctions.udf.CIQ(F$3,$Z$1,$B$2,$A14,"L",,"USD","H")} -> 8218 | AE14: {=_xll.ciqfunctions.udf.CIQ(G$3,$Z$1,$B$2,$A14,"L",,"USD","H")} -> 995 | AF14: {=_xll.ciqfunctions.udf.CIQ(B$3,$Z$1,$H$2,$A14,"L",,"USD","H")} -> 15841 | AG14: {=_xll.ciqfunctions.udf.CIQ(C$3,$Z$1,$H$2,$A14,"L",,"USD","H")} -> 61690 | AH14: {=_xll.ciqfunctions.udf.CIQ(D$3,$Z$1,$H$2,$A14,"L",,"USD","H")} -> 35780 | AI14: {=_xll.ciqfunctions.udf.CIQ(E$3,$Z$1,$H$2,$A14,"L",,"USD","H")} -> 9392 | AJ14: {=_xll.ciqfunctions.udf.CIQ(F$3,$Z$1,$H$2,$A14,"L",,"USD","H")} -> 26115 | AK14: {=_xll.ciqfunctions.udf.CIQ(G$3,$Z$1,$H$2,$A14,"L",,"USD","H")} -> 6021 | AL14: {=_xll.ciqfunctions.udf.CIQ(B$3,$AL$1,$AL$2,$A14,"L",,"USD","H")} -> -49.2968 | AM14: {=_xll.ciqfunctions.udf.CIQ(C$3,$AL$1,$AL$2,$A14,"L",,"USD","H")} -> 108.5766 | AN14: {=_xll.ciqfunctions.udf.CIQ(D$3,$AL$1,$AL$2,$A14,"L",,"USD","H")} -> 5.0327 | AO14: {=_xll.ciqfunctions.udf.CIQ(E$3,$AL$1,$AL$2,$A14,"L",,"USD","H")} -> 418.7179 | AP14: {=_xll.ciqfunctions.udf.CIQ(F$3,$AL$1,$AL$2,$A14,"L",,"USD","H")} -> NM | AQ14: {=_xll.ciqfunctions.udf.CIQ(G$3,$AL$1,$AL$2,$A14,"L",,"USD","H")} -> 0.6066 | AR14: {=_xll.ciqfunctions.udf.CIQ(B$3,$AL$1,$AR$2,$A14,"L",,"USD","H")} -> 23.2187 | AS14: {=_xll.ciqfunctions.udf.CIQ(C$3,$AL$1,$AR$2,$A14,"L",,"USD","H")} -> 139.2012 | AT14: {=_xll.ciqfunctions.udf.CIQ(D$3,$AL$1,$AR$2,$A14,"L",,"USD","H")} -> 74.477 | AU14: {=_xll.ciqfunctions.udf.CIQ(E$3,$AL$1,$AR$2,$A14,"L",,"USD","H")} -> 114.5761 | AV14: {=_xll.ciqfunctions.udf.CIQ(F$3,$AL$1,$AR$2,$A14,"L",,"USD","H")} -> NM | AW14: {=_xll.ciqfunctions.udf.CIQ(G$3,$AL$1,$AR$2,$A14,"L",,"USD","H")} -> 67.7626 | AX14: {=_xll.ciqfunctions.udf.CIQ(B$3,$AX$1,$AX$2,$A14,"L",,"USD","H")} -> 6462 | AY14: {=_xll.ciqfunctions.udf.CIQ(C$3,$AX$1,$AX$2,$A14,"L",,"USD","H")} -> 18825 | AZ14: {=_xll.ciqfunctions.udf.CIQ(D$3,$AX$1,$AX$2,$A14,"L",,"USD","H")} -> 11572 | BA14: {=_xll.ciqfunctions.udf.CIQ(E$3,$AX$1,$AX$2,$A14,"L",,"USD","H")} -> 3335 | BB14: {=_xll.ciqfunctions.udf.CIQ(F$3,$AX$1,$AX$2,$A14,"L",,"USD","H")} -> 15859 | BC14: {=_xll.ciqfunctions.udf.CIQ(G$3,$AX$1,$AX$2,$A14,"L",,"USD","H")} -> 1911 | BD14: {=_xll.ciqfunctions.udf.CIQ(B$3,$AX$1,$BD$2,$A14,"L",,"USD","H")} -> 32641 | BE14: {=_xll.ciqfunctions.udf.CIQ(C$3,$AX$1,$BD$2,$A14,"L",,"USD","H")} -> 93930 | BF14: {=_xll.ciqfunctions.udf.CIQ(D$3,$AX$1,$BD$2,$A14,"L",,"USD","H")} -> 58726 | BG14: =_xll.ciqfunctions.udf.CIQ("COP", "IQ_PRICEDATE", "10/31/2025") -> 45961 | BH14: {=_xll.ciqfunctions.udf.CIQ(F$3,$AX$1,$BD$2,$A14,"L",,"USD","H")} -> 58572 | BI14: {=_xll.ciqfunctions.udf.CIQ(G$3,$AX$1,$BD$2,$A14,"L",,"USD","H")} -> 10336 | BJ14: =AX14/AX18-1 -> -0.26038686 | BK14: =AY14/AY18-1 -> 0.24759759 | BL14: =AZ14/AZ18-1 -> 0.12425921 | BM14: =BA14/BA18-1 -> 1.3436402 | BN14: =BB14/BB18-1 -> 0.45937241 | BO14: =BC14/BC18-1 -> 0.036896365 | BP14: =BD14/BD18-1 -> 0.27658493 | BQ14: =BE14/BE18-1 -> 0.74283329 | ... BU14: =BI14/BI18-1 -> 0.54892852 | BV14: {=_xll.ciqfunctions.udf.CIQ(B$3,$BV$1,$BV$2,$A14,"L",,"USD","H")/100} -> 0.088424 | BW14: {=_xll.ciqfunctions.udf.CIQ(C$3,$BV$1,$BV$2,$A14,"L",,"USD","H")/100} -> 0.123752 | BX14: {=_xll.ciqfunctions.udf.CIQ(D$3,$BV$1,$BV$2,$A14,"L",,"USD","H")/100} -> 0.080096 | BY14: {=_xll.ciqfunctions.udf.CIQ(E$3,$BV$1,$BV$2,$A14,"L",,"USD","H")/100} -> 0.126708 | BZ14: {=_xll.ciqfunctions.udf.CIQ(F$3,$BV$1,$BV$2,$A14,"L",,"USD","H")/100} -> 0.198964 | CA14: {=_xll.ciqfunctions.udf.CIQ(G$3,$BV$1,$BV$2,$A14,"L",,"USD","H")/100} -> 0.089124 | CB14: {=_xll.ciqfunctions.udf.CIQ(B$3,$BV$1,$CB$2,$A14,"L",,"USD","H")/100} -> 0.143444 | CC14: {=_xll.ciqfunctions.udf.CIQ(C$3,$BV$1,$CB$2,$A14,"L",,"USD","H")/100} -> 0.198223 | CD14: {=_xll.ciqfunctions.udf.CIQ(D$3,$BV$1,$CB$2,$A14,"L",,"USD","H")/100} -> 0.137199 | CE14: {=_xll.ciqfunctions.udf.CIQ(E$3,$BV$1,$CB$2,$A14,"L",,"USD","H")/100} -> 0.280053 | CF14: {=_xll.ciqfunctions.udf.CIQ(F$3,$BV$1,$CB$2,$A14,"L",,"USD","H")/100} -> 0.148247 | CG14: {=_xll.ciqfunctions.udf.CIQ(G$3,$BV$1,$CB$2,$A14,"L",,"USD","H")/100} -> 0.159677
A15: =EDATE(A11,-12) -> 44926 | B15: {=_xll.ciqfunctions.udf.CIQ(B$3,$B$1,$B$2,$A15,"L",,"USD","H")} -> 19128 | C15: {=_xll.ciqfunctions.udf.CIQ(C$3,$B$1,$B$2,$A15,"L",,"USD","H")} -> 93790 | D15: {=_xll.ciqfunctions.udf.CIQ(D$3,$B$1,$B$2,$A15,"L",,"USD","H")} -> 53546 | E15: {=_xll.ciqfunctions.udf.CIQ(E$3,$B$1,$B$2,$A15,"L",,"USD","H")} -> 6513 | F15: {=_xll.ciqfunctions.udf.CIQ(F$3,$B$1,$B$2,$A15,"L",,"USD","H")} -> 68700 | G15: {=_xll.ciqfunctions.udf.CIQ(G$3,$B$1,$B$2,$A15,"L",,"USD","H")} -> 4142 | H15: {=_xll.ciqfunctions.udf.CIQ(B$3,$B$1,$H$2,$A15,"L",,"USD","H")} -> 80575 | I15: {=_xll.ciqfunctions.udf.CIQ(C$3,$B$1,$H$2,$A15,"L",,"USD","H")} -> 400737 | J15: {=_xll.ciqfunctions.udf.CIQ(D$3,$B$1,$H$2,$A15,"L",,"USD","H")} -> 235916 | K15: {=_xll.ciqfunctions.udf.CIQ(E$3,$B$1,$H$2,$A15,"L",,"USD","H")} -> 29610 | L15: {=_xll.ciqfunctions.udf.CIQ(F$3,$B$1,$H$2,$A15,"L",,"USD","H")} -> 239067 | M15: {=_xll.ciqfunctions.udf.CIQ(G$3,$B$1,$H$2,$A15,"L",,"USD","H")} -> 19827 | N15: {=_xll.ciqfunctions.udf.CIQ(B$3,$N$1,$B$2,$A15,"L",,"USD","H")} -> 23.7898 | O15: {=_xll.ciqfunctions.udf.CIQ(C$3,$N$1,$B$2,$A15,"L",,"USD","H")} -> 13.1567 | P15: {=_xll.ciqfunctions.udf.CIQ(D$3,$N$1,$B$2,$A15,"L",,"USD","H")} -> 18.1457 | Q15: {=_xll.ciqfunctions.udf.CIQ(E$3,$N$1,$B$2,$A15,"L",,"USD","H")} -> 9.7018 | R15: {=_xll.ciqfunctions.udf.CIQ(F$3,$N$1,$B$2,$A15,"L",,"USD","H")} -> 36.0315 | S15: {=_xll.ciqfunctions.udf.CIQ(G$3,$N$1,$B$2,$A15,"L",,"USD","H")} -> 2.1706 | T15: 4.9695 | U15: {=_xll.ciqfunctions.udf.CIQ(O$3,$N$1,$T$2,$A15,"L",,"USD","H")} -> 44.5973 | V15: {=_xll.ciqfunctions.udf.CIQ(P$3,$N$1,$T$2,$A15,"L",,"USD","H")} -> 52.1381 | W15: {=_xll.ciqfunctions.udf.CIQ(Q$3,$N$1,$T$2,$A15,"L",,"USD","H")} -> 49.7193 | X15: {=_xll.ciqfunctions.udf.CIQ(R$3,$N$1,$T$2,$A15,"L",,"USD","H")} -> 52.8258 | Y15: {=_xll.ciqfunctions.udf.CIQ(S$3,$N$1,$T$2,$A15,"L",,"USD","H")} -> 44.1963 | Z15: {=_xll.ciqfunctions.udf.CIQ(B$3,$Z$1,$B$2,$A15,"L",,"USD","H")} -> 3249 | AA15: {=_xll.ciqfunctions.udf.CIQ(C$3,$Z$1,$B$2,$A15,"L",,"USD","H")} -> 12750 | AB15: {=_xll.ciqfunctions.udf.CIQ(D$3,$Z$1,$B$2,$A15,"L",,"USD","H")} -> 6353 | AC15: {=_xll.ciqfunctions.udf.CIQ(E$3,$Z$1,$B$2,$A15,"L",,"USD","H")} -> 2277 | AD15: {=_xll.ciqfunctions.udf.CIQ(F$3,$Z$1,$B$2,$A15,"L",,"USD","H")} -> 10803 | AE15: {=_xll.ciqfunctions.udf.CIQ(G$3,$Z$1,$B$2,$A15,"L",,"USD","H")} -> 1201 | AF15: {=_xll.ciqfunctions.udf.CIQ(B$3,$Z$1,$H$2,$A15,"L",,"USD","H")} -> 18680 | AG15: {=_xll.ciqfunctions.udf.CIQ(C$3,$Z$1,$H$2,$A15,"L",,"USD","H")} -> 55740 | AH15: {=_xll.ciqfunctions.udf.CIQ(D$3,$Z$1,$H$2,$A15,"L",,"USD","H")} -> 35465 | AI15: {=_xll.ciqfunctions.udf.CIQ(E$3,$Z$1,$H$2,$A15,"L",,"USD","H")} -> 7759 | AJ15: {=_xll.ciqfunctions.udf.CIQ(F$3,$Z$1,$H$2,$A15,"L",,"USD","H")} -> -2487 | AK15: {=_xll.ciqfunctions.udf.CIQ(G$3,$Z$1,$H$2,$A15,"L",,"USD","H")} -> 6015 | AL15: {=_xll.ciqfunctions.udf.CIQ(B$3,$AL$1,$AL$2,$A15,"L",,"USD","H")} -> 23.6771 | AM15: {=_xll.ciqfunctions.udf.CIQ(C$3,$AL$1,$AL$2,$A15,"L",,"USD","H")} -> 43.7429 | AN15: {=_xll.ciqfunctions.udf.CIQ(D$3,$AL$1,$AL$2,$A15,"L",,"USD","H")} -> 25.6775 | AO15: {=_xll.ciqfunctions.udf.CIQ(E$3,$AL$1,$AL$2,$A15,"L",,"USD","H")} -> 14.7103 | AP15: {=_xll.ciqfunctions.udf.CIQ(F$3,$AL$1,$AL$2,$A15,"L",,"USD","H")} -> 364.4453 | AQ15: {=_xll.ciqfunctions.udf.CIQ(G$3,$AL$1,$AL$2,$A15,"L",,"USD","H")} -> -20.2524 | AR15: {=_xll.ciqfunctions.udf.CIQ(B$3,$AL$1,$AR$2,$A15,"L",,"USD","H")} -> 131.2167 | AS15: {=_xll.ciqfunctions.udf.CIQ(C$3,$AL$1,$AR$2,$A15,"L",,"USD","H")} -> 141.927 | AT15: {=_xll.ciqfunctions.udf.CIQ(D$3,$AL$1,$AR$2,$A15,"L",,"USD","H")} -> 126.976 | AU15: {=_xll.ciqfunctions.udf.CIQ(E$3,$AL$1,$AR$2,$A15,"L",,"USD","H")} -> 66.3593 | AV15: {=_xll.ciqfunctions.udf.CIQ(F$3,$AL$1,$AR$2,$A15,"L",,"USD","H")} -> NM | AW15: {=_xll.ciqfunctions.udf.CIQ(G$3,$AL$1,$AR$2,$A15,"L",,"USD","H")} -> 113.8286 | AX15: {=_xll.ciqfunctions.udf.CIQ(B$3,$AX$1,$AX$2,$A15,"L",,"USD","H")} -> 7391 | AY15: {=_xll.ciqfunctions.udf.CIQ(C$3,$AX$1,$AX$2,$A15,"L",,"USD","H")} -> 17974 | AZ15: {=_xll.ciqfunctions.udf.CIQ(D$3,$AX$1,$AX$2,$A15,"L",,"USD","H")} -> 13058 | BA15: {=_xll.ciqfunctions.udf.CIQ(E$3,$AX$1,$AX$2,$A15,"L",,"USD","H")} -> 3875 | BB15: {=_xll.ciqfunctions.udf.CIQ(F$3,$AX$1,$AX$2,$A15,"L",,"USD","H")} -> 21793 | BC15: {=_xll.ciqfunctions.udf.CIQ(G$3,$AX$1,$AX$2,$A15,"L",,"USD","H")} -> 2199 | BD15: {=_xll.ciqfunctions.udf.CIQ(B$3,$AX$1,$BD$2,$A15,"L",,"USD","H")} -> 34916 | BE15: {=_xll.ciqfunctions.udf.CIQ(C$3,$AX$1,$BD$2,$A15,"L",,"USD","H")} -> 89648 | BF15: {=_xll.ciqfunctions.udf.CIQ(D$3,$AX$1,$BD$2,$A15,"L",,"USD","H")} -> 57447 | BG15: =_xll.ciqfunctions.udf.CIQ("COP", "IQ_PRICEDATE", "10/24/2025") -> 45954 | BH15: {=_xll.ciqfunctions.udf.CIQ(F$3,$AX$1,$BD$2,$A15,"L",,"USD","H")} -> 55549 | BI15: {=_xll.ciqfunctions.udf.CIQ(G$3,$AX$1,$BD$2,$A15,"L",,"USD","H")} -> 10288 | BJ15: =AX15/AX19-1 -> 0.080555556 | BK15: =AY15/AY19-1 -> 0.15299249 | BL15: =AZ15/AZ19-1 -> 0.31328573 | BM15: =BA15/BA19-1 -> 0.058743169 | BN15: =BB15/BB19-1 -> 1.0298994 | BO15: =BC15/BC19-1 -> -0.048875433 | BP15: =BD15/BD19-1 -> 0.72220578 | BQ15: =BE15/BE19-1 -> 1.0242052 | ... BU15: =BI15/BI19-1 -> 0.86952571 | BV15: {=_xll.ciqfunctions.udf.CIQ(B$3,$BV$1,$BV$2,$A15,"L",,"USD","H")/100} -> 0.052364 | BW15: {=_xll.ciqfunctions.udf.CIQ(C$3,$BV$1,$BV$2,$A15,"L",,"USD","H")/100} -> 0.1473 | BX15: {=_xll.ciqfunctions.udf.CIQ(D$3,$BV$1,$BV$2,$A15,"L",,"USD","H")/100} -> 0.078512 | BY15: {=_xll.ciqfunctions.udf.CIQ(E$3,$BV$1,$BV$2,$A15,"L",,"USD","H")/100} -> 0.30408 | BZ15: {=_xll.ciqfunctions.udf.CIQ(F$3,$BV$1,$BV$2,$A15,"L",,"USD","H")/100} -> 0.324568 | CA15: {=_xll.ciqfunctions.udf.CIQ(G$3,$BV$1,$BV$2,$A15,"L",,"USD","H")/100} -> 0.072936 | CB15: {=_xll.ciqfunctions.udf.CIQ(B$3,$BV$1,$CB$2,$A15,"L",,"USD","H")/100} -> 0.197472 | CC15: {=_xll.ciqfunctions.udf.CIQ(C$3,$BV$1,$CB$2,$A15,"L",,"USD","H")/100} -> 0.170678 | CD15: {=_xll.ciqfunctions.udf.CIQ(D$3,$BV$1,$CB$2,$A15,"L",,"USD","H")/100} -> 0.135184 | CE15: {=_xll.ciqfunctions.udf.CIQ(E$3,$BV$1,$CB$2,$A15,"L",,"USD","H")/100} -> 0.088773 | CF15: {=_xll.ciqfunctions.udf.CIQ(F$3,$BV$1,$CB$2,$A15,"L",,"USD","H")/100} -> -0.04583 | CG15: {=_xll.ciqfunctions.udf.CIQ(G$3,$BV$1,$CB$2,$A15,"L",,"USD","H")/100} -> 0.154273
A16: =EDATE(A12,-12) -> 44834 | B16: {=_xll.ciqfunctions.udf.CIQ(B$3,$B$1,$B$2,$A16,"L",,"USD","H")} -> 21574 | C16: {=_xll.ciqfunctions.udf.CIQ(C$3,$B$1,$B$2,$A16,"L",,"USD","H")} -> 107438 | D16: {=_xll.ciqfunctions.udf.CIQ(D$3,$B$1,$B$2,$A16,"L",,"USD","H")} -> 64244 | E16: {=_xll.ciqfunctions.udf.CIQ(E$3,$B$1,$B$2,$A16,"L",,"USD","H")} -> 7632 | F16: {=_xll.ciqfunctions.udf.CIQ(F$3,$B$1,$B$2,$A16,"L",,"USD","H")} -> 54372 | G16: {=_xll.ciqfunctions.udf.CIQ(G$3,$B$1,$B$2,$A16,"L",,"USD","H")} -> 5184 | H16: {=_xll.ciqfunctions.udf.CIQ(B$3,$B$1,$H$2,$A16,"L",,"USD","H")} -> 76899 | I16: {=_xll.ciqfunctions.udf.CIQ(C$3,$B$1,$H$2,$A16,"L",,"USD","H")} -> 390278 | J16: {=_xll.ciqfunctions.udf.CIQ(D$3,$B$1,$H$2,$A16,"L",,"USD","H")} -> 227692 | K16: {=_xll.ciqfunctions.udf.CIQ(E$3,$B$1,$H$2,$A16,"L",,"USD","H")} -> 29034 | L16: {=_xll.ciqfunctions.udf.CIQ(F$3,$B$1,$H$2,$A16,"L",,"USD","H")} -> 220870 | M16: {=_xll.ciqfunctions.udf.CIQ(G$3,$B$1,$H$2,$A16,"L",,"USD","H")} -> 18785 | N16: {=_xll.ciqfunctions.udf.CIQ(B$3,$N$1,$B$2,$A16,"L",,"USD","H")} -> 86.5456 | O16: {=_xll.ciqfunctions.udf.CIQ(C$3,$N$1,$B$2,$A16,"L",,"USD","H")} -> 48.9794 | P16: {=_xll.ciqfunctions.udf.CIQ(D$3,$N$1,$B$2,$A16,"L",,"USD","H")} -> 50.9776 | Q16: {=_xll.ciqfunctions.udf.CIQ(E$3,$N$1,$B$2,$A16,"L",,"USD","H")} -> 45.1502 | R16: {=_xll.ciqfunctions.udf.CIQ(F$3,$N$1,$B$2,$A16,"L",,"USD","H")} -> 51.7922 | S16: {=_xll.ciqfunctions.udf.CIQ(G$3,$N$1,$B$2,$A16,"L",,"USD","H")} -> 36.3851 | T16: 45968 | U16: {=_xll.ciqfunctions.udf.CIQ(O$3,$N$1,$T$2,$A16,"L",,"USD","H")} -> 61.0728 | V16: {=_xll.ciqfunctions.udf.CIQ(P$3,$N$1,$T$2,$A16,"L",,"USD","H")} -> 69.6712 | W16: {=_xll.ciqfunctions.udf.CIQ(Q$3,$N$1,$T$2,$A16,"L",,"USD","H")} -> 73.4304 | X16: {=_xll.ciqfunctions.udf.CIQ(R$3,$N$1,$T$2,$A16,"L",,"USD","H")} -> 64.9822 | Y16: {=_xll.ciqfunctions.udf.CIQ(S$3,$N$1,$T$2,$A16,"L",,"USD","H")} -> 80.3995 | Z16: {=_xll.ciqfunctions.udf.CIQ(B$3,$Z$1,$B$2,$A16,"L",,"USD","H")} -> 4527 | AA16: {=_xll.ciqfunctions.udf.CIQ(C$3,$Z$1,$B$2,$A16,"L",,"USD","H")} -> 19660 | AB16: {=_xll.ciqfunctions.udf.CIQ(D$3,$Z$1,$B$2,$A16,"L",,"USD","H")} -> 11231 | AC16: {=_xll.ciqfunctions.udf.CIQ(E$3,$Z$1,$B$2,$A16,"L",,"USD","H")} -> 2854 | AD16: {=_xll.ciqfunctions.udf.CIQ(F$3,$Z$1,$B$2,$A16,"L",,"USD","H")} -> -2163 | AE16: {=_xll.ciqfunctions.udf.CIQ(G$3,$Z$1,$B$2,$A16,"L",,"USD","H")} -> 1893 | AF16: {=_xll.ciqfunctions.udf.CIQ(B$3,$Z$1,$H$2,$A16,"L",,"USD","H")} -> 18058 | AG16: {=_xll.ciqfunctions.udf.CIQ(C$3,$Z$1,$H$2,$A16,"L",,"USD","H")} -> 51860 | AH16: {=_xll.ciqfunctions.udf.CIQ(D$3,$Z$1,$H$2,$A16,"L",,"USD","H")} -> 34167 | AI16: {=_xll.ciqfunctions.udf.CIQ(E$3,$Z$1,$H$2,$A16,"L",,"USD","H")} -> 7467 | AJ16: {=_xll.ciqfunctions.udf.CIQ(F$3,$Z$1,$H$2,$A16,"L",,"USD","H")} -> -10964 | AK16: {=_xll.ciqfunctions.udf.CIQ(G$3,$Z$1,$H$2,$A16,"L",,"USD","H")} -> 6320 | AL16: {=_xll.ciqfunctions.udf.CIQ(B$3,$AL$1,$AL$2,$A16,"L",,"USD","H")} -> 90.29 | AM16: {=_xll.ciqfunctions.udf.CIQ(C$3,$AL$1,$AL$2,$A16,"L",,"USD","H")} -> 191.2592 | AN16: {=_xll.ciqfunctions.udf.CIQ(D$3,$AL$1,$AL$2,$A16,"L",,"USD","H")} -> 83.7833 | AO16: {=_xll.ciqfunctions.udf.CIQ(E$3,$AL$1,$AL$2,$A16,"L",,"USD","H")} -> 160.6392 | AP16: {=_xll.ciqfunctions.udf.CIQ(F$3,$AL$1,$AL$2,$A16,"L",,"USD","H")} -> NM | AQ16: {=_xll.ciqfunctions.udf.CIQ(G$3,$AL$1,$AL$2,$A16,"L",,"USD","H")} -> 125.8949 | AR16: {=_xll.ciqfunctions.udf.CIQ(B$3,$AL$1,$AR$2,$A16,"L",,"USD","H")} -> 285.8547 | AS16: {=_xll.ciqfunctions.udf.CIQ(C$3,$AL$1,$AR$2,$A16,"L",,"USD","H")} -> NM | AT16: {=_xll.ciqfunctions.udf.CIQ(D$3,$AL$1,$AR$2,$A16,"L",,"USD","H")} -> 244.9469 | AU16: {=_xll.ciqfunctions.udf.CIQ(E$3,$AL$1,$AR$2,$A16,"L",,"USD","H")} -> 147.5795 | AV16: {=_xll.ciqfunctions.udf.CIQ(F$3,$AL$1,$AR$2,$A16,"L",,"USD","H")} -> NM | AW16: {=_xll.ciqfunctions.udf.CIQ(G$3,$AL$1,$AR$2,$A16,"L",,"USD","H")} -> 424.4813 | AX16: {=_xll.ciqfunctions.udf.CIQ(B$3,$AX$1,$AX$2,$A16,"L",,"USD","H")} -> 9383 | AY16: {=_xll.ciqfunctions.udf.CIQ(C$3,$AX$1,$AX$2,$A16,"L",,"USD","H")} -> 33985 | AZ16: {=_xll.ciqfunctions.udf.CIQ(D$3,$AX$1,$AX$2,$A16,"L",,"USD","H")} -> 16728 | BA16: {=_xll.ciqfunctions.udf.CIQ(E$3,$AX$1,$AX$2,$A16,"L",,"USD","H")} -> 4685 | BB16: {=_xll.ciqfunctions.udf.CIQ(F$3,$AX$1,$AX$2,$A16,"L",,"USD","H")} -> 3905 | BC16: {=_xll.ciqfunctions.udf.CIQ(G$3,$AX$1,$AX$2,$A16,"L",,"USD","H")} -> 3120 | BD16: {=_xll.ciqfunctions.udf.CIQ(B$3,$AX$1,$BD$2,$A16,"L",,"USD","H")} -> 34365 | BE16: {=_xll.ciqfunctions.udf.CIQ(C$3,$AX$1,$BD$2,$A16,"L",,"USD","H")} -> 95153 | BF16: {=_xll.ciqfunctions.udf.CIQ(D$3,$AX$1,$BD$2,$A16,"L",,"USD","H")} -> 54332 | BG16: =_xll.ciqfunctions.udf.CIQ("COP", "IQ_PRICEDATE", "10/17/2025") -> 45947 | BH16: {=_xll.ciqfunctions.udf.CIQ(F$3,$AX$1,$BD$2,$A16,"L",,"USD","H")} -> 38088 | BI16: {=_xll.ciqfunctions.udf.CIQ(G$3,$AX$1,$BD$2,$A16,"L",,"USD","H")} -> 10381 | BJ16: =AX16/AX20-1 -> 0.76008254 | BK16: =AY16/AY20-1 -> 1.5863775 | BL16: =AZ16/AZ20-1 -> 0.61358156 | BM16: =BA16/BA20-1 -> 0.88987495 | BN16: =BB16/BB20-1 -> 0.44576083 | BO16: =BC16/BC20-1 -> 0.88633615 | BP16: =BD16/BD20-1 -> 1.3560263 | BQ16: =BE16/BE20-1 -> 1.7439802 | ... BU16: =BI16/BI20-1 -> 1.9600798 | BV16: {=_xll.ciqfunctions.udf.CIQ(B$3,$BV$1,$BV$2,$A16,"L",,"USD","H")/100} -> 0.182744 | BW16: {=_xll.ciqfunctions.udf.CIQ(C$3,$BV$1,$BV$2,$A16,"L",,"USD","H")/100} -> 0.271992 | BX16: {=_xll.ciqfunctions.udf.CIQ(D$3,$BV$1,$BV$2,$A16,"L",,"USD","H")/100} -> 0.186516 | BY16: {=_xll.ciqfunctions.udf.CIQ(E$3,$BV$1,$BV$2,$A16,"L",,"USD","H")/100} -> 0.217232 | BZ16: {=_xll.ciqfunctions.udf.CIQ(F$3,$BV$1,$BV$2,$A16,"L",,"USD","H")/100} -> -0.097764 | CA16: {=_xll.ciqfunctions.udf.CIQ(G$3,$BV$1,$BV$2,$A16,"L",,"USD","H")/100} -> 0.20418 | CB16: {=_xll.ciqfunctions.udf.CIQ(B$3,$BV$1,$CB$2,$A16,"L",,"USD","H")/100} -> 0.217419 | CC16: {=_xll.ciqfunctions.udf.CIQ(C$3,$BV$1,$CB$2,$A16,"L",,"USD","H")/100} -> 0.159647 | CD16: {=_xll.ciqfunctions.udf.CIQ(D$3,$BV$1,$CB$2,$A16,"L",,"USD","H")/100} -> 0.13066 | CE16: {=_xll.ciqfunctions.udf.CIQ(E$3,$BV$1,$CB$2,$A16,"L",,"USD","H")/100} -> 0.141847 | CF16: {=_xll.ciqfunctions.udf.CIQ(F$3,$BV$1,$CB$2,$A16,"L",,"USD","H")/100} -> -0.105996 | CG16: {=_xll.ciqfunctions.udf.CIQ(G$3,$BV$1,$CB$2,$A16,"L",,"USD","H")/100} -> 0.194288
A17: =EDATE(A13,-12) -> 44742 | B17: {=_xll.ciqfunctions.udf.CIQ(B$3,$B$1,$B$2,$A17,"L",,"USD","H")} -> 21685 | C17: {=_xll.ciqfunctions.udf.CIQ(C$3,$B$1,$B$2,$A17,"L",,"USD","H")} -> 111993 | D17: {=_xll.ciqfunctions.udf.CIQ(D$3,$B$1,$B$2,$A17,"L",,"USD","H")} -> 66305 | E17: {=_xll.ciqfunctions.udf.CIQ(E$3,$B$1,$B$2,$A17,"L",,"USD","H")} -> 8687 | F17: {=_xll.ciqfunctions.udf.CIQ(F$3,$B$1,$B$2,$A17,"L",,"USD","H")} -> 67242 | G17: {=_xll.ciqfunctions.udf.CIQ(G$3,$B$1,$B$2,$A17,"L",,"USD","H")} -> 5544 | H17: {=_xll.ciqfunctions.udf.CIQ(B$3,$B$1,$H$2,$A17,"L",,"USD","H")} -> 66890 | I17: {=_xll.ciqfunctions.udf.CIQ(C$3,$B$1,$H$2,$A17,"L",,"USD","H")} -> 354956 | J17: {=_xll.ciqfunctions.udf.CIQ(D$3,$B$1,$H$2,$A17,"L",,"USD","H")} -> 206000 | K17: {=_xll.ciqfunctions.udf.CIQ(E$3,$B$1,$H$2,$A17,"L",,"USD","H")} -> 26660 | L17: {=_xll.ciqfunctions.udf.CIQ(F$3,$B$1,$H$2,$A17,"L",,"USD","H")} -> 202318 | M17: {=_xll.ciqfunctions.udf.CIQ(G$3,$B$1,$H$2,$A17,"L",,"USD","H")} -> 17402 | N17: {=_xll.ciqfunctions.udf.CIQ(B$3,$N$1,$B$2,$A17,"L",,"USD","H")} -> 123.6719 | O17: {=_xll.ciqfunctions.udf.CIQ(C$3,$N$1,$B$2,$A17,"L",,"USD","H")} -> 68.9032 | P17: {=_xll.ciqfunctions.udf.CIQ(D$3,$N$1,$B$2,$A17,"L",,"USD","H")} -> 83.5839 | Q17: {=_xll.ciqfunctions.udf.CIQ(E$3,$N$1,$B$2,$A17,"L",,"USD","H")} -> 92.4031 | R17: {=_xll.ciqfunctions.udf.CIQ(F$3,$N$1,$B$2,$A17,"L",,"USD","H")} -> 85.8951 | S17: {=_xll.ciqfunctions.udf.CIQ(G$3,$N$1,$B$2,$A17,"L",,"USD","H")} -> 88.3152 | T17: 45961 | U17: {=_xll.ciqfunctions.udf.CIQ(O$3,$N$1,$T$2,$A17,"L",,"USD","H")} -> 64.4235 | V17: {=_xll.ciqfunctions.udf.CIQ(P$3,$N$1,$T$2,$A17,"L",,"USD","H")} -> 78.1375 | W17: {=_xll.ciqfunctions.udf.CIQ(Q$3,$N$1,$T$2,$A17,"L",,"USD","H")} -> 93.1324 | X17: {=_xll.ciqfunctions.udf.CIQ(R$3,$N$1,$T$2,$A17,"L",,"USD","H")} -> 62.8615 | Y17: {=_xll.ciqfunctions.udf.CIQ(S$3,$N$1,$T$2,$A17,"L",,"USD","H")} -> 124.0793 | Z17: {=_xll.ciqfunctions.udf.CIQ(B$3,$Z$1,$B$2,$A17,"L",,"USD","H")} -> 5145 | AA17: {=_xll.ciqfunctions.udf.CIQ(C$3,$Z$1,$B$2,$A17,"L",,"USD","H")} -> 17850 | AB17: {=_xll.ciqfunctions.udf.CIQ(D$3,$Z$1,$B$2,$A17,"L",,"USD","H")} -> 11622 | AC17: {=_xll.ciqfunctions.udf.CIQ(E$3,$Z$1,$B$2,$A17,"L",,"USD","H")} -> 2238 | AD17: {=_xll.ciqfunctions.udf.CIQ(F$3,$Z$1,$B$2,$A17,"L",,"USD","H")} -> 9257 | AE17: {=_xll.ciqfunctions.udf.CIQ(G$3,$Z$1,$B$2,$A17,"L",,"USD","H")} -> 1932 | AF17: {=_xll.ciqfunctions.udf.CIQ(B$3,$Z$1,$H$2,$A17,"L",,"USD","H")} -> 15910 | AG17: {=_xll.ciqfunctions.udf.CIQ(C$3,$Z$1,$H$2,$A17,"L",,"USD","H")} -> 38950 | AH17: {=_xll.ciqfunctions.udf.CIQ(D$3,$Z$1,$H$2,$A17,"L",,"USD","H")} -> 29047 | AI17: {=_xll.ciqfunctions.udf.CIQ(E$3,$Z$1,$H$2,$A17,"L",,"USD","H")} -> 5708 | AJ17: {=_xll.ciqfunctions.udf.CIQ(F$3,$Z$1,$H$2,$A17,"L",,"USD","H")} -> -11345 | AK17: {=_xll.ciqfunctions.udf.CIQ(G$3,$Z$1,$H$2,$A17,"L",,"USD","H")} -> 5265 | AL17: {=_xll.ciqfunctions.udf.CIQ(B$3,$AL$1,$AL$2,$A17,"L",,"USD","H")} -> 146.0545 | AM17: {=_xll.ciqfunctions.udf.CIQ(C$3,$AL$1,$AL$2,$A17,"L",,"USD","H")} -> 280.597 | AN17: {=_xll.ciqfunctions.udf.CIQ(D$3,$AL$1,$AL$2,$A17,"L",,"USD","H")} -> 277.0927 | AO17: {=_xll.ciqfunctions.udf.CIQ(E$3,$AL$1,$AL$2,$A17,"L",,"USD","H")} -> 146.7475 | AP17: {=_xll.ciqfunctions.udf.CIQ(F$3,$AL$1,$AL$2,$A17,"L",,"USD","H")} -> 197.0795 | AQ17: {=_xll.ciqfunctions.udf.CIQ(G$3,$AL$1,$AL$2,$A17,"L",,"USD","H")} -> 654.6875 | AR17: {=_xll.ciqfunctions.udf.CIQ(B$3,$AL$1,$AR$2,$A17,"L",,"USD","H")} -> 759.5353 | AS17: {=_xll.ciqfunctions.udf.CIQ(C$3,$AL$1,$AR$2,$A17,"L",,"USD","H")} -> NM | AT17: {=_xll.ciqfunctions.udf.CIQ(D$3,$AL$1,$AR$2,$A17,"L",,"USD","H")} -> 709.7853 | AU17: {=_xll.ciqfunctions.udf.CIQ(E$3,$AL$1,$AR$2,$A17,"L",,"USD","H")} -> 203.7786 | AV17: {=_xll.ciqfunctions.udf.CIQ(F$3,$AL$1,$AR$2,$A17,"L",,"USD","H")} -> NM | AW17: {=_xll.ciqfunctions.udf.CIQ(G$3,$AL$1,$AR$2,$A17,"L",,"USD","H")} -> 1814.5454 | AX17: {=_xll.ciqfunctions.udf.CIQ(B$3,$AX$1,$AX$2,$A17,"L",,"USD","H")} -> 9405 | AY17: {=_xll.ciqfunctions.udf.CIQ(C$3,$AX$1,$AX$2,$A17,"L",,"USD","H")} -> 25890 | AZ17: {=_xll.ciqfunctions.udf.CIQ(D$3,$AX$1,$AX$2,$A17,"L",,"USD","H")} -> 17368 | BA17: {=_xll.ciqfunctions.udf.CIQ(E$3,$AX$1,$AX$2,$A17,"L",,"USD","H")} -> 3808 | BB17: {=_xll.ciqfunctions.udf.CIQ(F$3,$AX$1,$AX$2,$A17,"L",,"USD","H")} -> 17015 | BC17: {=_xll.ciqfunctions.udf.CIQ(G$3,$AX$1,$AX$2,$A17,"L",,"USD","H")} -> 3106 | BD17: {=_xll.ciqfunctions.udf.CIQ(B$3,$AX$1,$BD$2,$A17,"L",,"USD","H")} -> 30313 | BE17: {=_xll.ciqfunctions.udf.CIQ(C$3,$AX$1,$BD$2,$A17,"L",,"USD","H")} -> 74308 | BF17: {=_xll.ciqfunctions.udf.CIQ(D$3,$AX$1,$BD$2,$A17,"L",,"USD","H")} -> 47936 | BG17: =_xll.ciqfunctions.udf.CIQ("COP", "IQ_PRICEDATE", "10/10/2025") -> 45940 | BH17: {=_xll.ciqfunctions.udf.CIQ(F$3,$AX$1,$BD$2,$A17,"L",,"USD","H")} -> 36884 | BI17: {=_xll.ciqfunctions.udf.CIQ(G$3,$AX$1,$BD$2,$A17,"L",,"USD","H")} -> 8915 | BJ17: =AX17/AX21-1 -> 1.0178073 | BK17: =AY17/AY21-1 -> 1.569217 | BL17: =AZ17/AZ21-1 -> 1.2706236 | BM17: =BA17/BA21-1 -> 0.83253128 | BN17: =BB17/BB21-1 -> 2.1445204 | BO17: =BC17/BC21-1 -> 2.5949074 | BP17: =BD17/BD21-1 -> 1.9172361 | BQ17: =BE17/BE21-1 -> 1.9856959 | ... BU17: =BI17/BI21-1 -> 3.2594362 | BV17: {=_xll.ciqfunctions.udf.CIQ(B$3,$BV$1,$BV$2,$A17,"L",,"USD","H")/100} -> 0.246088 | BW17: {=_xll.ciqfunctions.udf.CIQ(C$3,$BV$1,$BV$2,$A17,"L",,"USD","H")/100} -> 0.248068 | BX17: {=_xll.ciqfunctions.udf.CIQ(D$3,$BV$1,$BV$2,$A17,"L",,"USD","H")/100} -> 0.198324 | BY17: {=_xll.ciqfunctions.udf.CIQ(E$3,$BV$1,$BV$2,$A17,"L",,"USD","H")/100} -> 0.11042 | BZ17: {=_xll.ciqfunctions.udf.CIQ(F$3,$BV$1,$BV$2,$A17,"L",,"USD","H")/100} -> 0.226008 | CA17: {=_xll.ciqfunctions.udf.CIQ(G$3,$BV$1,$BV$2,$A17,"L",,"USD","H")/100} -> 0.265924 | CB17: {=_xll.ciqfunctions.udf.CIQ(B$3,$BV$1,$CB$2,$A17,"L",,"USD","H")/100} -> 0.195802 | CC17: {=_xll.ciqfunctions.udf.CIQ(C$3,$BV$1,$CB$2,$A17,"L",,"USD","H")/100} -> 0.104817 | CD17: {=_xll.ciqfunctions.udf.CIQ(D$3,$BV$1,$CB$2,$A17,"L",,"USD","H")/100} -> 0.102855 | CE17: {=_xll.ciqfunctions.udf.CIQ(E$3,$BV$1,$CB$2,$A17,"L",,"USD","H")/100} -> 0.101191 | CF17: {=_xll.ciqfunctions.udf.CIQ(F$3,$BV$1,$CB$2,$A17,"L",,"USD","H")/100} -> -0.100074 | CG17: {=_xll.ciqfunctions.udf.CIQ(G$3,$BV$1,$CB$2,$A17,"L",,"USD","H")/100} -> 0.178648
A18: =EDATE(A14,-12) -> 44651 | B18: {=_xll.ciqfunctions.udf.CIQ(B$3,$B$1,$B$2,$A18,"L",,"USD","H")} -> 18188 | C18: {=_xll.ciqfunctions.udf.CIQ(C$3,$B$1,$B$2,$A18,"L",,"USD","H")} -> 87962 | D18: {=_xll.ciqfunctions.udf.CIQ(D$3,$B$1,$B$2,$A18,"L",,"USD","H")} -> 51821 | E18: {=_xll.ciqfunctions.udf.CIQ(E$3,$B$1,$B$2,$A18,"L",,"USD","H")} -> 6778 | F18: {=_xll.ciqfunctions.udf.CIQ(F$3,$B$1,$B$2,$A18,"L",,"USD","H")} -> 48753 | G18: {=_xll.ciqfunctions.udf.CIQ(G$3,$B$1,$B$2,$A18,"L",,"USD","H")} -> 4003 | H18: {=_xll.ciqfunctions.udf.CIQ(B$3,$B$1,$H$2,$A18,"L",,"USD","H")} -> 54900 | I18: {=_xll.ciqfunctions.udf.CIQ(C$3,$B$1,$H$2,$A18,"L",,"USD","H")} -> 309269 | J18: {=_xll.ciqfunctions.udf.CIQ(D$3,$B$1,$H$2,$A18,"L",,"USD","H")} -> 175812 | K18: {=_xll.ciqfunctions.udf.CIQ(E$3,$B$1,$H$2,$A18,"L",,"USD","H")} -> 22488 | L18: {=_xll.ciqfunctions.udf.CIQ(F$3,$B$1,$H$2,$A18,"L",,"USD","H")} -> 171248 | M18: {=_xll.ciqfunctions.udf.CIQ(G$3,$B$1,$H$2,$A18,"L",,"USD","H")} -> 14802 | N18: {=_xll.ciqfunctions.udf.CIQ(B$3,$N$1,$B$2,$A18,"L",,"USD","H")} -> 82.8307 | O18: {=_xll.ciqfunctions.udf.CIQ(C$3,$N$1,$B$2,$A18,"L",,"USD","H")} -> 52.5158 | P18: {=_xll.ciqfunctions.udf.CIQ(D$3,$N$1,$B$2,$A18,"L",,"USD","H")} -> 66.7556 | Q18: {=_xll.ciqfunctions.udf.CIQ(E$3,$N$1,$B$2,$A18,"L",,"USD","H")} -> 66.6584 | R18: {=_xll.ciqfunctions.udf.CIQ(F$3,$N$1,$B$2,$A18,"L",,"USD","H")} -> 42.1743 | S18: {=_xll.ciqfunctions.udf.CIQ(G$3,$N$1,$B$2,$A18,"L",,"USD","H")} -> 72.6919 | T18: 45954 | U18: {=_xll.ciqfunctions.udf.CIQ(O$3,$N$1,$T$2,$A18,"L",,"USD","H")} -> 69.858 | V18: {=_xll.ciqfunctions.udf.CIQ(P$3,$N$1,$T$2,$A18,"L",,"USD","H")} -> 84.1927 | W18: {=_xll.ciqfunctions.udf.CIQ(Q$3,$N$1,$T$2,$A18,"L",,"USD","H")} -> 114.0694 | X18: {=_xll.ciqfunctions.udf.CIQ(R$3,$N$1,$T$2,$A18,"L",,"USD","H")} -> 56.8305 | Y18: {=_xll.ciqfunctions.udf.CIQ(S$3,$N$1,$T$2,$A18,"L",,"USD","H")} -> 167.4254 | Z18: {=_xll.ciqfunctions.udf.CIQ(B$3,$Z$1,$B$2,$A18,"L",,"USD","H")} -> 5759 | AA18: {=_xll.ciqfunctions.udf.CIQ(C$3,$Z$1,$B$2,$A18,"L",,"USD","H")} -> 5480 | AB18: {=_xll.ciqfunctions.udf.CIQ(D$3,$Z$1,$B$2,$A18,"L",,"USD","H")} -> 6259 | AC18: {=_xll.ciqfunctions.udf.CIQ(E$3,$Z$1,$B$2,$A18,"L",,"USD","H")} -> 390 | AD18: {=_xll.ciqfunctions.udf.CIQ(F$3,$Z$1,$B$2,$A18,"L",,"USD","H")} -> -20384 | AE18: {=_xll.ciqfunctions.udf.CIQ(G$3,$Z$1,$B$2,$A18,"L",,"USD","H")} -> 989 | AF18: {=_xll.ciqfunctions.udf.CIQ(B$3,$Z$1,$H$2,$A18,"L",,"USD","H")} -> 12856 | AG18: {=_xll.ciqfunctions.udf.CIQ(C$3,$Z$1,$H$2,$A18,"L",,"USD","H")} -> 25790 | AH18: {=_xll.ciqfunctions.udf.CIQ(D$3,$Z$1,$H$2,$A18,"L",,"USD","H")} -> 20507 | AI18: {=_xll.ciqfunctions.udf.CIQ(E$3,$Z$1,$H$2,$A18,"L",,"USD","H")} -> 4377 | AJ18: {=_xll.ciqfunctions.udf.CIQ(F$3,$Z$1,$H$2,$A18,"L",,"USD","H")} -> -17486 | AK18: {=_xll.ciqfunctions.udf.CIQ(G$3,$Z$1,$H$2,$A18,"L",,"USD","H")} -> 3589 | AL18: {=_xll.ciqfunctions.udf.CIQ(B$3,$AL$1,$AL$2,$A18,"L",,"USD","H")} -> 486.4562 | AM18: {=_xll.ciqfunctions.udf.CIQ(C$3,$AL$1,$AL$2,$A18,"L",,"USD","H")} -> 100.7326 | AN18: {=_xll.ciqfunctions.udf.CIQ(D$3,$AL$1,$AL$2,$A18,"L",,"USD","H")} -> 354.5388 | AO18: {=_xll.ciqfunctions.udf.CIQ(E$3,$AL$1,$AL$2,$A18,"L",,"USD","H")} -> -42.393 | AP18: {=_xll.ciqfunctions.udf.CIQ(F$3,$AL$1,$AL$2,$A18,"L",,"USD","H")} -> NM | AQ18: {=_xll.ciqfunctions.udf.CIQ(G$3,$AL$1,$AL$2,$A18,"L",,"USD","H")} -> 364.3192 | AR18: {=_xll.ciqfunctions.udf.CIQ(B$3,$AL$1,$AR$2,$A18,"L",,"USD","H")} -> 64180 | AS18: {=_xll.ciqfunctions.udf.CIQ(C$3,$AL$1,$AR$2,$A18,"L",,"USD","H")} -> NM | AT18: {=_xll.ciqfunctions.udf.CIQ(D$3,$AL$1,$AR$2,$A18,"L",,"USD","H")} -> NM | AU18: {=_xll.ciqfunctions.udf.CIQ(E$3,$AL$1,$AR$2,$A18,"L",,"USD","H")} -> 6959.6774 | AV18: {=_xll.ciqfunctions.udf.CIQ(F$3,$AL$1,$AR$2,$A18,"L",,"USD","H")} -> NM | AW18: {=_xll.ciqfunctions.udf.CIQ(G$3,$AL$1,$AR$2,$A18,"L",,"USD","H")} -> NM | AX18: {=_xll.ciqfunctions.udf.CIQ(B$3,$AX$1,$AX$2,$A18,"L",,"USD","H")} -> 8737 | AY18: {=_xll.ciqfunctions.udf.CIQ(C$3,$AX$1,$AX$2,$A18,"L",,"USD","H")} -> 15089 | AZ18: {=_xll.ciqfunctions.udf.CIQ(D$3,$AX$1,$AX$2,$A18,"L",,"USD","H")} -> 10293 | BA18: {=_xll.ciqfunctions.udf.CIQ(E$3,$AX$1,$AX$2,$A18,"L",,"USD","H")} -> 1423 | BB18: {=_xll.ciqfunctions.udf.CIQ(F$3,$AX$1,$AX$2,$A18,"L",,"USD","H")} -> 10867 | BC18: {=_xll.ciqfunctions.udf.CIQ(G$3,$AX$1,$AX$2,$A18,"L",,"USD","H")} -> 1843 | BD18: {=_xll.ciqfunctions.udf.CIQ(B$3,$AX$1,$BD$2,$A18,"L",,"USD","H")} -> 25569 | BE18: {=_xll.ciqfunctions.udf.CIQ(C$3,$AX$1,$BD$2,$A18,"L",,"USD","H")} -> 53895 | BF18: {=_xll.ciqfunctions.udf.CIQ(D$3,$AX$1,$BD$2,$A18,"L",,"USD","H")} -> 38256 | BG18: =_xll.ciqfunctions.udf.CIQ("COP", "IQ_PRICEDATE", "10/3/2025") -> 45933 | BH18: {=_xll.ciqfunctions.udf.CIQ(F$3,$AX$1,$BD$2,$A18,"L",,"USD","H")} -> 25280 | BI18: {=_xll.ciqfunctions.udf.CIQ(G$3,$AX$1,$BD$2,$A18,"L",,"USD","H")} -> 6673 | BJ18: =AX18/AX22-1 -> 1.676777 | BK18: =AY18/AY22-1 -> 1.0443029 | BL18: =AZ18/AZ22-1 -> 0.81566414 | BM18: =BA18/BA22-1 -> -0.24388948 | BN18: =BB18/BB22-1 -> 0.19181838 | BO18: =BC18/BC22-1 -> 1.7223043 | BP18: =BD18/BD22-1 -> 3.3125316 | BQ18: =BE18/BE22-1 -> 1.8497779 | ... BU18: =BI18/BI22-1 -> 6.2140541 | BV18: {=_xll.ciqfunctions.udf.CIQ(B$3,$BV$1,$BV$2,$A18,"L",,"USD","H")/100} -> 0.2923 | BW18: {=_xll.ciqfunctions.udf.CIQ(C$3,$BV$1,$BV$2,$A18,"L",,"USD","H")/100} -> 0.030388 | BX18: {=_xll.ciqfunctions.udf.CIQ(D$3,$BV$1,$BV$2,$A18,"L",,"USD","H")/100} -> 0.080012 | BY18: {=_xll.ciqfunctions.udf.CIQ(E$3,$BV$1,$BV$2,$A18,"L",,"USD","H")/100} -> -0.092156 | BZ18: {=_xll.ciqfunctions.udf.CIQ(F$3,$BV$1,$BV$2,$A18,"L",,"USD","H")/100} -> -0.557524 | CA18: {=_xll.ciqfunctions.udf.CIQ(G$3,$BV$1,$BV$2,$A18,"L",,"USD","H")/100} -> 0.079656 | CB18: {=_xll.ciqfunctions.udf.CIQ(B$3,$BV$1,$CB$2,$A18,"L",,"USD","H")/100} -> 0.155872 | CC18: {=_xll.ciqfunctions.udf.CIQ(C$3,$BV$1,$CB$2,$A18,"L",,"USD","H")/100} -> 0.047957 | CD18: {=_xll.ciqfunctions.udf.CIQ(D$3,$BV$1,$CB$2,$A18,"L",,"USD","H")/100} -> 0.05665 | CE18: {=_xll.ciqfunctions.udf.CIQ(E$3,$BV$1,$CB$2,$A18,"L",,"USD","H")/100} -> 0.099649 | CF18: {=_xll.ciqfunctions.udf.CIQ(F$3,$BV$1,$CB$2,$A18,"L",,"USD","H")/100} -> -0.139112 | CG18: {=_xll.ciqfunctions.udf.CIQ(G$3,$BV$1,$CB$2,$A18,"L",,"USD","H")/100} -> 0.112335
A19: =EDATE(A15,-12) -> 44561 | B19: {=_xll.ciqfunctions.udf.CIQ(B$3,$B$1,$B$2,$A19,"L",,"USD","H")} -> 15452 | C19: {=_xll.ciqfunctions.udf.CIQ(C$3,$B$1,$B$2,$A19,"L",,"USD","H")} -> 82885 | D19: {=_xll.ciqfunctions.udf.CIQ(D$3,$B$1,$B$2,$A19,"L",,"USD","H")} -> 45322 | E19: {=_xll.ciqfunctions.udf.CIQ(E$3,$B$1,$B$2,$A19,"L",,"USD","H")} -> 5937 | F19: {=_xll.ciqfunctions.udf.CIQ(F$3,$B$1,$B$2,$A19,"L",,"USD","H")} -> 50503 | G19: {=_xll.ciqfunctions.udf.CIQ(G$3,$B$1,$B$2,$A19,"L",,"USD","H")} -> 4054 | H19: {=_xll.ciqfunctions.udf.CIQ(B$3,$B$1,$H$2,$A19,"L",,"USD","H")} -> 46660 | I19: {=_xll.ciqfunctions.udf.CIQ(C$3,$B$1,$H$2,$A19,"L",,"USD","H")} -> 277140 | J19: {=_xll.ciqfunctions.udf.CIQ(D$3,$B$1,$H$2,$A19,"L",,"USD","H")} -> 155067 | K19: {=_xll.ciqfunctions.udf.CIQ(E$3,$B$1,$H$2,$A19,"L",,"USD","H")} -> 19777 | L19: {=_xll.ciqfunctions.udf.CIQ(F$3,$B$1,$H$2,$A19,"L",,"USD","H")} -> 156431 | M19: {=_xll.ciqfunctions.udf.CIQ(G$3,$B$1,$H$2,$A19,"L",,"USD","H")} -> 13750 | N19: {=_xll.ciqfunctions.udf.CIQ(B$3,$N$1,$B$2,$A19,"L",,"USD","H")} -> 177.0665 | O19: {=_xll.ciqfunctions.udf.CIQ(C$3,$N$1,$B$2,$A19,"L",,"USD","H")} -> 79.3931 | P19: {=_xll.ciqfunctions.udf.CIQ(D$3,$N$1,$B$2,$A19,"L",,"USD","H")} -> 85.3584 | Q19: {=_xll.ciqfunctions.udf.CIQ(E$3,$N$1,$B$2,$A19,"L",,"USD","H")} -> 104.6535 | R19: {=_xll.ciqfunctions.udf.CIQ(F$3,$N$1,$B$2,$A19,"L",,"USD","H")} -> 83.0349 | S19: {=_xll.ciqfunctions.udf.CIQ(G$3,$N$1,$B$2,$A19,"L",,"USD","H")} -> 200.2962 | T19: 45947 | U19: {=_xll.ciqfunctions.udf.CIQ(O$3,$N$1,$T$2,$A19,"L",,"USD","H")} -> 54.1516 | V19: {=_xll.ciqfunctions.udf.CIQ(P$3,$N$1,$T$2,$A19,"L",,"USD","H")} -> 64.9561 | W19: {=_xll.ciqfunctions.udf.CIQ(Q$3,$N$1,$T$2,$A19,"L",,"USD","H")} -> 99.0839 | X19: {=_xll.ciqfunctions.udf.CIQ(R$3,$N$1,$T$2,$A19,"L",,"USD","H")} -> 48.0344 | Y19: {=_xll.ciqfunctions.udf.CIQ(S$3,$N$1,$T$2,$A19,"L",,"USD","H")} -> 194.2435 | Z19: {=_xll.ciqfunctions.udf.CIQ(B$3,$Z$1,$B$2,$A19,"L",,"USD","H")} -> 2627 | AA19: {=_xll.ciqfunctions.udf.CIQ(C$3,$Z$1,$B$2,$A19,"L",,"USD","H")} -> 8870 | AB19: {=_xll.ciqfunctions.udf.CIQ(D$3,$Z$1,$B$2,$A19,"L",,"USD","H")} -> 5055 | AC19: {=_xll.ciqfunctions.udf.CIQ(E$3,$Z$1,$B$2,$A19,"L",,"USD","H")} -> 1985 | AD19: {=_xll.ciqfunctions.udf.CIQ(F$3,$Z$1,$B$2,$A19,"L",,"USD","H")} -> 2326 | AE19: {=_xll.ciqfunctions.udf.CIQ(G$3,$Z$1,$B$2,$A19,"L",,"USD","H")} -> 1506 | AF19: {=_xll.ciqfunctions.udf.CIQ(B$3,$Z$1,$H$2,$A19,"L",,"USD","H")} -> 8079 | AG19: {=_xll.ciqfunctions.udf.CIQ(C$3,$Z$1,$H$2,$A19,"L",,"USD","H")} -> 23040 | AH19: {=_xll.ciqfunctions.udf.CIQ(D$3,$Z$1,$H$2,$A19,"L",,"USD","H")} -> 15625 | AI19: {=_xll.ciqfunctions.udf.CIQ(E$3,$Z$1,$H$2,$A19,"L",,"USD","H")} -> 4664 | AJ19: {=_xll.ciqfunctions.udf.CIQ(F$3,$Z$1,$H$2,$A19,"L",,"USD","H")} -> 7565 | AK19: {=_xll.ciqfunctions.udf.CIQ(G$3,$Z$1,$H$2,$A19,"L",,"USD","H")} -> 2813 | AL19: {=_xll.ciqfunctions.udf.CIQ(B$3,$AL$1,$AL$2,$A19,"L",,"USD","H")} -> NM | AM19: {=_xll.ciqfunctions.udf.CIQ(C$3,$AL$1,$AL$2,$A19,"L",,"USD","H")} -> NM | AN19: {=_xll.ciqfunctions.udf.CIQ(D$3,$AL$1,$AL$2,$A19,"L",,"USD","H")} -> NM | AO19: {=_xll.ciqfunctions.udf.CIQ(E$3,$AL$1,$AL$2,$A19,"L",,"USD","H")} -> 489.0207 | AP19: {=_xll.ciqfunctions.udf.CIQ(F$3,$AL$1,$AL$2,$A19,"L",,"USD","H")} -> 71.2812 | AQ19: {=_xll.ciqfunctions.udf.CIQ(G$3,$AL$1,$AL$2,$A19,"L",,"USD","H")} -> NM | AR19: {=_xll.ciqfunctions.udf.CIQ(B$3,$AL$1,$AR$2,$A19,"L",,"USD","H")} -> NM | AS19: {=_xll.ciqfunctions.udf.CIQ(C$3,$AL$1,$AR$2,$A19,"L",,"USD","H")} -> NM | AT19: {=_xll.ciqfunctions.udf.CIQ(D$3,$AL$1,$AR$2,$A19,"L",,"USD","H")} -> NM | AU19: {=_xll.ciqfunctions.udf.CIQ(E$3,$AL$1,$AR$2,$A19,"L",,"USD","H")} -> NM | AV19: {=_xll.ciqfunctions.udf.CIQ(F$3,$AL$1,$AR$2,$A19,"L",,"USD","H")} -> NM | AW19: {=_xll.ciqfunctions.udf.CIQ(G$3,$AL$1,$AR$2,$A19,"L",,"USD","H")} -> NM | AX19: {=_xll.ciqfunctions.udf.CIQ(B$3,$AX$1,$AX$2,$A19,"L",,"USD","H")} -> 6840 | AY19: {=_xll.ciqfunctions.udf.CIQ(C$3,$AX$1,$AX$2,$A19,"L",,"USD","H")} -> 15589 | AZ19: {=_xll.ciqfunctions.udf.CIQ(D$3,$AX$1,$AX$2,$A19,"L",,"USD","H")} -> 9943 | BA19: {=_xll.ciqfunctions.udf.CIQ(E$3,$AX$1,$AX$2,$A19,"L",,"USD","H")} -> 3660 | BB19: {=_xll.ciqfunctions.udf.CIQ(F$3,$AX$1,$AX$2,$A19,"L",,"USD","H")} -> 10736 | BC19: {=_xll.ciqfunctions.udf.CIQ(G$3,$AX$1,$AX$2,$A19,"L",,"USD","H")} -> 2312 | BD19: {=_xll.ciqfunctions.udf.CIQ(B$3,$AX$1,$BD$2,$A19,"L",,"USD","H")} -> 20274 | BE19: {=_xll.ciqfunctions.udf.CIQ(C$3,$AX$1,$BD$2,$A19,"L",,"USD","H")} -> 44288 | BF19: {=_xll.ciqfunctions.udf.CIQ(D$3,$AX$1,$BD$2,$A19,"L",,"USD","H")} -> 33632 | BG19: =_xll.ciqfunctions.udf.CIQ("COP", "IQ_PRICEDATE", "9/26/2025") -> 45926 | BH19: {=_xll.ciqfunctions.udf.CIQ(F$3,$AX$1,$BD$2,$A19,"L",,"USD","H")} -> 25158 | BI19: {=_xll.ciqfunctions.udf.CIQ(G$3,$AX$1,$BD$2,$A19,"L",,"USD","H")} -> 5503 | BJ19: =AX19/AX23-1 -> 4.1428571 | BK19: =AY19/AY23-1 -> 2.82177 | BL19: =AZ19/AZ23-1 -> 1.4882382 | BM19: =BA19/BA23-1 -> 1.4286662 | BN19: =BB19/BB23-1 -> 13.144928 | BO19: =BC19/BC23-1 -> -0.26016 | BP19: =BD19/BD23-1 -> 3.22375 | BQ19: =BE19/BE23-1 -> 1.6027268 | ... BU19: =BI19/BI23-1 -> 2.9504666 | BV19: {=_xll.ciqfunctions.udf.CIQ(B$3,$BV$1,$BV$2,$A19,"L",,"USD","H")/100} -> 0.124384 | BW19: {=_xll.ciqfunctions.udf.CIQ(C$3,$BV$1,$BV$2,$A19,"L",,"USD","H")/100} -> 0.090224 | BX19: {=_xll.ciqfunctions.udf.CIQ(D$3,$BV$1,$BV$2,$A19,"L",,"USD","H")/100} -> 0.057048 | BY19: {=_xll.ciqfunctions.udf.CIQ(E$3,$BV$1,$BV$2,$A19,"L",,"USD","H")/100} -> 0.28758 | BZ19: {=_xll.ciqfunctions.udf.CIQ(F$3,$BV$1,$BV$2,$A19,"L",,"USD","H")/100} -> 0.057908 | CA19: {=_xll.ciqfunctions.udf.CIQ(G$3,$BV$1,$BV$2,$A19,"L",,"USD","H")/100} -> 0.238028 | CB19: {=_xll.ciqfunctions.udf.CIQ(B$3,$BV$1,$CB$2,$A19,"L",,"USD","H")/100} -> 0.102133 | CC19: {=_xll.ciqfunctions.udf.CIQ(C$3,$BV$1,$CB$2,$A19,"L",,"USD","H")/100} -> 0.034848 | CD19: {=_xll.ciqfunctions.udf.CIQ(D$3,$BV$1,$CB$2,$A19,"L",,"USD","H")/100} -> 0.030616 | CE19: {=_xll.ciqfunctions.udf.CIQ(E$3,$BV$1,$CB$2,$A19,"L",,"USD","H")/100} -> 0.135398 | CF19: {=_xll.ciqfunctions.udf.CIQ(F$3,$BV$1,$CB$2,$A19,"L",,"USD","H")/100} -> 0.019901 | CG19: {=_xll.ciqfunctions.udf.CIQ(G$3,$BV$1,$CB$2,$A19,"L",,"USD","H")/100} -> 0.126248
A20: =EDATE(A16,-12) -> 44469 | B20: {=_xll.ciqfunctions.udf.CIQ(B$3,$B$1,$B$2,$A20,"L",,"USD","H")} -> 11565 | C20: {=_xll.ciqfunctions.udf.CIQ(C$3,$B$1,$B$2,$A20,"L",,"USD","H")} -> 72116 | D20: {=_xll.ciqfunctions.udf.CIQ(D$3,$B$1,$B$2,$A20,"L",,"USD","H")} -> 42552 | E20: {=_xll.ciqfunctions.udf.CIQ(E$3,$B$1,$B$2,$A20,"L",,"USD","H")} -> 5258 | F20: {=_xll.ciqfunctions.udf.CIQ(F$3,$B$1,$B$2,$A20,"L",,"USD","H")} -> 35820 | G20: {=_xll.ciqfunctions.udf.CIQ(G$3,$B$1,$B$2,$A20,"L",,"USD","H")} -> 3801 | H20: {=_xll.ciqfunctions.udf.CIQ(B$3,$B$1,$H$2,$A20,"L",,"USD","H")} -> 36785 | I20: {=_xll.ciqfunctions.udf.CIQ(C$3,$B$1,$H$2,$A20,"L",,"USD","H")} -> 242299 | J20: {=_xll.ciqfunctions.udf.CIQ(D$3,$B$1,$H$2,$A20,"L",,"USD","H")} -> 134196 | K20: {=_xll.ciqfunctions.udf.CIQ(E$3,$B$1,$H$2,$A20,"L",,"USD","H")} -> 16741 | L20: {=_xll.ciqfunctions.udf.CIQ(F$3,$B$1,$H$2,$A20,"L",,"USD","H")} -> 133875 | M20: {=_xll.ciqfunctions.udf.CIQ(G$3,$B$1,$H$2,$A20,"L",,"USD","H")} -> 10413 | N20: {=_xll.ciqfunctions.udf.CIQ(B$3,$N$1,$B$2,$A20,"L",,"USD","H")} -> 161.5923 | O20: {=_xll.ciqfunctions.udf.CIQ(C$3,$N$1,$B$2,$A20,"L",,"USD","H")} -> 57.8168 | P20: {=_xll.ciqfunctions.udf.CIQ(D$3,$N$1,$B$2,$A20,"L",,"USD","H")} -> 77.3221 | Q20: {=_xll.ciqfunctions.udf.CIQ(E$3,$N$1,$B$2,$A20,"L",,"USD","H")} -> 126.5402 | R20: {=_xll.ciqfunctions.udf.CIQ(F$3,$N$1,$B$2,$A20,"L",,"USD","H")} -> 36.8638 | S20: {=_xll.ciqfunctions.udf.CIQ(G$3,$N$1,$B$2,$A20,"L",,"USD","H")} -> 229.376 | T20: 45940 | U20: {=_xll.ciqfunctions.udf.CIQ(O$3,$N$1,$T$2,$A20,"L",,"USD","H")} -> 23.6995 | V20: {=_xll.ciqfunctions.udf.CIQ(P$3,$N$1,$T$2,$A20,"L",,"USD","H")} -> 39.1915 | W20: {=_xll.ciqfunctions.udf.CIQ(Q$3,$N$1,$T$2,$A20,"L",,"USD","H")} -> 48.2077 | X20: {=_xll.ciqfunctions.udf.CIQ(R$3,$N$1,$T$2,$A20,"L",,"USD","H")} -> -10.227 | Y20: {=_xll.ciqfunctions.udf.CIQ(S$3,$N$1,$T$2,$A20,"L",,"USD","H")} -> 117.4357 | Z20: {=_xll.ciqfunctions.udf.CIQ(B$3,$Z$1,$B$2,$A20,"L",,"USD","H")} -> 2379 | AA20: {=_xll.ciqfunctions.udf.CIQ(C$3,$Z$1,$B$2,$A20,"L",,"USD","H")} -> 6750 | AB20: {=_xll.ciqfunctions.udf.CIQ(D$3,$Z$1,$B$2,$A20,"L",,"USD","H")} -> 6111 | AC20: {=_xll.ciqfunctions.udf.CIQ(E$3,$Z$1,$B$2,$A20,"L",,"USD","H")} -> 1095 | AD20: {=_xll.ciqfunctions.udf.CIQ(F$3,$Z$1,$B$2,$A20,"L",,"USD","H")} -> -2544 | AE20: {=_xll.ciqfunctions.udf.CIQ(G$3,$Z$1,$B$2,$A20,"L",,"USD","H")} -> 838 | AF20: {=_xll.ciqfunctions.udf.CIQ(B$3,$Z$1,$H$2,$A20,"L",,"USD","H")} -> 4680 | AG20: {=_xll.ciqfunctions.udf.CIQ(C$3,$Z$1,$H$2,$A20,"L",,"USD","H")} -> -5900 | AH20: {=_xll.ciqfunctions.udf.CIQ(D$3,$Z$1,$H$2,$A20,"L",,"USD","H")} -> 9905 | AI20: {=_xll.ciqfunctions.udf.CIQ(E$3,$Z$1,$H$2,$A20,"L",,"USD","H")} -> 3016 | AJ20: {=_xll.ciqfunctions.udf.CIQ(F$3,$Z$1,$H$2,$A20,"L",,"USD","H")} -> 6597 | AK20: {=_xll.ciqfunctions.udf.CIQ(G$3,$Z$1,$H$2,$A20,"L",,"USD","H")} -> 1205 | AL20: {=_xll.ciqfunctions.udf.CIQ(B$3,$AL$1,$AL$2,$A20,"L",,"USD","H")} -> NM | AM20: {=_xll.ciqfunctions.udf.CIQ(C$3,$AL$1,$AL$2,$A20,"L",,"USD","H")} -> NM | AN20: {=_xll.ciqfunctions.udf.CIQ(D$3,$AL$1,$AL$2,$A20,"L",,"USD","H")} -> NM | AO20: {=_xll.ciqfunctions.udf.CIQ(E$3,$AL$1,$AL$2,$A20,"L",,"USD","H")} -> NM | AP20: {=_xll.ciqfunctions.udf.CIQ(F$3,$AL$1,$AL$2,$A20,"L",,"USD","H")} -> NM | AQ20: {=_xll.ciqfunctions.udf.CIQ(G$3,$AL$1,$AL$2,$A20,"L",,"USD","H")} -> NM | AR20: {=_xll.ciqfunctions.udf.CIQ(B$3,$AL$1,$AR$2,$A20,"L",,"USD","H")} -> NM | AS20: {=_xll.ciqfunctions.udf.CIQ(C$3,$AL$1,$AR$2,$A20,"L",,"USD","H")} -> NM | AT20: {=_xll.ciqfunctions.udf.CIQ(D$3,$AL$1,$AR$2,$A20,"L",,"USD","H")} -> NM | AU20: {=_xll.ciqfunctions.udf.CIQ(E$3,$AL$1,$AR$2,$A20,"L",,"USD","H")} -> NM | AV20: {=_xll.ciqfunctions.udf.CIQ(F$3,$AL$1,$AR$2,$A20,"L",,"USD","H")} -> NM | AW20: {=_xll.ciqfunctions.udf.CIQ(G$3,$AL$1,$AR$2,$A20,"L",,"USD","H")} -> NM | AX20: {=_xll.ciqfunctions.udf.CIQ(B$3,$AX$1,$AX$2,$A20,"L",,"USD","H")} -> 5331 | AY20: {=_xll.ciqfunctions.udf.CIQ(C$3,$AX$1,$AX$2,$A20,"L",,"USD","H")} -> 13140 | AZ20: {=_xll.ciqfunctions.udf.CIQ(D$3,$AX$1,$AX$2,$A20,"L",,"USD","H")} -> 10367 | BA20: {=_xll.ciqfunctions.udf.CIQ(E$3,$AX$1,$AX$2,$A20,"L",,"USD","H")} -> 2479 | BB20: {=_xll.ciqfunctions.udf.CIQ(F$3,$AX$1,$AX$2,$A20,"L",,"USD","H")} -> 2701 | BC20: {=_xll.ciqfunctions.udf.CIQ(G$3,$AX$1,$AX$2,$A20,"L",,"USD","H")} -> 1654 | BD20: {=_xll.ciqfunctions.udf.CIQ(B$3,$AX$1,$BD$2,$A20,"L",,"USD","H")} -> 14586 | BE20: {=_xll.ciqfunctions.udf.CIQ(C$3,$AX$1,$BD$2,$A20,"L",,"USD","H")} -> 34677 | BF20: {=_xll.ciqfunctions.udf.CIQ(D$3,$AX$1,$BD$2,$A20,"L",,"USD","H")} -> 27685 | BG20: =_xll.ciqfunctions.udf.CIQ("COP", "IQ_PRICEDATE", "9/19/2025") -> 45919 | BH20: {=_xll.ciqfunctions.udf.CIQ(F$3,$AX$1,$BD$2,$A20,"L",,"USD","H")} -> 17989 | BI20: {=_xll.ciqfunctions.udf.CIQ(G$3,$AX$1,$BD$2,$A20,"L",,"USD","H")} -> 3507 | BJ20: =AX20/AX24-1 -> 3.6927817 | BK20: =AY20/AY24-1 -> 2.9212175 | BL20: =AZ20/AZ24-1 -> 1.8102467 | BM20: =BA20/BA24-1 -> 1.5556701 | BN20: =BB20/BB24-1 -> -0.43846154 | BO20: =BC20/BC24-1 -> 5.8916667 | BP20: =BD20/BD24-1 -> 1.2275504 | BQ20: =BE20/BE24-1 -> 0.81099854 | ... BU20: =BI20/BI24-1 -> 1.2996721 | BV20: {=_xll.ciqfunctions.udf.CIQ(B$3,$BV$1,$BV$2,$A20,"L",,"USD","H")/100} -> 0.112436 | BW20: {=_xll.ciqfunctions.udf.CIQ(C$3,$BV$1,$BV$2,$A20,"L",,"USD","H")/100} -> 0.053832 | BX20: {=_xll.ciqfunctions.udf.CIQ(D$3,$BV$1,$BV$2,$A20,"L",,"USD","H")/100} -> 0.080684 | BY20: {=_xll.ciqfunctions.udf.CIQ(E$3,$BV$1,$BV$2,$A20,"L",,"USD","H")/100} -> 0.041204 | BZ20: {=_xll.ciqfunctions.udf.CIQ(F$3,$BV$1,$BV$2,$A20,"L",,"USD","H")/100} -> -0.087976 | CA20: {=_xll.ciqfunctions.udf.CIQ(G$3,$BV$1,$BV$2,$A20,"L",,"USD","H")/100} -> 0.130664 | CB20: {=_xll.ciqfunctions.udf.CIQ(B$3,$BV$1,$CB$2,$A20,"L",,"USD","H")/100} -> 0.044855 | CC20: {=_xll.ciqfunctions.udf.CIQ(C$3,$BV$1,$CB$2,$A20,"L",,"USD","H")/100} -> -0.087015 | CD20: {=_xll.ciqfunctions.udf.CIQ(D$3,$BV$1,$CB$2,$A20,"L",,"USD","H")/100} -> -0.001009 | CE20: {=_xll.ciqfunctions.udf.CIQ(E$3,$BV$1,$CB$2,$A20,"L",,"USD","H")/100} -> 0.057007 | CF20: {=_xll.ciqfunctions.udf.CIQ(F$3,$BV$1,$CB$2,$A20,"L",,"USD","H")/100} -> 0.014206 | CG20: {=_xll.ciqfunctions.udf.CIQ(G$3,$BV$1,$CB$2,$A20,"L",,"USD","H")/100} -> 0.034246
A21: =EDATE(A17,-12) -> 44377 | B21: {=_xll.ciqfunctions.udf.CIQ(B$3,$B$1,$B$2,$A21,"L",,"USD","H")} -> 9695 | C21: {=_xll.ciqfunctions.udf.CIQ(C$3,$B$1,$B$2,$A21,"L",,"USD","H")} -> 66306 | D21: {=_xll.ciqfunctions.udf.CIQ(D$3,$B$1,$B$2,$A21,"L",,"USD","H")} -> 36117 | E21: {=_xll.ciqfunctions.udf.CIQ(E$3,$B$1,$B$2,$A21,"L",,"USD","H")} -> 4515 | F21: {=_xll.ciqfunctions.udf.CIQ(F$3,$B$1,$B$2,$A21,"L",,"USD","H")} -> 36172 | G21: {=_xll.ciqfunctions.udf.CIQ(G$3,$B$1,$B$2,$A21,"L",,"USD","H")} -> 2944 | H21: {=_xll.ciqfunctions.udf.CIQ(B$3,$B$1,$H$2,$A21,"L",,"USD","H")} -> 29641 | I21: {=_xll.ciqfunctions.udf.CIQ(C$3,$B$1,$H$2,$A21,"L",,"USD","H")} -> 215879 | J21: {=_xll.ciqfunctions.udf.CIQ(D$3,$B$1,$H$2,$A21,"L",,"USD","H")} -> 115641 | K21: {=_xll.ciqfunctions.udf.CIQ(E$3,$B$1,$H$2,$A21,"L",,"USD","H")} -> 13804 | L21: {=_xll.ciqfunctions.udf.CIQ(F$3,$B$1,$H$2,$A21,"L",,"USD","H")} -> 124227 | M21: {=_xll.ciqfunctions.udf.CIQ(G$3,$B$1,$H$2,$A21,"L",,"USD","H")} -> 7766 | N21: {=_xll.ciqfunctions.udf.CIQ(B$3,$N$1,$B$2,$A21,"L",,"USD","H")} -> 243.0644 | O21: {=_xll.ciqfunctions.udf.CIQ(C$3,$N$1,$B$2,$A21,"L",,"USD","H")} -> 104.0059 | P21: {=_xll.ciqfunctions.udf.CIQ(D$3,$N$1,$B$2,$A21,"L",,"USD","H")} -> 126.7801 | Q21: {=_xll.ciqfunctions.udf.CIQ(E$3,$N$1,$B$2,$A21,"L",,"USD","H")} -> 271.2993 | R21: {=_xll.ciqfunctions.udf.CIQ(F$3,$N$1,$B$2,$A21,"L",,"USD","H")} -> 71.123 | S21: {=_xll.ciqfunctions.udf.CIQ(G$3,$N$1,$B$2,$A21,"L",,"USD","H")} -> 312.9032 | T21: 45933 | U21: {=_xll.ciqfunctions.udf.CIQ(O$3,$N$1,$T$2,$A21,"L",,"USD","H")} -> 0.862 | V21: {=_xll.ciqfunctions.udf.CIQ(P$3,$N$1,$T$2,$A21,"L",,"USD","H")} -> 7.8811 | W21: {=_xll.ciqfunctions.udf.CIQ(Q$3,$N$1,$T$2,$A21,"L",,"USD","H")} -> 4.6335 | X21: {=_xll.ciqfunctions.udf.CIQ(R$3,$N$1,$T$2,$A21,"L",,"USD","H")} -> -34.9274 | Y21: {=_xll.ciqfunctions.udf.CIQ(S$3,$N$1,$T$2,$A21,"L",,"USD","H")} -> 49.4611 | Z21: {=_xll.ciqfunctions.udf.CIQ(B$3,$Z$1,$B$2,$A21,"L",,"USD","H")} -> 2091 | AA21: {=_xll.ciqfunctions.udf.CIQ(C$3,$Z$1,$B$2,$A21,"L",,"USD","H")} -> 4690 | AB21: {=_xll.ciqfunctions.udf.CIQ(D$3,$Z$1,$B$2,$A21,"L",,"USD","H")} -> 3082 | AC21: {=_xll.ciqfunctions.udf.CIQ(E$3,$Z$1,$B$2,$A21,"L",,"USD","H")} -> 907 | AD21: {=_xll.ciqfunctions.udf.CIQ(F$3,$Z$1,$B$2,$A21,"L",,"USD","H")} -> 3116 | AE21: {=_xll.ciqfunctions.udf.CIQ(G$3,$Z$1,$B$2,$A21,"L",,"USD","H")} -> 256 | AF21: {=_xll.ciqfunctions.udf.CIQ(B$3,$Z$1,$H$2,$A21,"L",,"USD","H")} -> 1851 | AG21: {=_xll.ciqfunctions.udf.CIQ(C$3,$Z$1,$H$2,$A21,"L",,"USD","H")} -> -13330 | AH21: {=_xll.ciqfunctions.udf.CIQ(D$3,$Z$1,$H$2,$A21,"L",,"USD","H")} -> 3587 | AI21: {=_xll.ciqfunctions.udf.CIQ(E$3,$Z$1,$H$2,$A21,"L",,"USD","H")} -> 1879 | AJ21: {=_xll.ciqfunctions.udf.CIQ(F$3,$Z$1,$H$2,$A21,"L",,"USD","H")} -> 8691 | AK21: {=_xll.ciqfunctions.udf.CIQ(G$3,$Z$1,$H$2,$A21,"L",,"USD","H")} -> 275 | AL21: {=_xll.ciqfunctions.udf.CIQ(B$3,$AL$1,$AL$2,$A21,"L",,"USD","H")} -> 704.2307 | AM21: {=_xll.ciqfunctions.udf.CIQ(C$3,$AL$1,$AL$2,$A21,"L",,"USD","H")} -> NM | AN21: {=_xll.ciqfunctions.udf.CIQ(D$3,$AL$1,$AL$2,$A21,"L",,"USD","H")} -> NM | AO21: {=_xll.ciqfunctions.udf.CIQ(E$3,$AL$1,$AL$2,$A21,"L",,"USD","H")} -> NM | AP21: {=_xll.ciqfunctions.udf.CIQ(F$3,$AL$1,$AL$2,$A21,"L",,"USD","H")} -> NM | AQ21: {=_xll.ciqfunctions.udf.CIQ(G$3,$AL$1,$AL$2,$A21,"L",,"USD","H")} -> NM | AR21: {=_xll.ciqfunctions.udf.CIQ(B$3,$AL$1,$AR$2,$A21,"L",,"USD","H")} -> -19.4167 | AS21: {=_xll.ciqfunctions.udf.CIQ(C$3,$AL$1,$AR$2,$A21,"L",,"USD","H")} -> NM | AT21: {=_xll.ciqfunctions.udf.CIQ(D$3,$AL$1,$AR$2,$A21,"L",,"USD","H")} -> NM | AU21: {=_xll.ciqfunctions.udf.CIQ(E$3,$AL$1,$AR$2,$A21,"L",,"USD","H")} -> 434.3487 | AV21: {=_xll.ciqfunctions.udf.CIQ(F$3,$AL$1,$AR$2,$A21,"L",,"USD","H")} -> NM | AW21: {=_xll.ciqfunctions.udf.CIQ(G$3,$AL$1,$AR$2,$A21,"L",,"USD","H")} -> NM | AX21: {=_xll.ciqfunctions.udf.CIQ(B$3,$AX$1,$AX$2,$A21,"L",,"USD","H")} -> 4661 | AY21: {=_xll.ciqfunctions.udf.CIQ(C$3,$AX$1,$AX$2,$A21,"L",,"USD","H")} -> 10077 | AZ21: {=_xll.ciqfunctions.udf.CIQ(D$3,$AX$1,$AX$2,$A21,"L",,"USD","H")} -> 7649 | BA21: {=_xll.ciqfunctions.udf.CIQ(E$3,$AX$1,$AX$2,$A21,"L",,"USD","H")} -> 2078 | BB21: {=_xll.ciqfunctions.udf.CIQ(F$3,$AX$1,$AX$2,$A21,"L",,"USD","H")} -> 5411 | BC21: {=_xll.ciqfunctions.udf.CIQ(G$3,$AX$1,$AX$2,$A21,"L",,"USD","H")} -> 864 | BD21: {=_xll.ciqfunctions.udf.CIQ(B$3,$AX$1,$BD$2,$A21,"L",,"USD","H")} -> 10391 | BE21: {=_xll.ciqfunctions.udf.CIQ(C$3,$AX$1,$BD$2,$A21,"L",,"USD","H")} -> 24888 | BF21: {=_xll.ciqfunctions.udf.CIQ(D$3,$AX$1,$BD$2,$A21,"L",,"USD","H")} -> 21042 | BG21: =_xll.ciqfunctions.udf.CIQ("COP", "IQ_PRICEDATE", "9/12/2025") -> 45912 | BH21: {=_xll.ciqfunctions.udf.CIQ(F$3,$AX$1,$BD$2,$A21,"L",,"USD","H")} -> 20098 | BI21: {=_xll.ciqfunctions.udf.CIQ(G$3,$AX$1,$BD$2,$A21,"L",,"USD","H")} -> 2093 | BJ21: =AX21/AX25-1 -> 22.422111 | BK21: =AY21/AY25-1 -> 1.4572056 | BL21: =AZ21/AZ25-1 -> -6.9804535 | BM21: =BA21/BA25-1 -> -24.348315 | BN21: =BB21/BB25-1 -> 0.084368737 | BO21: =BC21/BC25-1 -> -3.8421053 | BP21: =BD21/BD25-1 -> 0.19519209 | BQ21: =BE21/BE25-1 -> 0.018872559 | ... BU21: =BI21/BI25-1 -> 0.077200206 | BV21: {=_xll.ciqfunctions.udf.CIQ(B$3,$BV$1,$BV$2,$A21,"L",,"USD","H")/100} -> 0.09464 | BW21: {=_xll.ciqfunctions.udf.CIQ(C$3,$BV$1,$BV$2,$A21,"L",,"USD","H")/100} -> 0.017088 | BX21: {=_xll.ciqfunctions.udf.CIQ(D$3,$BV$1,$BV$2,$A21,"L",,"USD","H")/100} -> 0.01146 | BY21: {=_xll.ciqfunctions.udf.CIQ(E$3,$BV$1,$BV$2,$A21,"L",,"USD","H")/100} -> 0.101936 | BZ21: {=_xll.ciqfunctions.udf.CIQ(F$3,$BV$1,$BV$2,$A21,"L",,"USD","H")/100} -> 0.048892 | CA21: {=_xll.ciqfunctions.udf.CIQ(G$3,$BV$1,$BV$2,$A21,"L",,"USD","H")/100} -> 0.006884 | CB21: {=_xll.ciqfunctions.udf.CIQ(B$3,$BV$1,$CB$2,$A21,"L",,"USD","H")/100} -> -0.004296 | CC21: {=_xll.ciqfunctions.udf.CIQ(C$3,$BV$1,$CB$2,$A21,"L",,"USD","H")/100} -> -0.116818 | CD21: {=_xll.ciqfunctions.udf.CIQ(D$3,$BV$1,$CB$2,$A21,"L",,"USD","H")/100} -> -0.036534 | CE21: {=_xll.ciqfunctions.udf.CIQ(E$3,$BV$1,$CB$2,$A21,"L",,"USD","H")/100} -> 0.037397 | CF21: {=_xll.ciqfunctions.udf.CIQ(F$3,$BV$1,$CB$2,$A21,"L",,"USD","H")/100} -> 0.051355 | CG21: {=_xll.ciqfunctions.udf.CIQ(G$3,$BV$1,$CB$2,$A21,"L",,"USD","H")/100} -> -0.020748
A22: =EDATE(A18,-12) -> 44286 | B22: {=_xll.ciqfunctions.udf.CIQ(B$3,$B$1,$B$2,$A22,"L",,"USD","H")} -> 9948 | C22: {=_xll.ciqfunctions.udf.CIQ(C$3,$B$1,$B$2,$A22,"L",,"USD","H")} -> 57674 | D22: {=_xll.ciqfunctions.udf.CIQ(D$3,$B$1,$B$2,$A22,"L",,"USD","H")} -> 31076 | E22: {=_xll.ciqfunctions.udf.CIQ(E$3,$B$1,$B$2,$A22,"L",,"USD","H")} -> 4067 | F22: {=_xll.ciqfunctions.udf.CIQ(F$3,$B$1,$B$2,$A22,"L",,"USD","H")} -> 34291 | G22: {=_xll.ciqfunctions.udf.CIQ(G$3,$B$1,$B$2,$A22,"L",,"USD","H")} -> 2318 | H22: {=_xll.ciqfunctions.udf.CIQ(B$3,$B$1,$H$2,$A22,"L",,"USD","H")} -> 22772 | I22: {=_xll.ciqfunctions.udf.CIQ(C$3,$B$1,$H$2,$A22,"L",,"USD","H")} -> 182075 | J22: {=_xll.ciqfunctions.udf.CIQ(D$3,$B$1,$H$2,$A22,"L",,"USD","H")} -> 95450 | K22: {=_xll.ciqfunctions.udf.CIQ(E$3,$B$1,$H$2,$A22,"L",,"USD","H")} -> 10505 | L22: {=_xll.ciqfunctions.udf.CIQ(F$3,$B$1,$H$2,$A22,"L",,"USD","H")} -> 109193 | M22: {=_xll.ciqfunctions.udf.CIQ(G$3,$B$1,$H$2,$A22,"L",,"USD","H")} -> 5535 | N22: {=_xll.ciqfunctions.udf.CIQ(B$3,$N$1,$B$2,$A22,"L",,"USD","H")} -> 55.632 | O22: {=_xll.ciqfunctions.udf.CIQ(C$3,$N$1,$B$2,$A22,"L",,"USD","H")} -> 4.1366 | P22: {=_xll.ciqfunctions.udf.CIQ(D$3,$N$1,$B$2,$A22,"L",,"USD","H")} -> 4.6153 | Q22: {=_xll.ciqfunctions.udf.CIQ(E$3,$N$1,$B$2,$A22,"L",,"USD","H")} -> 16.3329 | R22: {=_xll.ciqfunctions.udf.CIQ(F$3,$N$1,$B$2,$A22,"L",,"USD","H")} -> 11.4429 | S22: {=_xll.ciqfunctions.udf.CIQ(G$3,$N$1,$B$2,$A22,"L",,"USD","H")} -> 80.2488 | T22: 45926 | U22: {=_xll.ciqfunctions.udf.CIQ(O$3,$N$1,$T$2,$A22,"L",,"USD","H")} -> -26.955 | V22: {=_xll.ciqfunctions.udf.CIQ(P$3,$N$1,$T$2,$A22,"L",,"USD","H")} -> -25.1901 | W22: {=_xll.ciqfunctions.udf.CIQ(Q$3,$N$1,$T$2,$A22,"L",,"USD","H")} -> -36.291 | X22: {=_xll.ciqfunctions.udf.CIQ(R$3,$N$1,$T$2,$A22,"L",,"USD","H")} -> -54.8924 | Y22: {=_xll.ciqfunctions.udf.CIQ(S$3,$N$1,$T$2,$A22,"L",,"USD","H")} -> -9.0387 | Z22: {=_xll.ciqfunctions.udf.CIQ(B$3,$Z$1,$B$2,$A22,"L",,"USD","H")} -> 982 | AA22: {=_xll.ciqfunctions.udf.CIQ(C$3,$Z$1,$B$2,$A22,"L",,"USD","H")} -> 2730 | AB22: {=_xll.ciqfunctions.udf.CIQ(D$3,$Z$1,$B$2,$A22,"L",,"USD","H")} -> 1377 | AC22: {=_xll.ciqfunctions.udf.CIQ(E$3,$Z$1,$B$2,$A22,"L",,"USD","H")} -> 677 | AD22: {=_xll.ciqfunctions.udf.CIQ(F$3,$Z$1,$B$2,$A22,"L",,"USD","H")} -> 4667 | AE22: {=_xll.ciqfunctions.udf.CIQ(G$3,$Z$1,$B$2,$A22,"L",,"USD","H")} -> 213 | AF22: {=_xll.ciqfunctions.udf.CIQ(B$3,$Z$1,$H$2,$A22,"L",,"USD","H")} -> 20 | AG22: {=_xll.ciqfunctions.udf.CIQ(C$3,$Z$1,$H$2,$A22,"L",,"USD","H")} -> -19100 | AH22: {=_xll.ciqfunctions.udf.CIQ(D$3,$Z$1,$H$2,$A22,"L",,"USD","H")} -> -7765 | AI22: {=_xll.ciqfunctions.udf.CIQ(E$3,$Z$1,$H$2,$A22,"L",,"USD","H")} -> 62 | AJ22: {=_xll.ciqfunctions.udf.CIQ(F$3,$Z$1,$H$2,$A22,"L",,"USD","H")} -> -11273 | AK22: {=_xll.ciqfunctions.udf.CIQ(G$3,$Z$1,$H$2,$A22,"L",,"USD","H")} -> -651 | AL22: {=_xll.ciqfunctions.udf.CIQ(B$3,$AL$1,$AL$2,$A22,"L",,"USD","H")} -> NM | AM22: {=_xll.ciqfunctions.udf.CIQ(C$3,$AL$1,$AL$2,$A22,"L",,"USD","H")} -> NM | AN22: {=_xll.ciqfunctions.udf.CIQ(D$3,$AL$1,$AL$2,$A22,"L",,"USD","H")} -> -61.7394 | AO22: {=_xll.ciqfunctions.udf.CIQ(E$3,$AL$1,$AL$2,$A22,"L",,"USD","H")} -> 6670 | AP22: {=_xll.ciqfunctions.udf.CIQ(F$3,$AL$1,$AL$2,$A22,"L",,"USD","H")} -> NM | AQ22: {=_xll.ciqfunctions.udf.CIQ(G$3,$AL$1,$AL$2,$A22,"L",,"USD","H")} -> NM | AR22: {=_xll.ciqfunctions.udf.CIQ(B$3,$AL$1,$AR$2,$A22,"L",,"USD","H")} -> -99.4471 | AS22: {=_xll.ciqfunctions.udf.CIQ(C$3,$AL$1,$AR$2,$A22,"L",,"USD","H")} -> NM | AT22: {=_xll.ciqfunctions.udf.CIQ(D$3,$AL$1,$AR$2,$A22,"L",,"USD","H")} -> NM | AU22: {=_xll.ciqfunctions.udf.CIQ(E$3,$AL$1,$AR$2,$A22,"L",,"USD","H")} -> -97.0609 | AV22: {=_xll.ciqfunctions.udf.CIQ(F$3,$AL$1,$AR$2,$A22,"L",,"USD","H")} -> NM | AW22: {=_xll.ciqfunctions.udf.CIQ(G$3,$AL$1,$AR$2,$A22,"L",,"USD","H")} -> NM | AX22: {=_xll.ciqfunctions.udf.CIQ(B$3,$AX$1,$AX$2,$A22,"L",,"USD","H")} -> 3264 | AY22: {=_xll.ciqfunctions.udf.CIQ(C$3,$AX$1,$AX$2,$A22,"L",,"USD","H")} -> 7381 | AZ22: {=_xll.ciqfunctions.udf.CIQ(D$3,$AX$1,$AX$2,$A22,"L",,"USD","H")} -> 5669 | BA22: {=_xll.ciqfunctions.udf.CIQ(E$3,$AX$1,$AX$2,$A22,"L",,"USD","H")} -> 1882 | BB22: {=_xll.ciqfunctions.udf.CIQ(F$3,$AX$1,$AX$2,$A22,"L",,"USD","H")} -> 9118 | BC22: {=_xll.ciqfunctions.udf.CIQ(G$3,$AX$1,$AX$2,$A22,"L",,"USD","H")} -> 677 | BD22: {=_xll.ciqfunctions.udf.CIQ(B$3,$AX$1,$BD$2,$A22,"L",,"USD","H")} -> 5929 | BE22: {=_xll.ciqfunctions.udf.CIQ(C$3,$AX$1,$BD$2,$A22,"L",,"USD","H")} -> 18912 | BF22: {=_xll.ciqfunctions.udf.CIQ(D$3,$AX$1,$BD$2,$A22,"L",,"USD","H")} -> 12075 | BG22: =_xll.ciqfunctions.udf.CIQ("COP", "IQ_PRICEDATE", "9/5/2025") -> 45905 | BH22: {=_xll.ciqfunctions.udf.CIQ(F$3,$AX$1,$BD$2,$A22,"L",,"USD","H")} -> 19677 | BI22: {=_xll.ciqfunctions.udf.CIQ(G$3,$AX$1,$BD$2,$A22,"L",,"USD","H")} -> 925 | BJ22: =AX22/AX26-1 -> 0.55725191 | BK22: =AY22/AY26-1 -> 0.46593843 | BL22: =AZ22/AZ26-1 -> -0.16620091 | BM22: =BA22/BA26-1 -> -0.28030593 | BN22: =BB22/BB26-1 -> 4.4435821 | BO22: =BC22/BC26-1 -> -0.40873362 | BP22: =BD22/BD26-1 -> -0.50890417 | BQ22: =BE22/BE26-1 -> -0.33516136 | ... BU22: =BI22/BI26-1 -> -0.68289338 | BV22: {=_xll.ciqfunctions.udf.CIQ(B$3,$BV$1,$BV$2,$A22,"L",,"USD","H")/100} -> 0.028868 | BW22: {=_xll.ciqfunctions.udf.CIQ(C$3,$BV$1,$BV$2,$A22,"L",,"USD","H")/100} -> -0.017048 | BX22: {=_xll.ciqfunctions.udf.CIQ(D$3,$BV$1,$BV$2,$A22,"L",,"USD","H")/100} -> -0.024288 | BY22: {=_xll.ciqfunctions.udf.CIQ(E$3,$BV$1,$BV$2,$A22,"L",,"USD","H")/100} -> 0.068848 | BZ22: {=_xll.ciqfunctions.udf.CIQ(F$3,$BV$1,$BV$2,$A22,"L",,"USD","H")/100} -> 0.086496 | CA22: {=_xll.ciqfunctions.udf.CIQ(G$3,$BV$1,$BV$2,$A22,"L",,"USD","H")/100} -> 0.003384 | CB22: {=_xll.ciqfunctions.udf.CIQ(B$3,$BV$1,$CB$2,$A22,"L",,"USD","H")/100} -> -0.035438 | CC22: {=_xll.ciqfunctions.udf.CIQ(C$3,$BV$1,$CB$2,$A22,"L",,"USD","H")/100} -> -0.14278 | CD22: {=_xll.ciqfunctions.udf.CIQ(D$3,$BV$1,$CB$2,$A22,"L",,"USD","H")/100} -> -0.098313 | CE22: {=_xll.ciqfunctions.udf.CIQ(E$3,$BV$1,$CB$2,$A22,"L",,"USD","H")/100} -> -0.0305 | CF22: {=_xll.ciqfunctions.udf.CIQ(F$3,$BV$1,$CB$2,$A22,"L",,"USD","H")/100} -> -0.099041 | CG22: {=_xll.ciqfunctions.udf.CIQ(G$3,$BV$1,$CB$2,$A22,"L",,"USD","H")/100} -> -0.079548
A23: =EDATE(A19,-12) -> 44196 | B23: {=_xll.ciqfunctions.udf.CIQ(B$3,$B$1,$B$2,$A23,"L",,"USD","H")} -> 5577 | C23: {=_xll.ciqfunctions.udf.CIQ(C$3,$B$1,$B$2,$A23,"L",,"USD","H")} -> 46203 | D23: {=_xll.ciqfunctions.udf.CIQ(D$3,$B$1,$B$2,$A23,"L",,"USD","H")} -> 24451 | E23: {=_xll.ciqfunctions.udf.CIQ(E$3,$B$1,$B$2,$A23,"L",,"USD","H")} -> 2901 | F23: {=_xll.ciqfunctions.udf.CIQ(F$3,$B$1,$B$2,$A23,"L",,"USD","H")} -> 27592 | G23: {=_xll.ciqfunctions.udf.CIQ(G$3,$B$1,$B$2,$A23,"L",,"USD","H")} -> 1350 | H23: {=_xll.ciqfunctions.udf.CIQ(B$3,$B$1,$H$2,$A23,"L",,"USD","H")} -> 19216 | I23: {=_xll.ciqfunctions.udf.CIQ(C$3,$B$1,$H$2,$A23,"L",,"USD","H")} -> 179784 | J23: {=_xll.ciqfunctions.udf.CIQ(D$3,$B$1,$H$2,$A23,"L",,"USD","H")} -> 94005 | K23: {=_xll.ciqfunctions.udf.CIQ(E$3,$B$1,$H$2,$A23,"L",,"USD","H")} -> 9934 | L23: {=_xll.ciqfunctions.udf.CIQ(F$3,$B$1,$H$2,$A23,"L",,"USD","H")} -> 105672 | M23: {=_xll.ciqfunctions.udf.CIQ(G$3,$B$1,$H$2,$A23,"L",,"USD","H")} -> 4673 | N23: {=_xll.ciqfunctions.udf.CIQ(B$3,$N$1,$B$2,$A23,"L",,"USD","H")} -> -28.8285 | O23: {=_xll.ciqfunctions.udf.CIQ(C$3,$N$1,$B$2,$A23,"L",,"USD","H")} -> -25.8332 | P23: {=_xll.ciqfunctions.udf.CIQ(D$3,$N$1,$B$2,$A23,"L",,"USD","H")} -> -8.7071 | Q23: {=_xll.ciqfunctions.udf.CIQ(E$3,$N$1,$B$2,$A23,"L",,"USD","H")} -> -31.9435 | R23: {=_xll.ciqfunctions.udf.CIQ(F$3,$N$1,$B$2,$A23,"L",,"USD","H")} -> -61.1632 | S23: {=_xll.ciqfunctions.udf.CIQ(G$3,$N$1,$B$2,$A23,"L",,"USD","H")} -> -17.4817 | T23: 45919 | U23: {=_xll.ciqfunctions.udf.CIQ(O$3,$N$1,$T$2,$A23,"L",,"USD","H")} -> -30.7183 | V23: {=_xll.ciqfunctions.udf.CIQ(P$3,$N$1,$T$2,$A23,"L",,"USD","H")} -> -32.5477 | W23: {=_xll.ciqfunctions.udf.CIQ(Q$3,$N$1,$T$2,$A23,"L",,"USD","H")} -> -41.8248 | X23: {=_xll.ciqfunctions.udf.CIQ(R$3,$N$1,$T$2,$A23,"L",,"USD","H")} -> -33.1651 | Y23: {=_xll.ciqfunctions.udf.CIQ(S$3,$N$1,$T$2,$A23,"L",,"USD","H")} -> -29.9821 | Z23: {=_xll.ciqfunctions.udf.CIQ(B$3,$Z$1,$B$2,$A23,"L",,"USD","H")} -> -772 | AA23: {=_xll.ciqfunctions.udf.CIQ(C$3,$Z$1,$B$2,$A23,"L",,"USD","H")} -> -20070 | AB23: {=_xll.ciqfunctions.udf.CIQ(D$3,$Z$1,$B$2,$A23,"L",,"USD","H")} -> -665 | AC23: {=_xll.ciqfunctions.udf.CIQ(E$3,$Z$1,$B$2,$A23,"L",,"USD","H")} -> 337 | AD23: {=_xll.ciqfunctions.udf.CIQ(F$3,$Z$1,$B$2,$A23,"L",,"USD","H")} -> 1358 | AE23: {=_xll.ciqfunctions.udf.CIQ(G$3,$Z$1,$B$2,$A23,"L",,"USD","H")} -> -102 | AF23: {=_xll.ciqfunctions.udf.CIQ(B$3,$Z$1,$H$2,$A23,"L",,"USD","H")} -> -2701 | AG23: {=_xll.ciqfunctions.udf.CIQ(C$3,$Z$1,$H$2,$A23,"L",,"USD","H")} -> -22440 | AH23: {=_xll.ciqfunctions.udf.CIQ(D$3,$Z$1,$H$2,$A23,"L",,"USD","H")} -> -5543 | AI23: {=_xll.ciqfunctions.udf.CIQ(E$3,$Z$1,$H$2,$A23,"L",,"USD","H")} -> -605 | AJ23: {=_xll.ciqfunctions.udf.CIQ(F$3,$Z$1,$H$2,$A23,"L",,"USD","H")} -> -20305 | AK23: {=_xll.ciqfunctions.udf.CIQ(G$3,$Z$1,$H$2,$A23,"L",,"USD","H")} -> -2680 | AL23: {=_xll.ciqfunctions.udf.CIQ(B$3,$AL$1,$AL$2,$A23,"L",,"USD","H")} -> NM | AM23: {=_xll.ciqfunctions.udf.CIQ(C$3,$AL$1,$AL$2,$A23,"L",,"USD","H")} -> NM | AN23: {=_xll.ciqfunctions.udf.CIQ(D$3,$AL$1,$AL$2,$A23,"L",,"USD","H")} -> NM | AO23: {=_xll.ciqfunctions.udf.CIQ(E$3,$AL$1,$AL$2,$A23,"L",,"USD","H")} -> -47.056 | AP23: {=_xll.ciqfunctions.udf.CIQ(F$3,$AL$1,$AL$2,$A23,"L",,"USD","H")} -> 7047.3684 | AQ23: {=_xll.ciqfunctions.udf.CIQ(G$3,$AL$1,$AL$2,$A23,"L",,"USD","H")} -> NM | AR23: {=_xll.ciqfunctions.udf.CIQ(B$3,$AL$1,$AR$2,$A23,"L",,"USD","H")} -> NM | AS23: {=_xll.ciqfunctions.udf.CIQ(C$3,$AL$1,$AR$2,$A23,"L",,"USD","H")} -> NM | AT23: {=_xll.ciqfunctions.udf.CIQ(D$3,$AL$1,$AR$2,$A23,"L",,"USD","H")} -> NM | AU23: {=_xll.ciqfunctions.udf.CIQ(E$3,$AL$1,$AR$2,$A23,"L",,"USD","H")} -> NM | AV23: {=_xll.ciqfunctions.udf.CIQ(F$3,$AL$1,$AR$2,$A23,"L",,"USD","H")} -> NM | AW23: {=_xll.ciqfunctions.udf.CIQ(G$3,$AL$1,$AR$2,$A23,"L",,"USD","H")} -> NM | AX23: {=_xll.ciqfunctions.udf.CIQ(B$3,$AX$1,$AX$2,$A23,"L",,"USD","H")} -> 1330 | AY23: {=_xll.ciqfunctions.udf.CIQ(C$3,$AX$1,$AX$2,$A23,"L",,"USD","H")} -> 4079 | AZ23: {=_xll.ciqfunctions.udf.CIQ(D$3,$AX$1,$AX$2,$A23,"L",,"USD","H")} -> 3996 | BA23: {=_xll.ciqfunctions.udf.CIQ(E$3,$AX$1,$AX$2,$A23,"L",,"USD","H")} -> 1507 | BB23: {=_xll.ciqfunctions.udf.CIQ(F$3,$AX$1,$AX$2,$A23,"L",,"USD","H")} -> 759 | BC23: {=_xll.ciqfunctions.udf.CIQ(G$3,$AX$1,$AX$2,$A23,"L",,"USD","H")} -> 3125 | BD23: {=_xll.ciqfunctions.udf.CIQ(B$3,$AX$1,$BD$2,$A23,"L",,"USD","H")} -> 4800 | BE23: {=_xll.ciqfunctions.udf.CIQ(C$3,$AX$1,$BD$2,$A23,"L",,"USD","H")} -> 17016 | BF23: {=_xll.ciqfunctions.udf.CIQ(D$3,$AX$1,$BD$2,$A23,"L",,"USD","H")} -> 13131 | BG23: =_xll.ciqfunctions.udf.CIQ("COP", "IQ_PRICEDATE", "8/29/2025") -> 45898 | BH23: {=_xll.ciqfunctions.udf.CIQ(F$3,$AX$1,$BD$2,$A23,"L",,"USD","H")} -> 14441 | BI23: {=_xll.ciqfunctions.udf.CIQ(G$3,$AX$1,$BD$2,$A23,"L",,"USD","H")} -> 1393 | BJ23: =AX23/AX27-1 -> -0.57330767 | BK23: =AY23/AY27-1 -> -0.38762949 | BL23: =AZ23/AZ27-1 -> -0.39010989 | BM23: =BA23/BA27-1 -> -0.32144382 | BN23: =BB23/BB27-1 -> -0.87840436 | BO23: =BC23/BC27-1 -> 6.0382883 | BP23: =BD23/BD27-1 -> -0.65080751 | BQ23: =BE23/BE27-1 -> -0.50596638 | ... BU23: =BI23/BI27-1 -> -0.18680677 | BV23: {=_xll.ciqfunctions.udf.CIQ(B$3,$BV$1,$BV$2,$A23,"L",,"USD","H")/100} -> -0.107276 | BW23: {=_xll.ciqfunctions.udf.CIQ(C$3,$BV$1,$BV$2,$A23,"L",,"USD","H")/100} -> -0.387944 | BX23: {=_xll.ciqfunctions.udf.CIQ(D$3,$BV$1,$BV$2,$A23,"L",,"USD","H")/100} -> -0.071996 | BY23: {=_xll.ciqfunctions.udf.CIQ(E$3,$BV$1,$BV$2,$A23,"L",,"USD","H")/100} -> 0.0176 | BZ23: {=_xll.ciqfunctions.udf.CIQ(F$3,$BV$1,$BV$2,$A23,"L",,"USD","H")/100} -> 0.007208 | CA23: {=_xll.ciqfunctions.udf.CIQ(G$3,$BV$1,$BV$2,$A23,"L",,"USD","H")/100} -> -0.074916 | CB23: {=_xll.ciqfunctions.udf.CIQ(B$3,$BV$1,$CB$2,$A23,"L",,"USD","H")/100} -> -0.093559 | CC23: {=_xll.ciqfunctions.udf.CIQ(C$3,$BV$1,$CB$2,$A23,"L",,"USD","H")/100} -> -0.152646 | CD23: {=_xll.ciqfunctions.udf.CIQ(D$3,$BV$1,$CB$2,$A23,"L",,"USD","H")/100} -> -0.085117 | CE23: {=_xll.ciqfunctions.udf.CIQ(E$3,$BV$1,$CB$2,$A23,"L",,"USD","H")/100} -> -0.052168 | CF23: {=_xll.ciqfunctions.udf.CIQ(F$3,$BV$1,$CB$2,$A23,"L",,"USD","H")/100} -> -0.154174 | CG23: {=_xll.ciqfunctions.udf.CIQ(G$3,$BV$1,$CB$2,$A23,"L",,"USD","H")/100} -> -0.314733
A24: =EDATE(A20,-12) -> 44104 | B24: {=_xll.ciqfunctions.udf.CIQ(B$3,$B$1,$B$2,$A24,"L",,"USD","H")} -> 4421 | C24: {=_xll.ciqfunctions.udf.CIQ(C$3,$B$1,$B$2,$A24,"L",,"USD","H")} -> 45696 | D24: {=_xll.ciqfunctions.udf.CIQ(D$3,$B$1,$B$2,$A24,"L",,"USD","H")} -> 23997 | E24: {=_xll.ciqfunctions.udf.CIQ(E$3,$B$1,$B$2,$A24,"L",,"USD","H")} -> 2321 | F24: {=_xll.ciqfunctions.udf.CIQ(F$3,$B$1,$B$2,$A24,"L",,"USD","H")} -> 26172 | G24: {=_xll.ciqfunctions.udf.CIQ(G$3,$B$1,$B$2,$A24,"L",,"USD","H")} -> 1154 | H24: {=_xll.ciqfunctions.udf.CIQ(B$3,$B$1,$H$2,$A24,"L",,"USD","H")} -> 21475 | I24: {=_xll.ciqfunctions.udf.CIQ(C$3,$B$1,$H$2,$A24,"L",,"USD","H")} -> 195877 | J24: {=_xll.ciqfunctions.udf.CIQ(D$3,$B$1,$H$2,$A24,"L",,"USD","H")} -> 96411 | K24: {=_xll.ciqfunctions.udf.CIQ(E$3,$B$1,$H$2,$A24,"L",,"USD","H")} -> 11295.63 | L24: {=_xll.ciqfunctions.udf.CIQ(F$3,$B$1,$H$2,$A24,"L",,"USD","H")} -> 149126 | M24: {=_xll.ciqfunctions.udf.CIQ(G$3,$B$1,$H$2,$A24,"L",,"USD","H")} -> 4789 | N24: {=_xll.ciqfunctions.udf.CIQ(B$3,$N$1,$B$2,$A24,"L",,"USD","H")} -> -45.0535 | O24: {=_xll.ciqfunctions.udf.CIQ(C$3,$N$1,$B$2,$A24,"L",,"USD","H")} -> -28.4357 | P24: {=_xll.ciqfunctions.udf.CIQ(D$3,$N$1,$B$2,$A24,"L",,"USD","H")} -> -31.0015 | Q24: {=_xll.ciqfunctions.udf.CIQ(E$3,$N$1,$B$2,$A24,"L",,"USD","H")} -> -44.975 | R24: {=_xll.ciqfunctions.udf.CIQ(F$3,$N$1,$B$2,$A24,"L",,"USD","H")} -> -61.4841 | S24: {=_xll.ciqfunctions.udf.CIQ(G$3,$N$1,$B$2,$A24,"L",,"USD","H")} -> -26.0731 | T24: 45912 | U24: {=_xll.ciqfunctions.udf.CIQ(O$3,$N$1,$T$2,$A24,"L",,"USD","H")} -> -25.1676 | V24: {=_xll.ciqfunctions.udf.CIQ(P$3,$N$1,$T$2,$A24,"L",,"USD","H")} -> -30.0194 | W24: {=_xll.ciqfunctions.udf.CIQ(Q$3,$N$1,$T$2,$A24,"L",,"USD","H")} -> -34.236 | X24: {=_xll.ciqfunctions.udf.CIQ(R$3,$N$1,$T$2,$A24,"L",,"USD","H")} -> -47.0516 | Y24: {=_xll.ciqfunctions.udf.CIQ(S$3,$N$1,$T$2,$A24,"L",,"USD","H")} -> -37.6352 | Z24: {=_xll.ciqfunctions.udf.CIQ(B$3,$Z$1,$B$2,$A24,"L",,"USD","H")} -> -450 | AA24: {=_xll.ciqfunctions.udf.CIQ(C$3,$Z$1,$B$2,$A24,"L",,"USD","H")} -> -680 | AB24: {=_xll.ciqfunctions.udf.CIQ(D$3,$Z$1,$B$2,$A24,"L",,"USD","H")} -> -207 | AC24: {=_xll.ciqfunctions.udf.CIQ(E$3,$Z$1,$B$2,$A24,"L",,"USD","H")} -> -42 | AD24: {=_xll.ciqfunctions.udf.CIQ(F$3,$Z$1,$B$2,$A24,"L",,"USD","H")} -> -450 | AE24: {=_xll.ciqfunctions.udf.CIQ(G$3,$Z$1,$B$2,$A24,"L",,"USD","H")} -> -92 | AF24: {=_xll.ciqfunctions.udf.CIQ(B$3,$Z$1,$H$2,$A24,"L",,"USD","H")} -> -1209 | AG24: {=_xll.ciqfunctions.udf.CIQ(C$3,$Z$1,$H$2,$A24,"L",,"USD","H")} -> 3320 | AH24: {=_xll.ciqfunctions.udf.CIQ(D$3,$Z$1,$H$2,$A24,"L",,"USD","H")} -> -11488 | AI24: {=_xll.ciqfunctions.udf.CIQ(E$3,$Z$1,$H$2,$A24,"L",,"USD","H")} -> -305.479 | AJ24: {=_xll.ciqfunctions.udf.CIQ(F$3,$Z$1,$H$2,$A24,"L",,"USD","H")} -> -21644 | AK24: {=_xll.ciqfunctions.udf.CIQ(G$3,$Z$1,$H$2,$A24,"L",,"USD","H")} -> -3220 | AL24: {=_xll.ciqfunctions.udf.CIQ(B$3,$AL$1,$AL$2,$A24,"L",,"USD","H")} -> NM | AM24: {=_xll.ciqfunctions.udf.CIQ(C$3,$AL$1,$AL$2,$A24,"L",,"USD","H")} -> NM | AN24: {=_xll.ciqfunctions.udf.CIQ(D$3,$AL$1,$AL$2,$A24,"L",,"USD","H")} -> NM | AO24: {=_xll.ciqfunctions.udf.CIQ(E$3,$AL$1,$AL$2,$A24,"L",,"USD","H")} -> NM | AP24: {=_xll.ciqfunctions.udf.CIQ(F$3,$AL$1,$AL$2,$A24,"L",,"USD","H")} -> NM | AQ24: {=_xll.ciqfunctions.udf.CIQ(G$3,$AL$1,$AL$2,$A24,"L",,"USD","H")} -> NM | AR24: {=_xll.ciqfunctions.udf.CIQ(B$3,$AL$1,$AR$2,$A24,"L",,"USD","H")} -> NM | AS24: {=_xll.ciqfunctions.udf.CIQ(C$3,$AL$1,$AR$2,$A24,"L",,"USD","H")} -> -77.3379 | AT24: {=_xll.ciqfunctions.udf.CIQ(D$3,$AL$1,$AR$2,$A24,"L",,"USD","H")} -> NM | AU24: {=_xll.ciqfunctions.udf.CIQ(E$3,$AL$1,$AR$2,$A24,"L",,"USD","H")} -> NM | AV24: {=_xll.ciqfunctions.udf.CIQ(F$3,$AL$1,$AR$2,$A24,"L",,"USD","H")} -> NM | AW24: {=_xll.ciqfunctions.udf.CIQ(G$3,$AL$1,$AR$2,$A24,"L",,"USD","H")} -> NM | AX24: {=_xll.ciqfunctions.udf.CIQ(B$3,$AX$1,$AX$2,$A24,"L",,"USD","H")} -> 1136 | AY24: {=_xll.ciqfunctions.udf.CIQ(C$3,$AX$1,$AX$2,$A24,"L",,"USD","H")} -> 3351 | AZ24: {=_xll.ciqfunctions.udf.CIQ(D$3,$AX$1,$AX$2,$A24,"L",,"USD","H")} -> 3689 | BA24: {=_xll.ciqfunctions.udf.CIQ(E$3,$AX$1,$AX$2,$A24,"L",,"USD","H")} -> 970 | BB24: {=_xll.ciqfunctions.udf.CIQ(F$3,$AX$1,$AX$2,$A24,"L",,"USD","H")} -> 4810 | BC24: {=_xll.ciqfunctions.udf.CIQ(G$3,$AX$1,$AX$2,$A24,"L",,"USD","H")} -> 240 | BD24: {=_xll.ciqfunctions.udf.CIQ(B$3,$AX$1,$BD$2,$A24,"L",,"USD","H")} -> 6548 | BE24: {=_xll.ciqfunctions.udf.CIQ(C$3,$AX$1,$BD$2,$A24,"L",,"USD","H")} -> 19148 | BF24: {=_xll.ciqfunctions.udf.CIQ(D$3,$AX$1,$BD$2,$A24,"L",,"USD","H")} -> 15761 | BG24: =_xll.ciqfunctions.udf.CIQ("COP", "IQ_PRICEDATE", "8/22/2025") -> 45891 | BH24: {=_xll.ciqfunctions.udf.CIQ(F$3,$AX$1,$BD$2,$A24,"L",,"USD","H")} -> 17717 | BI24: {=_xll.ciqfunctions.udf.CIQ(G$3,$AX$1,$BD$2,$A24,"L",,"USD","H")} -> 1525 | BJ24: =AX24/AX28-1 -> -0.66079427 | BK24: =AY24/AY28-1 -> -0.61170336 | BL24: =AZ24/AZ28-1 -> -0.49257221 | BM24: =BA24/BA28-1 -> -0.45569192 | BN24: =BB24/BB28-1 -> -0.3741054 | BO24: =BC24/BC28-1 -> -0.63246554 | BP24: =BD24/BD28-1 -> -0.54866281 | BQ24: =BE24/BE28-1 -> -0.43355816 | ... BU24: =BI24/BI28-1 -> -0.48962517 | BV24: {=_xll.ciqfunctions.udf.CIQ(B$3,$BV$1,$BV$2,$A24,"L",,"USD","H")/100} -> -0.078044 | BW24: {=_xll.ciqfunctions.udf.CIQ(C$3,$BV$1,$BV$2,$A24,"L",,"USD","H")/100} -> -0.068944 | BX24: {=_xll.ciqfunctions.udf.CIQ(D$3,$BV$1,$BV$2,$A24,"L",,"USD","H")/100} -> -0.061964 | BY24: {=_xll.ciqfunctions.udf.CIQ(E$3,$BV$1,$BV$2,$A24,"L",,"USD","H")/100} -> -0.039472 | BZ24: {=_xll.ciqfunctions.udf.CIQ(F$3,$BV$1,$BV$2,$A24,"L",,"USD","H")/100} -> -0.036344 | CA24: {=_xll.ciqfunctions.udf.CIQ(G$3,$BV$1,$BV$2,$A24,"L",,"USD","H")/100} -> -0.069216 | CB24: {=_xll.ciqfunctions.udf.CIQ(B$3,$BV$1,$CB$2,$A24,"L",,"USD","H")/100} -> -0.062573 | CC24: {=_xll.ciqfunctions.udf.CIQ(C$3,$BV$1,$CB$2,$A24,"L",,"USD","H")/100} -> -0.045871 | CD24: {=_xll.ciqfunctions.udf.CIQ(D$3,$BV$1,$CB$2,$A24,"L",,"USD","H")/100} -> -0.115911 | CE24: {=_xll.ciqfunctions.udf.CIQ(E$3,$BV$1,$CB$2,$A24,"L",,"USD","H")/100} -> -0.040297 | CF24: {=_xll.ciqfunctions.udf.CIQ(F$3,$BV$1,$CB$2,$A24,"L",,"USD","H")/100} -> -0.170711 | CG24: {=_xll.ciqfunctions.udf.CIQ(G$3,$BV$1,$CB$2,$A24,"L",,"USD","H")/100} -> -0.358867
A25: =EDATE(A21,-12) -> 44012 | B25: {=_xll.ciqfunctions.udf.CIQ(B$3,$B$1,$B$2,$A25,"L",,"USD","H")} -> 2826 | C25: {=_xll.ciqfunctions.udf.CIQ(C$3,$B$1,$B$2,$A25,"L",,"USD","H")} -> 32502 | D25: {=_xll.ciqfunctions.udf.CIQ(D$3,$B$1,$B$2,$A25,"L",,"USD","H")} -> 15926 | E25: {=_xll.ciqfunctions.udf.CIQ(E$3,$B$1,$B$2,$A25,"L",,"USD","H")} -> 1216 | F25: {=_xll.ciqfunctions.udf.CIQ(F$3,$B$1,$B$2,$A25,"L",,"USD","H")} -> 21138 | G25: {=_xll.ciqfunctions.udf.CIQ(G$3,$B$1,$B$2,$A25,"L",,"USD","H")} -> 713 | H25: {=_xll.ciqfunctions.udf.CIQ(B$3,$B$1,$H$2,$A25,"L",,"USD","H")} -> 25100 | I25: {=_xll.ciqfunctions.udf.CIQ(C$3,$B$1,$H$2,$A25,"L",,"USD","H")} -> 214034 | J25: {=_xll.ciqfunctions.udf.CIQ(D$3,$B$1,$H$2,$A25,"L",,"USD","H")} -> 107193 | K25: {=_xll.ciqfunctions.udf.CIQ(E$3,$B$1,$H$2,$A25,"L",,"USD","H")} -> 13192.706 | L25: {=_xll.ciqfunctions.udf.CIQ(F$3,$B$1,$H$2,$A25,"L",,"USD","H")} -> 190905 | M25: {=_xll.ciqfunctions.udf.CIQ(G$3,$B$1,$H$2,$A25,"L",,"USD","H")} -> 5196 | N25: {=_xll.ciqfunctions.udf.CIQ(B$3,$N$1,$B$2,$A25,"L",,"USD","H")} -> -65.2228 | O25: {=_xll.ciqfunctions.udf.CIQ(C$3,$N$1,$B$2,$A25,"L",,"USD","H")} -> -52.0139 | P25: {=_xll.ciqfunctions.udf.CIQ(D$3,$N$1,$B$2,$A25,"L",,"USD","H")} -> -56.1546 | Q25: {=_xll.ciqfunctions.udf.CIQ(E$3,$N$1,$B$2,$A25,"L",,"USD","H")} -> -73.0516 | R25: {=_xll.ciqfunctions.udf.CIQ(F$3,$N$1,$B$2,$A25,"L",,"USD","H")} -> -70.7656 | S25: {=_xll.ciqfunctions.udf.CIQ(G$3,$N$1,$B$2,$A25,"L",,"USD","H")} -> -55.4932 | T25: 45905 | U25: {=_xll.ciqfunctions.udf.CIQ(O$3,$N$1,$T$2,$A25,"L",,"USD","H")} -> -21.3365 | V25: {=_xll.ciqfunctions.udf.CIQ(P$3,$N$1,$T$2,$A25,"L",,"USD","H")} -> -26.1217 | W25: {=_xll.ciqfunctions.udf.CIQ(Q$3,$N$1,$T$2,$A25,"L",,"USD","H")} -> -25.3624 | X25: {=_xll.ciqfunctions.udf.CIQ(R$3,$N$1,$T$2,$A25,"L",,"USD","H")} -> -34.7802 | Y25: {=_xll.ciqfunctions.udf.CIQ(S$3,$N$1,$T$2,$A25,"L",,"USD","H")} -> -36.5878 | Z25: {=_xll.ciqfunctions.udf.CIQ(B$3,$Z$1,$B$2,$A25,"L",,"USD","H")} -> 260 | AA25: {=_xll.ciqfunctions.udf.CIQ(C$3,$Z$1,$B$2,$A25,"L",,"USD","H")} -> -1080 | AB25: {=_xll.ciqfunctions.udf.CIQ(D$3,$Z$1,$B$2,$A25,"L",,"USD","H")} -> -8270 | AC25: {=_xll.ciqfunctions.udf.CIQ(E$3,$Z$1,$B$2,$A25,"L",,"USD","H")} -> -910 | AD25: {=_xll.ciqfunctions.udf.CIQ(F$3,$Z$1,$B$2,$A25,"L",,"USD","H")} -> -16848 | AE25: {=_xll.ciqfunctions.udf.CIQ(G$3,$Z$1,$B$2,$A25,"L",,"USD","H")} -> -670 | AF25: {=_xll.ciqfunctions.udf.CIQ(B$3,$Z$1,$H$2,$A25,"L",,"USD","H")} -> 2297 | AG25: {=_xll.ciqfunctions.udf.CIQ(C$3,$Z$1,$H$2,$A25,"L",,"USD","H")} -> 7170 | AH25: {=_xll.ciqfunctions.udf.CIQ(D$3,$Z$1,$H$2,$A25,"L",,"USD","H")} -> -8701 | AI25: {=_xll.ciqfunctions.udf.CIQ(E$3,$Z$1,$H$2,$A25,"L",,"USD","H")} -> 351.643 | AJ25: {=_xll.ciqfunctions.udf.CIQ(F$3,$Z$1,$H$2,$A25,"L",,"USD","H")} -> -21943 | AK25: {=_xll.ciqfunctions.udf.CIQ(G$3,$Z$1,$H$2,$A25,"L",,"USD","H")} -> -3019 | AL25: {=_xll.ciqfunctions.udf.CIQ(B$3,$AL$1,$AL$2,$A25,"L",,"USD","H")} -> -83.5444 | AM25: {=_xll.ciqfunctions.udf.CIQ(C$3,$AL$1,$AL$2,$A25,"L",,"USD","H")} -> NM | AN25: {=_xll.ciqfunctions.udf.CIQ(D$3,$AL$1,$AL$2,$A25,"L",,"USD","H")} -> NM | AO25: {=_xll.ciqfunctions.udf.CIQ(E$3,$AL$1,$AL$2,$A25,"L",,"USD","H")} -> NM | AP25: {=_xll.ciqfunctions.udf.CIQ(F$3,$AL$1,$AL$2,$A25,"L",,"USD","H")} -> NM | AQ25: {=_xll.ciqfunctions.udf.CIQ(G$3,$AL$1,$AL$2,$A25,"L",,"USD","H")} -> NM | AR25: {=_xll.ciqfunctions.udf.CIQ(B$3,$AL$1,$AR$2,$A25,"L",,"USD","H")} -> -67.8382 | AS25: {=_xll.ciqfunctions.udf.CIQ(C$3,$AL$1,$AR$2,$A25,"L",,"USD","H")} -> -59.5373 | AT25: {=_xll.ciqfunctions.udf.CIQ(D$3,$AL$1,$AR$2,$A25,"L",,"USD","H")} -> NM | AU25: {=_xll.ciqfunctions.udf.CIQ(E$3,$AL$1,$AR$2,$A25,"L",,"USD","H")} -> -90.1418 | AV25: {=_xll.ciqfunctions.udf.CIQ(F$3,$AL$1,$AR$2,$A25,"L",,"USD","H")} -> NM | AW25: {=_xll.ciqfunctions.udf.CIQ(G$3,$AL$1,$AR$2,$A25,"L",,"USD","H")} -> NM | AX25: {=_xll.ciqfunctions.udf.CIQ(B$3,$AX$1,$AX$2,$A25,"L",,"USD","H")} -> 199 | AY25: {=_xll.ciqfunctions.udf.CIQ(C$3,$AX$1,$AX$2,$A25,"L",,"USD","H")} -> 4101 | AZ25: {=_xll.ciqfunctions.udf.CIQ(D$3,$AX$1,$AX$2,$A25,"L",,"USD","H")} -> -1279 | BA25: {=_xll.ciqfunctions.udf.CIQ(E$3,$AX$1,$AX$2,$A25,"L",,"USD","H")} -> -89 | BB25: {=_xll.ciqfunctions.udf.CIQ(F$3,$AX$1,$AX$2,$A25,"L",,"USD","H")} -> 4990 | BC25: {=_xll.ciqfunctions.udf.CIQ(G$3,$AX$1,$AX$2,$A25,"L",,"USD","H")} -> -304 | BD25: {=_xll.ciqfunctions.udf.CIQ(B$3,$AX$1,$BD$2,$A25,"L",,"USD","H")} -> 8694 | BE25: {=_xll.ciqfunctions.udf.CIQ(C$3,$AX$1,$BD$2,$A25,"L",,"USD","H")} -> 24427 | BF25: {=_xll.ciqfunctions.udf.CIQ(D$3,$AX$1,$BD$2,$A25,"L",,"USD","H")} -> 19342 | BG25: =_xll.ciqfunctions.udf.CIQ("COP", "IQ_PRICEDATE", "8/15/2025") -> 45884 | BH25: {=_xll.ciqfunctions.udf.CIQ(F$3,$AX$1,$BD$2,$A25,"L",,"USD","H")} -> 20592 | BI25: {=_xll.ciqfunctions.udf.CIQ(G$3,$AX$1,$BD$2,$A25,"L",,"USD","H")} -> 1943 | BJ25: =AX25/AX29-1 -> -0.94384876 | BK25: =AY25/AY29-1 -> -0.49495074 | BL25: =AZ25/AZ29-1 -> -1.161144 | BM25: =BA25/BA29-1 -> -1.0427871 | BN25: =BB25/BB29-1 -> -0.41301023 | BO25: =BC25/BC29-1 -> -1.4537313 | BP25: =BD25/BD29-1 -> -0.44443734 | BQ25: =BE25/BE29-1 -> -0.33430534 | ... BU25: =BI25/BI29-1 -> -0.29139314 | BV25: {=_xll.ciqfunctions.udf.CIQ(B$3,$BV$1,$BV$2,$A25,"L",,"USD","H")/100} -> -0.0168 | BW25: {=_xll.ciqfunctions.udf.CIQ(C$3,$BV$1,$BV$2,$A25,"L",,"USD","H")/100} -> -0.075956 | BX25: {=_xll.ciqfunctions.udf.CIQ(D$3,$BV$1,$BV$2,$A25,"L",,"USD","H")/100} -> -0.246776 | BY25: {=_xll.ciqfunctions.udf.CIQ(E$3,$BV$1,$BV$2,$A25,"L",,"USD","H")/100} -> -0.1689 | BZ25: {=_xll.ciqfunctions.udf.CIQ(F$3,$BV$1,$BV$2,$A25,"L",,"USD","H")/100} -> -0.450132 | CA25: {=_xll.ciqfunctions.udf.CIQ(G$3,$BV$1,$BV$2,$A25,"L",,"USD","H")/100} -> -0.345232 | CB25: {=_xll.ciqfunctions.udf.CIQ(B$3,$BV$1,$CB$2,$A25,"L",,"USD","H")/100} -> 0.012142 | CC25: {=_xll.ciqfunctions.udf.CIQ(C$3,$BV$1,$CB$2,$A25,"L",,"USD","H")/100} -> -0.03043 | CD25: {=_xll.ciqfunctions.udf.CIQ(D$3,$BV$1,$CB$2,$A25,"L",,"USD","H")/100} -> -0.099626 | CE25: {=_xll.ciqfunctions.udf.CIQ(E$3,$BV$1,$CB$2,$A25,"L",,"USD","H")/100} -> -0.013781 | CF25: {=_xll.ciqfunctions.udf.CIQ(F$3,$BV$1,$CB$2,$A25,"L",,"USD","H")/100} -> -0.170992 | CG25: {=_xll.ciqfunctions.udf.CIQ(G$3,$BV$1,$CB$2,$A25,"L",,"USD","H")/100} -> -0.324479
A26: =EDATE(A22,-12) -> 43921 | B26: {=_xll.ciqfunctions.udf.CIQ(B$3,$B$1,$B$2,$A26,"L",,"USD","H")} -> 6392 | C26: {=_xll.ciqfunctions.udf.CIQ(C$3,$B$1,$B$2,$A26,"L",,"USD","H")} -> 55383 | D26: {=_xll.ciqfunctions.udf.CIQ(D$3,$B$1,$B$2,$A26,"L",,"USD","H")} -> 29705 | E26: {=_xll.ciqfunctions.udf.CIQ(E$3,$B$1,$B$2,$A26,"L",,"USD","H")} -> 3496 | F26: {=_xll.ciqfunctions.udf.CIQ(F$3,$B$1,$B$2,$A26,"L",,"USD","H")} -> 30770 | G26: {=_xll.ciqfunctions.udf.CIQ(G$3,$B$1,$B$2,$A26,"L",,"USD","H")} -> 1286 | H26: {=_xll.ciqfunctions.udf.CIQ(B$3,$B$1,$H$2,$A26,"L",,"USD","H")} -> 30400 | I26: {=_xll.ciqfunctions.udf.CIQ(C$3,$B$1,$H$2,$A26,"L",,"USD","H")} -> 249264 | J26: {=_xll.ciqfunctions.udf.CIQ(D$3,$B$1,$H$2,$A26,"L",,"USD","H")} -> 127590 | K26: {=_xll.ciqfunctions.udf.CIQ(E$3,$B$1,$H$2,$A26,"L",,"USD","H")} -> 16489.027 | L26: {=_xll.ciqfunctions.udf.CIQ(F$3,$B$1,$H$2,$A26,"L",,"USD","H")} -> 242072 | M26: {=_xll.ciqfunctions.udf.CIQ(G$3,$B$1,$H$2,$A26,"L",,"USD","H")} -> 6085 | N26: {=_xll.ciqfunctions.udf.CIQ(B$3,$N$1,$B$2,$A26,"L",,"USD","H")} -> -31.5486 | O26: {=_xll.ciqfunctions.udf.CIQ(C$3,$N$1,$B$2,$A26,"L",,"USD","H")} -> -10.5514 | P26: {=_xll.ciqfunctions.udf.CIQ(D$3,$N$1,$B$2,$A26,"L",,"USD","H")} -> -13.1154 | Q26: {=_xll.ciqfunctions.udf.CIQ(E$3,$N$1,$B$2,$A26,"L",,"USD","H")} -> -14.378 | R26: {=_xll.ciqfunctions.udf.CIQ(F$3,$N$1,$B$2,$A26,"L",,"USD","H")} -> -53.306 | S26: {=_xll.ciqfunctions.udf.CIQ(G$3,$N$1,$B$2,$A26,"L",,"USD","H")} -> -20.8129 | T26: 45898 | U26: {=_xll.ciqfunctions.udf.CIQ(O$3,$N$1,$T$2,$A26,"L",,"USD","H")} -> -9.6254 | V26: {=_xll.ciqfunctions.udf.CIQ(P$3,$N$1,$T$2,$A26,"L",,"USD","H")} -> -14.5195 | W26: {=_xll.ciqfunctions.udf.CIQ(Q$3,$N$1,$T$2,$A26,"L",,"USD","H")} -> -6.2785 | X26: {=_xll.ciqfunctions.udf.CIQ(R$3,$N$1,$T$2,$A26,"L",,"USD","H")} -> -18.0287 | Y26: {=_xll.ciqfunctions.udf.CIQ(S$3,$N$1,$T$2,$A26,"L",,"USD","H")} -> -27.9882 | Z26: {=_xll.ciqfunctions.udf.CIQ(B$3,$Z$1,$B$2,$A26,"L",,"USD","H")} -> -1739 | AA26: {=_xll.ciqfunctions.udf.CIQ(C$3,$Z$1,$B$2,$A26,"L",,"USD","H")} -> -610 | AB26: {=_xll.ciqfunctions.udf.CIQ(D$3,$Z$1,$B$2,$A26,"L",,"USD","H")} -> 3599 | AC26: {=_xll.ciqfunctions.udf.CIQ(E$3,$Z$1,$B$2,$A26,"L",,"USD","H")} -> 10 | AD26: {=_xll.ciqfunctions.udf.CIQ(F$3,$Z$1,$B$2,$A26,"L",,"USD","H")} -> -4365 | AE26: {=_xll.ciqfunctions.udf.CIQ(G$3,$Z$1,$B$2,$A26,"L",,"USD","H")} -> -1816 | AF26: {=_xll.ciqfunctions.udf.CIQ(B$3,$Z$1,$H$2,$A26,"L",,"USD","H")} -> 3617 | AG26: {=_xll.ciqfunctions.udf.CIQ(C$3,$Z$1,$H$2,$A26,"L",,"USD","H")} -> 11380 | AH26: {=_xll.ciqfunctions.udf.CIQ(D$3,$Z$1,$H$2,$A26,"L",,"USD","H")} -> 3874 | AI26: {=_xll.ciqfunctions.udf.CIQ(E$3,$Z$1,$H$2,$A26,"L",,"USD","H")} -> 2109.484 | AJ26: {=_xll.ciqfunctions.udf.CIQ(F$3,$Z$1,$H$2,$A26,"L",,"USD","H")} -> -3273 | AK26: {=_xll.ciqfunctions.udf.CIQ(G$3,$Z$1,$H$2,$A26,"L",,"USD","H")} -> -1854 | AL26: {=_xll.ciqfunctions.udf.CIQ(B$3,$AL$1,$AL$2,$A26,"L",,"USD","H")} -> NM | AM26: {=_xll.ciqfunctions.udf.CIQ(C$3,$AL$1,$AL$2,$A26,"L",,"USD","H")} -> NM | AN26: {=_xll.ciqfunctions.udf.CIQ(D$3,$AL$1,$AL$2,$A26,"L",,"USD","H")} -> 35.8625 | AO26: {=_xll.ciqfunctions.udf.CIQ(E$3,$AL$1,$AL$2,$A26,"L",,"USD","H")} -> -98.4263 | AP26: {=_xll.ciqfunctions.udf.CIQ(F$3,$AL$1,$AL$2,$A26,"L",,"USD","H")} -> NM | AQ26: {=_xll.ciqfunctions.udf.CIQ(G$3,$AL$1,$AL$2,$A26,"L",,"USD","H")} -> NM | AR26: {=_xll.ciqfunctions.udf.CIQ(B$3,$AL$1,$AR$2,$A26,"L",,"USD","H")} -> -49.7779 | AS26: {=_xll.ciqfunctions.udf.CIQ(C$3,$AL$1,$AR$2,$A26,"L",,"USD","H")} -> -38.6193 | AT26: {=_xll.ciqfunctions.udf.CIQ(D$3,$AL$1,$AR$2,$A26,"L",,"USD","H")} -> -71.9986 | AU26: {=_xll.ciqfunctions.udf.CIQ(E$3,$AL$1,$AR$2,$A26,"L",,"USD","H")} -> -38.2448 | AV26: {=_xll.ciqfunctions.udf.CIQ(F$3,$AL$1,$AR$2,$A26,"L",,"USD","H")} -> NM | AW26: {=_xll.ciqfunctions.udf.CIQ(G$3,$AL$1,$AR$2,$A26,"L",,"USD","H")} -> NM | AX26: {=_xll.ciqfunctions.udf.CIQ(B$3,$AX$1,$AX$2,$A26,"L",,"USD","H")} -> 2096 | AY26: {=_xll.ciqfunctions.udf.CIQ(C$3,$AX$1,$AX$2,$A26,"L",,"USD","H")} -> 5035 | AZ26: {=_xll.ciqfunctions.udf.CIQ(D$3,$AX$1,$AX$2,$A26,"L",,"USD","H")} -> 6799 | BA26: {=_xll.ciqfunctions.udf.CIQ(E$3,$AX$1,$AX$2,$A26,"L",,"USD","H")} -> 2615 | BB26: {=_xll.ciqfunctions.udf.CIQ(F$3,$AX$1,$AX$2,$A26,"L",,"USD","H")} -> 1675 | BC26: {=_xll.ciqfunctions.udf.CIQ(G$3,$AX$1,$AX$2,$A26,"L",,"USD","H")} -> 1145 | BD26: {=_xll.ciqfunctions.udf.CIQ(B$3,$AX$1,$BD$2,$A26,"L",,"USD","H")} -> 12073 | BE26: {=_xll.ciqfunctions.udf.CIQ(C$3,$AX$1,$BD$2,$A26,"L",,"USD","H")} -> 28446 | BF26: {=_xll.ciqfunctions.udf.CIQ(D$3,$AX$1,$BD$2,$A26,"L",,"USD","H")} -> 28558 | BG26: =_xll.ciqfunctions.udf.CIQ("COP", "IQ_PRICEDATE", "8/8/2025") -> 45877 | BH26: {=_xll.ciqfunctions.udf.CIQ(F$3,$AX$1,$BD$2,$A26,"L",,"USD","H")} -> 23988 | BI26: {=_xll.ciqfunctions.udf.CIQ(G$3,$AX$1,$BD$2,$A26,"L",,"USD","H")} -> 2917 | BJ26: =AX26/AX30-1 -> -0.44388432 | BK26: =AY26/AY30-1 -> -0.31328423 | BL26: =AZ26/AZ30-1 -> -0.064143152 | BM26: =BA26/BA30-1 -> 0.48582838 | BN26: =BB26/BB30-1 -> -0.82403614 | BO26: =BC26/BC30-1 -> -20.40678 | BP26: =BD26/BD30-1 -> -0.23506304 | BQ26: =BE26/BE30-1 -> -0.24700214 | ... BU26: =BI26/BI30-1 -> 0.26277056 | BV26: {=_xll.ciqfunctions.udf.CIQ(B$3,$BV$1,$BV$2,$A26,"L",,"USD","H")/100} -> -0.180752 | BW26: {=_xll.ciqfunctions.udf.CIQ(C$3,$BV$1,$BV$2,$A26,"L",,"USD","H")/100} -> -0.069252 | BX26: {=_xll.ciqfunctions.udf.CIQ(D$3,$BV$1,$BV$2,$A26,"L",,"USD","H")/100} -> 0.0271 | BY26: {=_xll.ciqfunctions.udf.CIQ(E$3,$BV$1,$BV$2,$A26,"L",,"USD","H")/100} -> -0.022988 | BZ26: {=_xll.ciqfunctions.udf.CIQ(F$3,$BV$1,$BV$2,$A26,"L",,"USD","H")/100} -> -0.14904 | CA26: {=_xll.ciqfunctions.udf.CIQ(G$3,$BV$1,$BV$2,$A26,"L",,"USD","H")/100} -> -0.776128 | CB26: {=_xll.ciqfunctions.udf.CIQ(B$3,$BV$1,$CB$2,$A26,"L",,"USD","H")/100} -> 0.042182 | CC26: {=_xll.ciqfunctions.udf.CIQ(C$3,$BV$1,$CB$2,$A26,"L",,"USD","H")/100} -> -0.014203 | CD26: {=_xll.ciqfunctions.udf.CIQ(D$3,$BV$1,$CB$2,$A26,"L",,"USD","H")/100} -> -0.028294 | CE26: {=_xll.ciqfunctions.udf.CIQ(E$3,$BV$1,$CB$2,$A26,"L",,"USD","H")/100} -> 0.054958 | CF26: {=_xll.ciqfunctions.udf.CIQ(F$3,$BV$1,$CB$2,$A26,"L",,"USD","H")/100} -> -0.062457 | CG26: {=_xll.ciqfunctions.udf.CIQ(G$3,$BV$1,$CB$2,$A26,"L",,"USD","H")/100} -> -0.176444
A27: =EDATE(A23,-12) -> 43830 | B27: {=_xll.ciqfunctions.udf.CIQ(B$3,$B$1,$B$2,$A27,"L",,"USD","H")} -> 7836 | C27: {=_xll.ciqfunctions.udf.CIQ(C$3,$B$1,$B$2,$A27,"L",,"USD","H")} -> 62296 | D27: {=_xll.ciqfunctions.udf.CIQ(D$3,$B$1,$B$2,$A27,"L",,"USD","H")} -> 26783 | E27: {=_xll.ciqfunctions.udf.CIQ(E$3,$B$1,$B$2,$A27,"L",,"USD","H")} -> 4262.63 | F27: {=_xll.ciqfunctions.udf.CIQ(F$3,$B$1,$B$2,$A27,"L",,"USD","H")} -> 71046 | G27: {=_xll.ciqfunctions.udf.CIQ(G$3,$B$1,$B$2,$A27,"L",,"USD","H")} -> 1636 | H27: {=_xll.ciqfunctions.udf.CIQ(B$3,$B$1,$H$2,$A27,"L",,"USD","H")} -> 33346 | I27: {=_xll.ciqfunctions.udf.CIQ(C$3,$B$1,$H$2,$A27,"L",,"USD","H")} -> 259497 | J27: {=_xll.ciqfunctions.udf.CIQ(D$3,$B$1,$H$2,$A27,"L",,"USD","H")} -> 139365 | K27: {=_xll.ciqfunctions.udf.CIQ(E$3,$B$1,$H$2,$A27,"L",,"USD","H")} -> 17076 | L27: {=_xll.ciqfunctions.udf.CIQ(F$3,$B$1,$H$2,$A27,"L",,"USD","H")} -> 158109 | M27: {=_xll.ciqfunctions.udf.CIQ(G$3,$B$1,$H$2,$A27,"L",,"USD","H")} -> 6674 | N27: {=_xll.ciqfunctions.udf.CIQ(B$3,$N$1,$B$2,$A27,"L",,"USD","H")} -> -21.4279 | O27: {=_xll.ciqfunctions.udf.CIQ(C$3,$N$1,$B$2,$A27,"L",,"USD","H")} -> -8.7279 | P27: {=_xll.ciqfunctions.udf.CIQ(D$3,$N$1,$B$2,$A27,"L",,"USD","H")} -> -17.5325 | Q27: {=_xll.ciqfunctions.udf.CIQ(E$3,$N$1,$B$2,$A27,"L",,"USD","H")} -> -2.2902 | R27: {=_xll.ciqfunctions.udf.CIQ(F$3,$N$1,$B$2,$A27,"L",,"USD","H")} -> -5.8882 | S27: {=_xll.ciqfunctions.udf.CIQ(G$3,$N$1,$B$2,$A27,"L",,"USD","H")} -> -43.4302 | T27: 45891 | U27: {=_xll.ciqfunctions.udf.CIQ(O$3,$N$1,$T$2,$A27,"L",,"USD","H")} -> -7.6721 | V27: {=_xll.ciqfunctions.udf.CIQ(P$3,$N$1,$T$2,$A27,"L",,"USD","H")} -> -7.7304 | W27: {=_xll.ciqfunctions.udf.CIQ(Q$3,$N$1,$T$2,$A27,"L",,"USD","H")} -> -1.1032 | X27: {=_xll.ciqfunctions.udf.CIQ(R$3,$N$1,$T$2,$A27,"L",,"USD","H")} -> -46.8601 | Y27: {=_xll.ciqfunctions.udf.CIQ(S$3,$N$1,$T$2,$A27,"L",,"USD","H")} -> -20.9149 | Z27: {=_xll.ciqfunctions.udf.CIQ(B$3,$Z$1,$B$2,$A27,"L",,"USD","H")} -> 720 | AA27: {=_xll.ciqfunctions.udf.CIQ(C$3,$Z$1,$B$2,$A27,"L",,"USD","H")} -> 5690 | AB27: {=_xll.ciqfunctions.udf.CIQ(D$3,$Z$1,$B$2,$A27,"L",,"USD","H")} -> -6610 | AC27: {=_xll.ciqfunctions.udf.CIQ(E$3,$Z$1,$B$2,$A27,"L",,"USD","H")} -> 636.521 | AD27: {=_xll.ciqfunctions.udf.CIQ(F$3,$Z$1,$B$2,$A27,"L",,"USD","H")} -> 19 | AE27: {=_xll.ciqfunctions.udf.CIQ(G$3,$Z$1,$B$2,$A27,"L",,"USD","H")} -> -642 | AF27: {=_xll.ciqfunctions.udf.CIQ(B$3,$Z$1,$H$2,$A27,"L",,"USD","H")} -> 7189 | AG27: {=_xll.ciqfunctions.udf.CIQ(C$3,$Z$1,$H$2,$A27,"L",,"USD","H")} -> 14340 | AH27: {=_xll.ciqfunctions.udf.CIQ(D$3,$Z$1,$H$2,$A27,"L",,"USD","H")} -> 2924 | AI27: {=_xll.ciqfunctions.udf.CIQ(E$3,$Z$1,$H$2,$A27,"L",,"USD","H")} -> 2735 | AJ27: {=_xll.ciqfunctions.udf.CIQ(F$3,$Z$1,$H$2,$A27,"L",,"USD","H")} -> 4026 | AK27: {=_xll.ciqfunctions.udf.CIQ(G$3,$Z$1,$H$2,$A27,"L",,"USD","H")} -> -355 | AL27: {=_xll.ciqfunctions.udf.CIQ(B$3,$AL$1,$AL$2,$A27,"L",,"USD","H")} -> -61.4562 | AM27: {=_xll.ciqfunctions.udf.CIQ(C$3,$AL$1,$AL$2,$A27,"L",,"USD","H")} -> -5.1667 | AN27: {=_xll.ciqfunctions.udf.CIQ(D$3,$AL$1,$AL$2,$A27,"L",,"USD","H")} -> NM | AO27: {=_xll.ciqfunctions.udf.CIQ(E$3,$AL$1,$AL$2,$A27,"L",,"USD","H")} -> -28.7026 | AP27: {=_xll.ciqfunctions.udf.CIQ(F$3,$AL$1,$AL$2,$A27,"L",,"USD","H")} -> -97.5196 | AQ27: {=_xll.ciqfunctions.udf.CIQ(G$3,$AL$1,$AL$2,$A27,"L",,"USD","H")} -> NM | AR27: {=_xll.ciqfunctions.udf.CIQ(B$3,$AL$1,$AR$2,$A27,"L",,"USD","H")} -> 14.8953 | AS27: {=_xll.ciqfunctions.udf.CIQ(C$3,$AL$1,$AR$2,$A27,"L",,"USD","H")} -> -31.1901 | AT27: {=_xll.ciqfunctions.udf.CIQ(D$3,$AL$1,$AR$2,$A27,"L",,"USD","H")} -> -80.2753 | AU27: {=_xll.ciqfunctions.udf.CIQ(E$3,$AL$1,$AR$2,$A27,"L",,"USD","H")} -> -20.0068 | AV27: {=_xll.ciqfunctions.udf.CIQ(F$3,$AL$1,$AR$2,$A27,"L",,"USD","H")} -> -57.0927 | AW27: {=_xll.ciqfunctions.udf.CIQ(G$3,$AL$1,$AR$2,$A27,"L",,"USD","H")} -> NM | AX27: {=_xll.ciqfunctions.udf.CIQ(B$3,$AX$1,$AX$2,$A27,"L",,"USD","H")} -> 3117 | AY27: {=_xll.ciqfunctions.udf.CIQ(C$3,$AX$1,$AX$2,$A27,"L",,"USD","H")} -> 6661 | AZ27: {=_xll.ciqfunctions.udf.CIQ(D$3,$AX$1,$AX$2,$A27,"L",,"USD","H")} -> 6552 | BA27: {=_xll.ciqfunctions.udf.CIQ(E$3,$AX$1,$AX$2,$A27,"L",,"USD","H")} -> 2220.892 | BB27: {=_xll.ciqfunctions.udf.CIQ(F$3,$AX$1,$AX$2,$A27,"L",,"USD","H")} -> 6242 | BC27: {=_xll.ciqfunctions.udf.CIQ(G$3,$AX$1,$AX$2,$A27,"L",,"USD","H")} -> 444 | BD27: {=_xll.ciqfunctions.udf.CIQ(B$3,$AX$1,$BD$2,$A27,"L",,"USD","H")} -> 13746 | BE27: {=_xll.ciqfunctions.udf.CIQ(C$3,$AX$1,$BD$2,$A27,"L",,"USD","H")} -> 34443 | BF27: {=_xll.ciqfunctions.udf.CIQ(D$3,$AX$1,$BD$2,$A27,"L",,"USD","H")} -> 29024 | BG27: =_xll.ciqfunctions.udf.CIQ("COP", "IQ_PRICEDATE", "8/1/2025") -> 45870 | BH27: {=_xll.ciqfunctions.udf.CIQ(F$3,$AX$1,$BD$2,$A27,"L",,"USD","H")} -> 34073 | BI27: {=_xll.ciqfunctions.udf.CIQ(G$3,$AX$1,$BD$2,$A27,"L",,"USD","H")} -> 1713 | BJ27: =AX27/AX31-1 -> -0.19644238 | BK27: =AY27/AY31-1 -> -0.31485291 | BL27: =AZ27/AZ31-1 -> -0.24350537 | BM27: =BA27/BA31-1 -> 0.035242853 | BN27: =BB27/BB31-1 -> -0.10930365 | BO27: =BC27/BC31-1 -> -0.7417103 | BP27: =BD27/BD31-1 -> -0.12362129 | BQ27: =BE27/BE31-1 -> -0.1662713 | ... BU27: =BI27/BI31-1 -> -0.39852528 | BV27: {=_xll.ciqfunctions.udf.CIQ(B$3,$BV$1,$BV$2,$A27,"L",,"USD","H")/100} -> 0.020188 | BW27: {=_xll.ciqfunctions.udf.CIQ(C$3,$BV$1,$BV$2,$A27,"L",,"USD","H")/100} -> 0.031476 | BX27: {=_xll.ciqfunctions.udf.CIQ(D$3,$BV$1,$BV$2,$A27,"L",,"USD","H")/100} -> -0.191156 | BY27: {=_xll.ciqfunctions.udf.CIQ(E$3,$BV$1,$BV$2,$A27,"L",,"USD","H")/100} -> 0.068508 | BZ27: {=_xll.ciqfunctions.udf.CIQ(F$3,$BV$1,$BV$2,$A27,"L",,"USD","H")/100} -> -0.046528 | CA27: {=_xll.ciqfunctions.udf.CIQ(G$3,$BV$1,$BV$2,$A27,"L",,"USD","H")/100} -> -0.25066 | CB27: {=_xll.ciqfunctions.udf.CIQ(B$3,$BV$1,$CB$2,$A27,"L",,"USD","H")/100} -> 0.116209 | CC27: {=_xll.ciqfunctions.udf.CIQ(C$3,$BV$1,$CB$2,$A27,"L",,"USD","H")/100} -> -0.001278 | CD27: {=_xll.ciqfunctions.udf.CIQ(D$3,$BV$1,$CB$2,$A27,"L",,"USD","H")/100} -> -0.032963 | CE27: {=_xll.ciqfunctions.udf.CIQ(E$3,$BV$1,$CB$2,$A27,"L",,"USD","H")/100} -> 0.080922 | CF27: {=_xll.ciqfunctions.udf.CIQ(F$3,$BV$1,$CB$2,$A27,"L",,"USD","H")/100} -> -0.016902 | CG27: {=_xll.ciqfunctions.udf.CIQ(G$3,$BV$1,$CB$2,$A27,"L",,"USD","H")/100} -> -0.041053
A28: =EDATE(A24,-12) -> 43738 | B28: {=_xll.ciqfunctions.udf.CIQ(B$3,$B$1,$B$2,$A28,"L",,"USD","H")} -> 8046 | C28: {=_xll.ciqfunctions.udf.CIQ(C$3,$B$1,$B$2,$A28,"L",,"USD","H")} -> 63853 | D28: {=_xll.ciqfunctions.udf.CIQ(D$3,$B$1,$B$2,$A28,"L",,"USD","H")} -> 34779 | E28: {=_xll.ciqfunctions.udf.CIQ(E$3,$B$1,$B$2,$A28,"L",,"USD","H")} -> 4218.076 | F28: {=_xll.ciqfunctions.udf.CIQ(F$3,$B$1,$B$2,$A28,"L",,"USD","H")} -> 67951 | G28: {=_xll.ciqfunctions.udf.CIQ(G$3,$B$1,$B$2,$A28,"L",,"USD","H")} -> 1561 | H28: {=_xll.ciqfunctions.udf.CIQ(B$3,$B$1,$H$2,$A28,"L",,"USD","H")} -> 35483 | I28: {=_xll.ciqfunctions.udf.CIQ(C$3,$B$1,$H$2,$A28,"L",,"USD","H")} -> 261754 | J28: {=_xll.ciqfunctions.udf.CIQ(D$3,$B$1,$H$2,$A28,"L",,"USD","H")} -> 137768 | K28: {=_xll.ciqfunctions.udf.CIQ(E$3,$B$1,$H$2,$A28,"L",,"USD","H")} -> 17175.992 | L28: {=_xll.ciqfunctions.udf.CIQ(F$3,$B$1,$H$2,$A28,"L",,"USD","H")} -> 281644 | M28: {=_xll.ciqfunctions.udf.CIQ(G$3,$B$1,$H$2,$A28,"L",,"USD","H")} -> 7679 | N28: {=_xll.ciqfunctions.udf.CIQ(B$3,$N$1,$B$2,$A28,"L",,"USD","H")} -> -17.4177 | O28: {=_xll.ciqfunctions.udf.CIQ(C$3,$N$1,$B$2,$A28,"L",,"USD","H")} -> -13.9297 | P28: {=_xll.ciqfunctions.udf.CIQ(D$3,$N$1,$B$2,$A28,"L",,"USD","H")} -> -17.3994 | Q28: {=_xll.ciqfunctions.udf.CIQ(E$3,$N$1,$B$2,$A28,"L",,"USD","H")} -> -10.5916 | R28: {=_xll.ciqfunctions.udf.CIQ(F$3,$N$1,$B$2,$A28,"L",,"USD","H")} -> -14.0046 | S28: {=_xll.ciqfunctions.udf.CIQ(G$3,$N$1,$B$2,$A28,"L",,"USD","H")} -> -24.8074 | T28: 45884 | U28: {=_xll.ciqfunctions.udf.CIQ(O$3,$N$1,$T$2,$A28,"L",,"USD","H")} -> -5.2958 | V28: {=_xll.ciqfunctions.udf.CIQ(P$3,$N$1,$T$2,$A28,"L",,"USD","H")} -> -9.9974 | W28: {=_xll.ciqfunctions.udf.CIQ(Q$3,$N$1,$T$2,$A28,"L",,"USD","H")} -> 5.0221 | X28: {=_xll.ciqfunctions.udf.CIQ(R$3,$N$1,$T$2,$A28,"L",,"USD","H")} -> -2.5568 | Y28: {=_xll.ciqfunctions.udf.CIQ(S$3,$N$1,$T$2,$A28,"L",,"USD","H")} -> -5.0099 | Z28: {=_xll.ciqfunctions.udf.CIQ(B$3,$Z$1,$B$2,$A28,"L",,"USD","H")} -> 3056 | AA28: {=_xll.ciqfunctions.udf.CIQ(C$3,$Z$1,$B$2,$A28,"L",,"USD","H")} -> 3170 | AB28: {=_xll.ciqfunctions.udf.CIQ(D$3,$Z$1,$B$2,$A28,"L",,"USD","H")} -> 2580 | AC28: {=_xll.ciqfunctions.udf.CIQ(E$3,$Z$1,$B$2,$A28,"L",,"USD","H")} -> 615.122 | AD28: {=_xll.ciqfunctions.udf.CIQ(F$3,$Z$1,$B$2,$A28,"L",,"USD","H")} -> -749 | AE28: {=_xll.ciqfunctions.udf.CIQ(G$3,$Z$1,$B$2,$A28,"L",,"USD","H")} -> 109 | AF28: {=_xll.ciqfunctions.udf.CIQ(B$3,$Z$1,$H$2,$A28,"L",,"USD","H")} -> 8337 | AG28: {=_xll.ciqfunctions.udf.CIQ(C$3,$Z$1,$H$2,$A28,"L",,"USD","H")} -> 14650 | AH28: {=_xll.ciqfunctions.udf.CIQ(D$3,$Z$1,$H$2,$A28,"L",,"USD","H")} -> 13264 | AI28: {=_xll.ciqfunctions.udf.CIQ(E$3,$Z$1,$H$2,$A28,"L",,"USD","H")} -> 2991.157 | AJ28: {=_xll.ciqfunctions.udf.CIQ(F$3,$Z$1,$H$2,$A28,"L",,"USD","H")} -> 4773 | AK28: {=_xll.ciqfunctions.udf.CIQ(G$3,$Z$1,$H$2,$A28,"L",,"USD","H")} -> 1436 | AL28: {=_xll.ciqfunctions.udf.CIQ(B$3,$AL$1,$AL$2,$A28,"L",,"USD","H")} -> 64.2127 | AM28: {=_xll.ciqfunctions.udf.CIQ(C$3,$AL$1,$AL$2,$A28,"L",,"USD","H")} -> -49.1988 | AN28: {=_xll.ciqfunctions.udf.CIQ(D$3,$AL$1,$AL$2,$A28,"L",,"USD","H")} -> -36.2491 | AO28: {=_xll.ciqfunctions.udf.CIQ(E$3,$AL$1,$AL$2,$A28,"L",,"USD","H")} -> -48.3504 | AP28: {=_xll.ciqfunctions.udf.CIQ(F$3,$AL$1,$AL$2,$A28,"L",,"USD","H")} -> NM | AQ28: {=_xll.ciqfunctions.udf.CIQ(G$3,$AL$1,$AL$2,$A28,"L",,"USD","H")} -> -95.7036 | AR28: {=_xll.ciqfunctions.udf.CIQ(B$3,$AL$1,$AR$2,$A28,"L",,"USD","H")} -> 39.695 | AS28: {=_xll.ciqfunctions.udf.CIQ(C$3,$AL$1,$AR$2,$A28,"L",,"USD","H")} -> -36.9079 | AT28: {=_xll.ciqfunctions.udf.CIQ(D$3,$AL$1,$AR$2,$A28,"L",,"USD","H")} -> -6.6245 | AU28: {=_xll.ciqfunctions.udf.CIQ(E$3,$AL$1,$AR$2,$A28,"L",,"USD","H")} -> -39.6548 | AV28: {=_xll.ciqfunctions.udf.CIQ(F$3,$AL$1,$AR$2,$A28,"L",,"USD","H")} -> -44.7826 | AW28: {=_xll.ciqfunctions.udf.CIQ(G$3,$AL$1,$AR$2,$A28,"L",,"USD","H")} -> -31.5539 | AX28: {=_xll.ciqfunctions.udf.CIQ(B$3,$AX$1,$AX$2,$A28,"L",,"USD","H")} -> 3349 | AY28: {=_xll.ciqfunctions.udf.CIQ(C$3,$AX$1,$AX$2,$A28,"L",,"USD","H")} -> 8630 | AZ28: {=_xll.ciqfunctions.udf.CIQ(D$3,$AX$1,$AX$2,$A28,"L",,"USD","H")} -> 7270 | BA28: {=_xll.ciqfunctions.udf.CIQ(E$3,$AX$1,$AX$2,$A28,"L",,"USD","H")} -> 1782.079 | BB28: {=_xll.ciqfunctions.udf.CIQ(F$3,$AX$1,$AX$2,$A28,"L",,"USD","H")} -> 7685 | BC28: {=_xll.ciqfunctions.udf.CIQ(G$3,$AX$1,$AX$2,$A28,"L",,"USD","H")} -> 653 | BD28: {=_xll.ciqfunctions.udf.CIQ(B$3,$AX$1,$BD$2,$A28,"L",,"USD","H")} -> 14508 | BE28: {=_xll.ciqfunctions.udf.CIQ(C$3,$AX$1,$BD$2,$A28,"L",,"USD","H")} -> 33804 | BF28: {=_xll.ciqfunctions.udf.CIQ(D$3,$AX$1,$BD$2,$A28,"L",,"USD","H")} -> 31133 | BG28: =_xll.ciqfunctions.udf.CIQ("COP", "IQ_PRICEDATE", "7/25/2025") -> 45863 | BH28: {=_xll.ciqfunctions.udf.CIQ(F$3,$AX$1,$BD$2,$A28,"L",,"USD","H")} -> 32598 | BI28: {=_xll.ciqfunctions.udf.CIQ(G$3,$AX$1,$BD$2,$A28,"L",,"USD","H")} -> 2988 | BJ28: =AX28/AX32-1 -> -0.21329575 | BK28: =AY28/AY32-1 -> -0.25086806 | BL28: =AZ28/AZ32-1 -> -0.2249467 | BM28: =BA28/BA32-1 -> -0.24280913 | BN28: =BB28/BB32-1 -> -0.17365591 | BO28: =BC28/BC32-1 -> 0.58880779 | BP28: =BD28/BD32-1 -> -0.023161864 | BQ28: =BE28/BE32-1 -> -0.1034373 | ... BU28: =BI28/BI32-1 -> 0.63100437 | BV28: {=_xll.ciqfunctions.udf.CIQ(B$3,$BV$1,$BV$2,$A28,"L",,"USD","H")/100} -> 0.217188 | BW28: {=_xll.ciqfunctions.udf.CIQ(C$3,$BV$1,$BV$2,$A28,"L",,"USD","H")/100} -> -0.008748 | BX28: {=_xll.ciqfunctions.udf.CIQ(D$3,$BV$1,$BV$2,$A28,"L",,"USD","H")/100} -> 0.007108 | BY28: {=_xll.ciqfunctions.udf.CIQ(E$3,$BV$1,$BV$2,$A28,"L",,"USD","H")/100} -> 0.066628 | BZ28: {=_xll.ciqfunctions.udf.CIQ(F$3,$BV$1,$BV$2,$A28,"L",,"USD","H")/100} -> -0.05388 | CA28: {=_xll.ciqfunctions.udf.CIQ(G$3,$BV$1,$BV$2,$A28,"L",,"USD","H")/100} -> 0.02608 | CB28: {=_xll.ciqfunctions.udf.CIQ(B$3,$BV$1,$CB$2,$A28,"L",,"USD","H")/100} -> 0.141697 | CC28: {=_xll.ciqfunctions.udf.CIQ(C$3,$BV$1,$CB$2,$A28,"L",,"USD","H")/100} -> 0.00087 | CD28: {=_xll.ciqfunctions.udf.CIQ(D$3,$BV$1,$CB$2,$A28,"L",,"USD","H")/100} -> 0.022949 | CE28: {=_xll.ciqfunctions.udf.CIQ(E$3,$BV$1,$CB$2,$A28,"L",,"USD","H")/100} -> 0.093714 | CF28: {=_xll.ciqfunctions.udf.CIQ(F$3,$BV$1,$CB$2,$A28,"L",,"USD","H")/100} -> -0.010668 | CG28: {=_xll.ciqfunctions.udf.CIQ(G$3,$BV$1,$CB$2,$A28,"L",,"USD","H")/100} -> 0.099282
A29: =EDATE(A25,-12) -> 43646 | B29: {=_xll.ciqfunctions.udf.CIQ(B$3,$B$1,$B$2,$A29,"L",,"USD","H")} -> 8126 | C29: {=_xll.ciqfunctions.udf.CIQ(C$3,$B$1,$B$2,$A29,"L",,"USD","H")} -> 67732 | D29: {=_xll.ciqfunctions.udf.CIQ(D$3,$B$1,$B$2,$A29,"L",,"USD","H")} -> 36323 | E29: {=_xll.ciqfunctions.udf.CIQ(E$3,$B$1,$B$2,$A29,"L",,"USD","H")} -> 4512.321 | F29: {=_xll.ciqfunctions.udf.CIQ(F$3,$B$1,$B$2,$A29,"L",,"USD","H")} -> 72305 | G29: {=_xll.ciqfunctions.udf.CIQ(G$3,$B$1,$B$2,$A29,"L",,"USD","H")} -> 1602 | H29: {=_xll.ciqfunctions.udf.CIQ(B$3,$B$1,$H$2,$A29,"L",,"USD","H")} -> 37180 | I29: {=_xll.ciqfunctions.udf.CIQ(C$3,$B$1,$H$2,$A29,"L",,"USD","H")} -> 272088 | J29: {=_xll.ciqfunctions.udf.CIQ(D$3,$B$1,$H$2,$A29,"L",,"USD","H")} -> 145094 | K29: {=_xll.ciqfunctions.udf.CIQ(E$3,$B$1,$H$2,$A29,"L",,"USD","H")} -> 17675.677 | L29: {=_xll.ciqfunctions.udf.CIQ(F$3,$B$1,$H$2,$A29,"L",,"USD","H")} -> 292710 | M29: {=_xll.ciqfunctions.udf.CIQ(G$3,$B$1,$H$2,$A29,"L",,"USD","H")} -> 8194 | N29: {=_xll.ciqfunctions.udf.CIQ(B$3,$N$1,$B$2,$A29,"L",,"USD","H")} -> -7.3327 | O29: {=_xll.ciqfunctions.udf.CIQ(C$3,$N$1,$B$2,$A29,"L",,"USD","H")} -> -5.2116 | P29: {=_xll.ciqfunctions.udf.CIQ(D$3,$N$1,$B$2,$A29,"L",,"USD","H")} -> -10.2937 | Q29: {=_xll.ciqfunctions.udf.CIQ(E$3,$N$1,$B$2,$A29,"L",,"USD","H")} -> 1.8518 | R29: {=_xll.ciqfunctions.udf.CIQ(F$3,$N$1,$B$2,$A29,"L",,"USD","H")} -> -3.475 | S29: {=_xll.ciqfunctions.udf.CIQ(G$3,$N$1,$B$2,$A29,"L",,"USD","H")} -> -13.7783 | T29: 45877 | U29: {=_xll.ciqfunctions.udf.CIQ(O$3,$N$1,$T$2,$A29,"L",,"USD","H")} -> 4.0274 | V29: {=_xll.ciqfunctions.udf.CIQ(P$3,$N$1,$T$2,$A29,"L",,"USD","H")} -> 1.4707 | W29: {=_xll.ciqfunctions.udf.CIQ(Q$3,$N$1,$T$2,$A29,"L",,"USD","H")} -> 23.6362 | X29: {=_xll.ciqfunctions.udf.CIQ(R$3,$N$1,$T$2,$A29,"L",,"USD","H")} -> 8.5775 | Y29: {=_xll.ciqfunctions.udf.CIQ(S$3,$N$1,$T$2,$A29,"L",,"USD","H")} -> 3.7872 | Z29: {=_xll.ciqfunctions.udf.CIQ(B$3,$Z$1,$B$2,$A29,"L",,"USD","H")} -> 1580 | AA29: {=_xll.ciqfunctions.udf.CIQ(C$3,$Z$1,$B$2,$A29,"L",,"USD","H")} -> 3130 | AB29: {=_xll.ciqfunctions.udf.CIQ(D$3,$Z$1,$B$2,$A29,"L",,"USD","H")} -> 4305 | AC29: {=_xll.ciqfunctions.udf.CIQ(E$3,$Z$1,$B$2,$A29,"L",,"USD","H")} -> 847.841 | AD29: {=_xll.ciqfunctions.udf.CIQ(F$3,$Z$1,$B$2,$A29,"L",,"USD","H")} -> 1822 | AE29: {=_xll.ciqfunctions.udf.CIQ(G$3,$Z$1,$B$2,$A29,"L",,"USD","H")} -> 495 | AF29: {=_xll.ciqfunctions.udf.CIQ(B$3,$Z$1,$H$2,$A29,"L",,"USD","H")} -> 7142 | AG29: {=_xll.ciqfunctions.udf.CIQ(C$3,$Z$1,$H$2,$A29,"L",,"USD","H")} -> 17720 | AH29: {=_xll.ciqfunctions.udf.CIQ(D$3,$Z$1,$H$2,$A29,"L",,"USD","H")} -> 14731 | AI29: {=_xll.ciqfunctions.udf.CIQ(E$3,$Z$1,$H$2,$A29,"L",,"USD","H")} -> 3566.987 | AJ29: {=_xll.ciqfunctions.udf.CIQ(F$3,$Z$1,$H$2,$A29,"L",,"USD","H")} -> 8871 | AK29: {=_xll.ciqfunctions.udf.CIQ(G$3,$Z$1,$H$2,$A29,"L",,"USD","H")} -> 3864 | AL29: {=_xll.ciqfunctions.udf.CIQ(B$3,$AL$1,$AL$2,$A29,"L",,"USD","H")} -> -3.6586 | AM29: {=_xll.ciqfunctions.udf.CIQ(C$3,$AL$1,$AL$2,$A29,"L",,"USD","H")} -> -20.7595 | AN29: {=_xll.ciqfunctions.udf.CIQ(D$3,$AL$1,$AL$2,$A29,"L",,"USD","H")} -> 26.2833 | AO29: {=_xll.ciqfunctions.udf.CIQ(E$3,$AL$1,$AL$2,$A29,"L",,"USD","H")} -> 21.6884 | AP29: {=_xll.ciqfunctions.udf.CIQ(F$3,$AL$1,$AL$2,$A29,"L",,"USD","H")} -> -34.9054 | AQ29: {=_xll.ciqfunctions.udf.CIQ(G$3,$AL$1,$AL$2,$A29,"L",,"USD","H")} -> NM | AR29: {=_xll.ciqfunctions.udf.CIQ(B$3,$AL$1,$AR$2,$A29,"L",,"USD","H")} -> 57.7645 | AS29: {=_xll.ciqfunctions.udf.CIQ(C$3,$AL$1,$AR$2,$A29,"L",,"USD","H")} -> -15.4177 | AT29: {=_xll.ciqfunctions.udf.CIQ(D$3,$AL$1,$AR$2,$A29,"L",,"USD","H")} -> 21.6432 | AU29: {=_xll.ciqfunctions.udf.CIQ(E$3,$AL$1,$AR$2,$A29,"L",,"USD","H")} -> -7.7423 | AV29: {=_xll.ciqfunctions.udf.CIQ(F$3,$AL$1,$AR$2,$A29,"L",,"USD","H")} -> 25.5804 | AW29: {=_xll.ciqfunctions.udf.CIQ(G$3,$AL$1,$AR$2,$A29,"L",,"USD","H")} -> NM | AX29: {=_xll.ciqfunctions.udf.CIQ(B$3,$AX$1,$AX$2,$A29,"L",,"USD","H")} -> 3544 | AY29: {=_xll.ciqfunctions.udf.CIQ(C$3,$AX$1,$AX$2,$A29,"L",,"USD","H")} -> 8120 | AZ29: {=_xll.ciqfunctions.udf.CIQ(D$3,$AX$1,$AX$2,$A29,"L",,"USD","H")} -> 7937 | BA29: {=_xll.ciqfunctions.udf.CIQ(E$3,$AX$1,$AX$2,$A29,"L",,"USD","H")} -> 2080.066 | BB29: {=_xll.ciqfunctions.udf.CIQ(F$3,$AX$1,$AX$2,$A29,"L",,"USD","H")} -> 8501 | BC29: {=_xll.ciqfunctions.udf.CIQ(G$3,$AX$1,$AX$2,$A29,"L",,"USD","H")} -> 670 | BD29: {=_xll.ciqfunctions.udf.CIQ(B$3,$AX$1,$BD$2,$A29,"L",,"USD","H")} -> 15649 | BE29: {=_xll.ciqfunctions.udf.CIQ(C$3,$AX$1,$BD$2,$A29,"L",,"USD","H")} -> 36694 | BF29: {=_xll.ciqfunctions.udf.CIQ(D$3,$AX$1,$BD$2,$A29,"L",,"USD","H")} -> 33243 | BG29: =_xll.ciqfunctions.udf.CIQ("COP", "IQ_PRICEDATE", "7/18/2025") -> 45856 | BH29: {=_xll.ciqfunctions.udf.CIQ(F$3,$AX$1,$BD$2,$A29,"L",,"USD","H")} -> 34213 | BI29: {=_xll.ciqfunctions.udf.CIQ(G$3,$AX$1,$BD$2,$A29,"L",,"USD","H")} -> 2742 | BJ29: =AX29/AX33-1 -> -0.047567858 | BK29: =AY29/AY33-1 -> -0.11767902 | BL29: =AZ29/AZ33-1 -> 0.0077450482 | BM29: =BA29/BA33-1 -> 0.11136603 | BN29: =BB29/BB33-1 -> 0.072546051 | BO29: =BC29/BC33-1 -> 1.8151261 | BP29: =BD29/BD33-1 -> 0.23210771 | BQ29: =BE29/BE33-1 -> 0.04816042 | ... BU29: =BI29/BI33-1 -> 0.48296376 | BV29: {=_xll.ciqfunctions.udf.CIQ(B$3,$BV$1,$BV$2,$A29,"L",,"USD","H")/100} -> 0.1008 | BW29: {=_xll.ciqfunctions.udf.CIQ(C$3,$BV$1,$BV$2,$A29,"L",,"USD","H")/100} -> -0.009516 | BX29: {=_xll.ciqfunctions.udf.CIQ(D$3,$BV$1,$BV$2,$A29,"L",,"USD","H")/100} -> 0.042644 | BY29: {=_xll.ciqfunctions.udf.CIQ(E$3,$BV$1,$BV$2,$A29,"L",,"USD","H")/100} -> 0.10748 | BZ29: {=_xll.ciqfunctions.udf.CIQ(F$3,$BV$1,$BV$2,$A29,"L",,"USD","H")/100} -> 0.000952 | CA29: {=_xll.ciqfunctions.udf.CIQ(G$3,$BV$1,$BV$2,$A29,"L",,"USD","H")/100} -> 0.143096 | CB29: {=_xll.ciqfunctions.udf.CIQ(B$3,$BV$1,$CB$2,$A29,"L",,"USD","H")/100} -> 0.120919 | CC29: {=_xll.ciqfunctions.udf.CIQ(C$3,$BV$1,$CB$2,$A29,"L",,"USD","H")/100} -> 0.014445 | CD29: {=_xll.ciqfunctions.udf.CIQ(D$3,$BV$1,$CB$2,$A29,"L",,"USD","H")/100} -> 0.031183 | CE29: {=_xll.ciqfunctions.udf.CIQ(E$3,$BV$1,$CB$2,$A29,"L",,"USD","H")/100} -> 0.121606 | CF29: {=_xll.ciqfunctions.udf.CIQ(F$3,$BV$1,$CB$2,$A29,"L",,"USD","H")/100} -> 0.014629 | CG29: {=_xll.ciqfunctions.udf.CIQ(G$3,$BV$1,$CB$2,$A29,"L",,"USD","H")/100} -> 0.243699
A30: =EDATE(A26,-12) -> 43555 | B30: {=_xll.ciqfunctions.udf.CIQ(B$3,$B$1,$B$2,$A30,"L",,"USD","H")} -> 9338 | C30: {=_xll.ciqfunctions.udf.CIQ(C$3,$B$1,$B$2,$A30,"L",,"USD","H")} -> 61916 | D30: {=_xll.ciqfunctions.udf.CIQ(D$3,$B$1,$B$2,$A30,"L",,"USD","H")} -> 34189 | E30: {=_xll.ciqfunctions.udf.CIQ(E$3,$B$1,$B$2,$A30,"L",,"USD","H")} -> 4083.058 | F30: {=_xll.ciqfunctions.udf.CIQ(F$3,$B$1,$B$2,$A30,"L",,"USD","H")} -> 65897 | G30: {=_xll.ciqfunctions.udf.CIQ(G$3,$B$1,$B$2,$A30,"L",,"USD","H")} -> 1624 | H30: {=_xll.ciqfunctions.udf.CIQ(B$3,$B$1,$H$2,$A30,"L",,"USD","H")} -> 37823 | I30: {=_xll.ciqfunctions.udf.CIQ(C$3,$B$1,$H$2,$A30,"L",,"USD","H")} -> 275812 | J30: {=_xll.ciqfunctions.udf.CIQ(D$3,$B$1,$H$2,$A30,"L",,"USD","H")} -> 149262 | K30: {=_xll.ciqfunctions.udf.CIQ(E$3,$B$1,$H$2,$A30,"L",,"USD","H")} -> 17593.633 | L30: {=_xll.ciqfunctions.udf.CIQ(F$3,$B$1,$H$2,$A30,"L",,"USD","H")} -> 295313 | M30: {=_xll.ciqfunctions.udf.CIQ(G$3,$B$1,$H$2,$A30,"L",,"USD","H")} -> 8450 | N30: {=_xll.ciqfunctions.udf.CIQ(B$3,$N$1,$B$2,$A30,"L",,"USD","H")} -> 3.6864 | O30: {=_xll.ciqfunctions.udf.CIQ(C$3,$N$1,$B$2,$A30,"L",,"USD","H")} -> -5.3794 | P30: {=_xll.ciqfunctions.udf.CIQ(D$3,$N$1,$B$2,$A30,"L",,"USD","H")} -> -4.9461 | Q30: {=_xll.ciqfunctions.udf.CIQ(E$3,$N$1,$B$2,$A30,"L",,"USD","H")} -> 8.7104 | R30: {=_xll.ciqfunctions.udf.CIQ(F$3,$N$1,$B$2,$A30,"L",,"USD","H")} -> -2.8126 | S30: {=_xll.ciqfunctions.udf.CIQ(G$3,$N$1,$B$2,$A30,"L",,"USD","H")} -> -10.8672 | T30: 45870 | U30: {=_xll.ciqfunctions.udf.CIQ(O$3,$N$1,$T$2,$A30,"L",,"USD","H")} -> 12.0622 | V30: {=_xll.ciqfunctions.udf.CIQ(P$3,$N$1,$T$2,$A30,"L",,"USD","H")} -> 11.718 | W30: {=_xll.ciqfunctions.udf.CIQ(Q$3,$N$1,$T$2,$A30,"L",,"USD","H")} -> 40.9951 | X30: {=_xll.ciqfunctions.udf.CIQ(R$3,$N$1,$T$2,$A30,"L",,"USD","H")} -> 17.7286 | Y30: {=_xll.ciqfunctions.udf.CIQ(S$3,$N$1,$T$2,$A30,"L",,"USD","H")} -> 3.5412 | Z30: {=_xll.ciqfunctions.udf.CIQ(B$3,$Z$1,$B$2,$A30,"L",,"USD","H")} -> 1833 | AA30: {=_xll.ciqfunctions.udf.CIQ(C$3,$Z$1,$B$2,$A30,"L",,"USD","H")} -> 2350 | AB30: {=_xll.ciqfunctions.udf.CIQ(D$3,$Z$1,$B$2,$A30,"L",,"USD","H")} -> 2649 | AC30: {=_xll.ciqfunctions.udf.CIQ(E$3,$Z$1,$B$2,$A30,"L",,"USD","H")} -> 635.426 | AD30: {=_xll.ciqfunctions.udf.CIQ(F$3,$Z$1,$B$2,$A30,"L",,"USD","H")} -> 2934 | AE30: {=_xll.ciqfunctions.udf.CIQ(G$3,$Z$1,$B$2,$A30,"L",,"USD","H")} -> -317 | AF30: {=_xll.ciqfunctions.udf.CIQ(B$3,$Z$1,$H$2,$A30,"L",,"USD","H")} -> 7202 | AG30: {=_xll.ciqfunctions.udf.CIQ(C$3,$Z$1,$H$2,$A30,"L",,"USD","H")} -> 18540 | AH30: {=_xll.ciqfunctions.udf.CIQ(D$3,$Z$1,$H$2,$A30,"L",,"USD","H")} -> 13835 | AI30: {=_xll.ciqfunctions.udf.CIQ(E$3,$Z$1,$H$2,$A30,"L",,"USD","H")} -> 3415.877 | AJ30: {=_xll.ciqfunctions.udf.CIQ(F$3,$Z$1,$H$2,$A30,"L",,"USD","H")} -> 9848 | AK30: {=_xll.ciqfunctions.udf.CIQ(G$3,$Z$1,$H$2,$A30,"L",,"USD","H")} -> 2944 | AL30: {=_xll.ciqfunctions.udf.CIQ(B$3,$AL$1,$AL$2,$A30,"L",,"USD","H")} -> 106.4189 | AM30: {=_xll.ciqfunctions.udf.CIQ(C$3,$AL$1,$AL$2,$A30,"L",,"USD","H")} -> -49.4624 | AN30: {=_xll.ciqfunctions.udf.CIQ(D$3,$AL$1,$AL$2,$A30,"L",,"USD","H")} -> -27.1853 | AO30: {=_xll.ciqfunctions.udf.CIQ(E$3,$AL$1,$AL$2,$A30,"L",,"USD","H")} -> -0.4954 | AP30: {=_xll.ciqfunctions.udf.CIQ(F$3,$AL$1,$AL$2,$A30,"L",,"USD","H")} -> 18.8335 | AQ30: {=_xll.ciqfunctions.udf.CIQ(G$3,$AL$1,$AL$2,$A30,"L",,"USD","H")} -> NM | AR30: {=_xll.ciqfunctions.udf.CIQ(B$3,$AL$1,$AR$2,$A30,"L",,"USD","H")} -> NM | AS30: {=_xll.ciqfunctions.udf.CIQ(C$3,$AL$1,$AR$2,$A30,"L",,"USD","H")} -> -8.8944 | AT30: {=_xll.ciqfunctions.udf.CIQ(D$3,$AL$1,$AR$2,$A30,"L",,"USD","H")} -> 36.2919 | AU30: {=_xll.ciqfunctions.udf.CIQ(E$3,$AL$1,$AR$2,$A30,"L",,"USD","H")} -> 6.9918 | AV30: {=_xll.ciqfunctions.udf.CIQ(F$3,$AL$1,$AR$2,$A30,"L",,"USD","H")} -> 123.3613 | AW30: {=_xll.ciqfunctions.udf.CIQ(G$3,$AL$1,$AR$2,$A30,"L",,"USD","H")} -> 639.6984 | AX30: {=_xll.ciqfunctions.udf.CIQ(B$3,$AX$1,$AX$2,$A30,"L",,"USD","H")} -> 3769 | AY30: {=_xll.ciqfunctions.udf.CIQ(C$3,$AX$1,$AX$2,$A30,"L",,"USD","H")} -> 7332 | AZ30: {=_xll.ciqfunctions.udf.CIQ(D$3,$AX$1,$AX$2,$A30,"L",,"USD","H")} -> 7265 | BA30: {=_xll.ciqfunctions.udf.CIQ(E$3,$AX$1,$AX$2,$A30,"L",,"USD","H")} -> 1759.961 | BB30: {=_xll.ciqfunctions.udf.CIQ(F$3,$AX$1,$AX$2,$A30,"L",,"USD","H")} -> 9519 | BC30: {=_xll.ciqfunctions.udf.CIQ(G$3,$AX$1,$AX$2,$A30,"L",,"USD","H")} -> -59 | BD30: {=_xll.ciqfunctions.udf.CIQ(B$3,$AX$1,$BD$2,$A30,"L",,"USD","H")} -> 15783 | BE30: {=_xll.ciqfunctions.udf.CIQ(C$3,$AX$1,$BD$2,$A30,"L",,"USD","H")} -> 37777 | BF30: {=_xll.ciqfunctions.udf.CIQ(D$3,$AX$1,$BD$2,$A30,"L",,"USD","H")} -> 33181 | BG30: =_xll.ciqfunctions.udf.CIQ("COP", "IQ_PRICEDATE", "7/11/2025") -> 45849 | BH30: {=_xll.ciqfunctions.udf.CIQ(F$3,$AX$1,$BD$2,$A30,"L",,"USD","H")} -> 33667 | BI30: {=_xll.ciqfunctions.udf.CIQ(G$3,$AX$1,$BD$2,$A30,"L",,"USD","H")} -> 2310 | BJ30: =AX30/AX34-1 -> 0.024741707 | BK30: =AY30/AY34-1 -> -0.19772404 | BL30: =AZ30/AZ34-1 -> -0.059546926 | BM30: =BA30/BA34-1 -> 0.033594929 | BN30: =BB30/BB34-1 -> 0.18587268 | BO30: =BC30/BC34-1 -> -1.1231733 | BP30: =BD30/BD34-1 -> 0.44242369 | BQ30: =BE30/BE34-1 -> 0.15455379 | ... BU30: =BI30/BI34-1 -> 0.043360434 | BV30: {=_xll.ciqfunctions.udf.CIQ(B$3,$BV$1,$BV$2,$A30,"L",,"USD","H")/100} -> 0.123676 | BW30: {=_xll.ciqfunctions.udf.CIQ(C$3,$BV$1,$BV$2,$A30,"L",,"USD","H")/100} -> -0.019296 | BX30: {=_xll.ciqfunctions.udf.CIQ(D$3,$BV$1,$BV$2,$A30,"L",,"USD","H")/100} -> 0.008448 | BY30: {=_xll.ciqfunctions.udf.CIQ(E$3,$BV$1,$BV$2,$A30,"L",,"USD","H")/100} -> 0.0776 | BZ30: {=_xll.ciqfunctions.udf.CIQ(F$3,$BV$1,$BV$2,$A30,"L",,"USD","H")/100} -> 0.03456 | CA30: {=_xll.ciqfunctions.udf.CIQ(G$3,$BV$1,$BV$2,$A30,"L",,"USD","H")/100} -> -0.10156 | CB30: {=_xll.ciqfunctions.udf.CIQ(B$3,$BV$1,$CB$2,$A30,"L",,"USD","H")/100} -> 0.12057 | CC30: {=_xll.ciqfunctions.udf.CIQ(C$3,$BV$1,$CB$2,$A30,"L",,"USD","H")/100} -> 0.018944 | CD30: {=_xll.ciqfunctions.udf.CIQ(D$3,$BV$1,$CB$2,$A30,"L",,"USD","H")/100} -> 0.027105 | CE30: {=_xll.ciqfunctions.udf.CIQ(E$3,$BV$1,$CB$2,$A30,"L",,"USD","H")/100} -> 0.117456 | CF30: {=_xll.ciqfunctions.udf.CIQ(F$3,$BV$1,$CB$2,$A30,"L",,"USD","H")/100} -> 0.0206 | CG30: {=_xll.ciqfunctions.udf.CIQ(G$3,$BV$1,$CB$2,$A30,"L",,"USD","H")/100} -> 0.148024
A31: =EDATE(A27,-12) -> 43465 | B31: {=_xll.ciqfunctions.udf.CIQ(B$3,$B$1,$B$2,$A31,"L",,"USD","H")} -> 9973 | C31: {=_xll.ciqfunctions.udf.CIQ(C$3,$B$1,$B$2,$A31,"L",,"USD","H")} -> 68253 | D31: {=_xll.ciqfunctions.udf.CIQ(D$3,$B$1,$B$2,$A31,"L",,"USD","H")} -> 32477 | E31: {=_xll.ciqfunctions.udf.CIQ(E$3,$B$1,$B$2,$A31,"L",,"USD","H")} -> 4362.537 | F31: {=_xll.ciqfunctions.udf.CIQ(F$3,$B$1,$B$2,$A31,"L",,"USD","H")} -> 75491 | G31: {=_xll.ciqfunctions.udf.CIQ(G$3,$B$1,$B$2,$A31,"L",,"USD","H")} -> 2892 | H31: {=_xll.ciqfunctions.udf.CIQ(B$3,$B$1,$H$2,$A31,"L",,"USD","H")} -> 37491 | I31: {=_xll.ciqfunctions.udf.CIQ(C$3,$B$1,$H$2,$A31,"L",,"USD","H")} -> 281060 | J31: {=_xll.ciqfunctions.udf.CIQ(D$3,$B$1,$H$2,$A31,"L",,"USD","H")} -> 151041 | K31: {=_xll.ciqfunctions.udf.CIQ(E$3,$B$1,$H$2,$A31,"L",,"USD","H")} -> 17266.477 | L31: {=_xll.ciqfunctions.udf.CIQ(F$3,$B$1,$H$2,$A31,"L",,"USD","H")} -> 297533 | M31: {=_xll.ciqfunctions.udf.CIQ(G$3,$B$1,$H$2,$A31,"L",,"USD","H")} -> 8439 | N31: {=_xll.ciqfunctions.udf.CIQ(B$3,$N$1,$B$2,$A31,"L",,"USD","H")} -> 19.911 | O31: {=_xll.ciqfunctions.udf.CIQ(C$3,$N$1,$B$2,$A31,"L",,"USD","H")} -> 4.503 | P31: {=_xll.ciqfunctions.udf.CIQ(D$3,$N$1,$B$2,$A31,"L",,"USD","H")} -> -5.8829 | Q31: {=_xll.ciqfunctions.udf.CIQ(E$3,$N$1,$B$2,$A31,"L",,"USD","H")} -> 26.425 | R31: {=_xll.ciqfunctions.udf.CIQ(F$3,$N$1,$B$2,$A31,"L",,"USD","H")} -> 12.1625 | S31: {=_xll.ciqfunctions.udf.CIQ(G$3,$N$1,$B$2,$A31,"L",,"USD","H")} -> 24.2268 | T31: 45863 | U31: {=_xll.ciqfunctions.udf.CIQ(O$3,$N$1,$T$2,$A31,"L",,"USD","H")} -> 18.5097 | V31: {=_xll.ciqfunctions.udf.CIQ(P$3,$N$1,$T$2,$A31,"L",,"USD","H")} -> 18.4774 | W31: {=_xll.ciqfunctions.udf.CIQ(Q$3,$N$1,$T$2,$A31,"L",,"USD","H")} -> 52.9687 | X31: {=_xll.ciqfunctions.udf.CIQ(R$3,$N$1,$T$2,$A31,"L",,"USD","H")} -> 24.7868 | Y31: {=_xll.ciqfunctions.udf.CIQ(S$3,$N$1,$T$2,$A31,"L",,"USD","H")} -> 33.1072 | Z31: {=_xll.ciqfunctions.udf.CIQ(B$3,$Z$1,$B$2,$A31,"L",,"USD","H")} -> 1868 | AA31: {=_xll.ciqfunctions.udf.CIQ(C$3,$Z$1,$B$2,$A31,"L",,"USD","H")} -> 6000 | AB31: {=_xll.ciqfunctions.udf.CIQ(D$3,$Z$1,$B$2,$A31,"L",,"USD","H")} -> 3730 | AC31: {=_xll.ciqfunctions.udf.CIQ(E$3,$Z$1,$B$2,$A31,"L",,"USD","H")} -> 892.768 | AD31: {=_xll.ciqfunctions.udf.CIQ(F$3,$Z$1,$B$2,$A31,"L",,"USD","H")} -> 766 | AE31: {=_xll.ciqfunctions.udf.CIQ(G$3,$Z$1,$B$2,$A31,"L",,"USD","H")} -> 1149 | AF31: {=_xll.ciqfunctions.udf.CIQ(B$3,$Z$1,$H$2,$A31,"L",,"USD","H")} -> 6257 | AG31: {=_xll.ciqfunctions.udf.CIQ(C$3,$Z$1,$H$2,$A31,"L",,"USD","H")} -> 20840 | AH31: {=_xll.ciqfunctions.udf.CIQ(D$3,$Z$1,$H$2,$A31,"L",,"USD","H")} -> 14824 | AI31: {=_xll.ciqfunctions.udf.CIQ(E$3,$Z$1,$H$2,$A31,"L",,"USD","H")} -> 3419.04 | AJ31: {=_xll.ciqfunctions.udf.CIQ(F$3,$Z$1,$H$2,$A31,"L",,"USD","H")} -> 9383 | AK31: {=_xll.ciqfunctions.udf.CIQ(G$3,$Z$1,$H$2,$A31,"L",,"USD","H")} -> 3064 | AL31: {=_xll.ciqfunctions.udf.CIQ(B$3,$AL$1,$AL$2,$A31,"L",,"USD","H")} -> 18.3027 | AM31: {=_xll.ciqfunctions.udf.CIQ(C$3,$AL$1,$AL$2,$A31,"L",,"USD","H")} -> -28.401 | AN31: {=_xll.ciqfunctions.udf.CIQ(D$3,$AL$1,$AL$2,$A31,"L",,"USD","H")} -> 19.8971 | AO31: {=_xll.ciqfunctions.udf.CIQ(E$3,$AL$1,$AL$2,$A31,"L",,"USD","H")} -> -63.2677 | AP31: {=_xll.ciqfunctions.udf.CIQ(F$3,$AL$1,$AL$2,$A31,"L",,"USD","H")} -> 2737.037 | AQ31: {=_xll.ciqfunctions.udf.CIQ(G$3,$AL$1,$AL$2,$A31,"L",,"USD","H")} -> 527.8688 | AR31: {=_xll.ciqfunctions.udf.CIQ(B$3,$AL$1,$AR$2,$A31,"L",,"USD","H")} -> NM | AS31: {=_xll.ciqfunctions.udf.CIQ(C$3,$AL$1,$AR$2,$A31,"L",,"USD","H")} -> 5.7331 | AT31: {=_xll.ciqfunctions.udf.CIQ(D$3,$AL$1,$AR$2,$A31,"L",,"USD","H")} -> 61.218 | AU31: {=_xll.ciqfunctions.udf.CIQ(E$3,$AL$1,$AR$2,$A31,"L",,"USD","H")} -> 32.3885 | AV31: {=_xll.ciqfunctions.udf.CIQ(F$3,$AL$1,$AR$2,$A31,"L",,"USD","H")} -> 176.8663 | AW31: {=_xll.ciqfunctions.udf.CIQ(G$3,$AL$1,$AR$2,$A31,"L",,"USD","H")} -> 241.2026 | AX31: {=_xll.ciqfunctions.udf.CIQ(B$3,$AX$1,$AX$2,$A31,"L",,"USD","H")} -> 3879 | AY31: {=_xll.ciqfunctions.udf.CIQ(C$3,$AX$1,$AX$2,$A31,"L",,"USD","H")} -> 9722 | AZ31: {=_xll.ciqfunctions.udf.CIQ(D$3,$AX$1,$AX$2,$A31,"L",,"USD","H")} -> 8661 | BA31: {=_xll.ciqfunctions.udf.CIQ(E$3,$AX$1,$AX$2,$A31,"L",,"USD","H")} -> 2145.286 | BB31: {=_xll.ciqfunctions.udf.CIQ(F$3,$AX$1,$AX$2,$A31,"L",,"USD","H")} -> 7008 | BC31: {=_xll.ciqfunctions.udf.CIQ(G$3,$AX$1,$AX$2,$A31,"L",,"USD","H")} -> 1719 | BD31: {=_xll.ciqfunctions.udf.CIQ(B$3,$AX$1,$BD$2,$A31,"L",,"USD","H")} -> 15685 | BE31: {=_xll.ciqfunctions.udf.CIQ(C$3,$AX$1,$BD$2,$A31,"L",,"USD","H")} -> 41312 | BF31: {=_xll.ciqfunctions.udf.CIQ(D$3,$AX$1,$BD$2,$A31,"L",,"USD","H")} -> 33641 | BG31: =_xll.ciqfunctions.udf.CIQ("COP", "IQ_PRICEDATE", "7/3/2025") -> 45841 | BH31: {=_xll.ciqfunctions.udf.CIQ(F$3,$AX$1,$BD$2,$A31,"L",,"USD","H")} -> 32488 | BI31: {=_xll.ciqfunctions.udf.CIQ(G$3,$AX$1,$BD$2,$A31,"L",,"USD","H")} -> 2848 | BJ31: =AX31/AX35-1 -> 0.27640671 | BK31: =AY31/AY35-1 -> 0.23973476 | BL31: =AZ31/AZ35-1 -> 0.66782207 | BM31: =BA31/BA35-1 -> 0.36094661 | BN31: =BB31/BB35-1 -> 0.048473968 | BO31: =BC31/BC35-1 -> 1.4452347 | BP31: =BD31/BD35-1 -> 0.61767739 | BQ31: =BE31/BE35-1 -> 0.29233272 | ... BU31: =BI31/BI35-1 -> 1.0430416 | BV31: {=_xll.ciqfunctions.udf.CIQ(B$3,$BV$1,$BV$2,$A31,"L",,"USD","H")/100} -> 0.1287 | BW31: {=_xll.ciqfunctions.udf.CIQ(C$3,$BV$1,$BV$2,$A31,"L",,"USD","H")/100} -> 0.042232 | BX31: {=_xll.ciqfunctions.udf.CIQ(D$3,$BV$1,$BV$2,$A31,"L",,"USD","H")/100} -> 0.033816 | BY31: {=_xll.ciqfunctions.udf.CIQ(E$3,$BV$1,$BV$2,$A31,"L",,"USD","H")/100} -> 0.121504 | BZ31: {=_xll.ciqfunctions.udf.CIQ(F$3,$BV$1,$BV$2,$A31,"L",,"USD","H")/100} -> -0.023096 | CA31: {=_xll.ciqfunctions.udf.CIQ(G$3,$BV$1,$BV$2,$A31,"L",,"USD","H")/100} -> 0.311188 | CB31: {=_xll.ciqfunctions.udf.CIQ(B$3,$BV$1,$CB$2,$A31,"L",,"USD","H")/100} -> 0.100352 | CC31: {=_xll.ciqfunctions.udf.CIQ(C$3,$BV$1,$CB$2,$A31,"L",,"USD","H")/100} -> 0.029765 | CD31: {=_xll.ciqfunctions.udf.CIQ(D$3,$BV$1,$CB$2,$A31,"L",,"USD","H")/100} -> 0.033433 | CE31: {=_xll.ciqfunctions.udf.CIQ(E$3,$BV$1,$CB$2,$A31,"L",,"USD","H")/100} -> 0.123904 | CF31: {=_xll.ciqfunctions.udf.CIQ(F$3,$BV$1,$CB$2,$A31,"L",,"USD","H")/100} -> 0.016203 | CG31: {=_xll.ciqfunctions.udf.CIQ(G$3,$BV$1,$CB$2,$A31,"L",,"USD","H")/100} -> 0.168147
